Workbook

Sheet INPUT_VENTA
A2: Mes | B2: Mayo
A3: Nombre prenda
A4: Talla
A5: Propietario prenda
A6: Vendedor
A7: Precio venta (BRUTO)
A8: Tipo de pago
A9: Marca (Tienda/externa)
A10: Observaciones

Sheet Precios
A1: SEASON | C1: $ | D1: nube | F1: $ | G1: SCAMMERS | I1: $ | J1: POP DISASTER | L1: $
A2: SHORTS | D2: HOODIE | F2: 35000 | J2: IDIOT | L2: 25000
A3: PANTALONES | C3: 75000 | D3: POLERON ZIP | F3: 40000 | J3: MILEY | L3: 25000
A4: MANGA LARGA | D4: BUZO | F4: 30000 | J4: RATA FOUNDRY | L4: 25000
A5: BBY TEE | C5: 20000 | D5: JEANS | F5: 42000 | J5: PATOS FOUNDRY | L5: 25000
A6: TAK TOP | C6: 25000 | D6: POLERON JAPON | F6: 36000
D7: POLERA JAPON | F7: 23000
D8: TAKASHI CLOUT | F8: 40000
D9: HOODIE BORDADO (ROJO Y NEGRO) | F9: 40000
D10: NUBENZ | F10: 45000

Sheet Pagos
A1: Pagos y saldos mensuales
A3: Resumen Tienda - Enero
A4: Concepto | B4: Valor (CLP)
A5: Neto total tienda (todas las ventas) | B5: =SUM(Enero!$M$4:Enero!$M$103) -> 0
A6: Neto prendas 'Tienda' (propietario) | B6: =SUMIF(Enero!$C$4:$C$103,"Tienda",Enero!$M$4:$M$103) -> 0
A7: Neto prendas 'Consignacion' (propietario) | B7: =SUMIF(Enero!$C$4:$C$103,"Consignacion",Enero!$M$4:$M$103) -> 0
A8: Total gastos fijos | B8: =Enero!$B$130 -> 1751960
A9: Gasto fijo por integrante (÷5) | B9: =Enero!$B$131 -> 350392
A11: Pagos fundadores - Enero
A12: Integrante | B12: Neto prendas propias | C12: Cuota gastos fijos | D12: Saldo final (a pagar / a depositar) | E12: Reembolso gastos personales
A13: Aaron | B13: =SUMIF(Enero!$C$4:$C$103,A13,Enero!$M$4:$M$103) -> 0 | C13: =$B$9 -> 350392 | D13: =B13-C13+E13 -> -350392 | E13: =SUMIFS(Gastos_Personales!$D:$D,Gastos_Personales!$E:$E,A13,Gastos_Personales!$A:$A,"Enero") -> 0
A14: Benja R | B14: =SUMIF(Enero!$C$4:$C$103,A14,Enero!$M$4:$M$103) -> 0 | C14: =$B$9 -> 350392 | D14: =B14-C14+E14 -> -350392 | E14: =SUMIFS(Gastos_Personales!$D:$D,Gastos_Personales!$E:$E,A14,Gastos_Personales!$A:$A,"Enero") -> 0
A15: Benja M | B15: =SUMIF(Enero!$C$4:$C$103,A15,Enero!$M$4:$M$103) -> 0 | C15: =$B$9 -> 350392 | D15: =B15-C15+E15 -> -350392 | E15: =SUMIFS(Gastos_Personales!$D:$D,Gastos_Personales!$E:$E,A15,Gastos_Personales!$A:$A,"Enero") -> 0
A16: Juanito | B16: =SUMIF(Enero!$C$4:$C$103,A16,Enero!$M$4:$M$103) -> 0 | C16: =$B$9 -> 350392 | D16: =B16-C16+E16 -> -350392 | E16: =SUMIFS(Gastos_Personales!$D:$D,Gastos_Personales!$E:$E,A16,Gastos_Personales!$A:$A,"Enero") -> 0
A17: Fabio | B17: =SUMIF(Enero!$C$4:$C$103,A17,Enero!$M$4:$M$103) -> 0 | C17: =$B$9 -> 350392 | D17: =B17-C17+E17 -> -350392 | E17: =SUMIFS(Gastos_Personales!$D:$D,Gastos_Personales!$E:$E,A17,Gastos_Personales!$A:$A,"Enero") -> 0
A19: Marcas externas - Enero
A20: Marca | B20: Ventas brutas marca | C20: Base comisión tienda (neto base) | D20: % comisión tienda | E20: Comisión tienda ($) | F20: IVA total marca
A21: =Marcas!$A$2 -> Nube | B21: =IF(A21="","",SUMIF(Enero!$O$4:$O$103,A21,Enero!$E$4:$E$103)) -> 0 | C21: =IF(A21="","",SUMIF(Enero!$O$4:$O$103,A21,Enero!$J$4:$J$103)) -> 0 | D21: =IF(A21="","",Marcas!$B$2) -> 0.25 | E21: =IF(A21="","",C21*D21) -> 0 | F21: =IF(A21="","",SUMIF(Enero!$O$4:$O$103,A21,Enero!$G$4:$G$103)) -> 0
A22: =Marcas!$A$3 -> Season Archive | B22: =IF(A22="","",SUMIF(Enero!$O$4:$O$103,A22,Enero!$E$4:$E$103)) -> 0 | C22: =IF(A22="","",SUMIF(Enero!$O$4:$O$103,A22,Enero!$J$4:$J$103)) -> 0 | D22: =IF(A22="","",Marcas!$B$3) -> 0.25 | E22: =IF(A22="","",C22*D22) -> 0 | F22: =IF(A22="","",SUMIF(Enero!$O$4:$O$103,A22,Enero!$G$4:$G$103)) -> 0
A23: =Marcas!$A$4 -> Gelattos | B23: =IF(A23="","",SUMIF(Enero!$O$4:$O$103,A23,Enero!$E$4:$E$103)) -> 0 | C23: =IF(A23="","",SUMIF(Enero!$O$4:$O$103,A23,Enero!$J$4:$J$103)) -> 0 | D23: =IF(A23="","",Marcas!$B$4) -> 0.25 | E23: =IF(A23="","",C23*D23) -> 0 | F23: =IF(A23="","",SUMIF(Enero!$O$4:$O$103,A23,Enero!$G$4:$G$103)) -> 0
A24: =Marcas!$A$5 -> Tienda | B24: =IF(A24="","",SUMIF(Enero!$O$4:$O$103,A24,Enero!$E$4:$E$103)) -> 0 | C24: =IF(A24="","",SUMIF(Enero!$O$4:$O$103,A24,Enero!$J$4:$J$103)) -> 0 | D24: =IF(A24="","",Marcas!$B$5) -> 0 | E24: =IF(A24="","",C24*D24) -> 0 | F24: =IF(A24="","",SUMIF(Enero!$O$4:$O$103,A24,Enero!$G$4:$G$103)) -> 0
A25: =Marcas!$A$6 -> Pop disaster | B25: =IF(A25="","",SUMIF(Enero!$O$4:$O$103,A25,Enero!$E$4:$E$103)) -> 0 | C25: =IF(A25="","",SUMIF(Enero!$O$4:$O$103,A25,Enero!$J$4:$J$103)) -> 0 | D25: =IF(A25="","",Marcas!$B$6) -> 0.25 | E25: =IF(A25="","",C25*D25) -> 0 | F25: =IF(A25="","",SUMIF(Enero!$O$4:$O$103,A25,Enero!$G$4:$G$103)) -> 0
A26: =Marcas!$A$7 -> Pedritos | B26: =IF(A26="","",SUMIF(Enero!$O$4:$O$103,A26,Enero!$E$4:$E$103)) -> 0 | C26: =IF(A26="","",SUMIF(Enero!$O$4:$O$103,A26,Enero!$J$4:$J$103)) -> 0 | D26: =IF(A26="","",Marcas!$B$7) -> 0.25 | E26: =IF(A26="","",C26*D26) -> 0 | F26: =IF(A26="","",SUMIF(Enero!$O$4:$O$103,A26,Enero!$G$4:$G$103)) -> 0
A27: =Marcas!$A$8 | B27: =IF(A27="","",SUMIF(Enero!$O$4:$O$103,A27,Enero!$E$4:$E$103)) | C27: =IF(A27="","",SUMIF(Enero!$O$4:$O$103,A27,Enero!$J$4:$J$103)) | D27: =IF(A27="","",Marcas!$B$8) | E27: =IF(A27="","",C27*D27) | F27: =IF(A27="","",SUMIF(Enero!$O$4:$O$103,A27,Enero!$G$4:$G$103))
A28: =Marcas!$A$9 | B28: =IF(A28="","",SUMIF(Enero!$O$4:$O$103,A28,Enero!$E$4:$E$103)) | C28: =IF(A28="","",SUMIF(Enero!$O$4:$O$103,A28,Enero!$J$4:$J$103)) | D28: =IF(A28="","",Marcas!$B$9) | E28: =IF(A28="","",C28*D28) | F28: =IF(A28="","",SUMIF(Enero!$O$4:$O$103,A28,Enero!$G$4:$G$103))
A29: =Marcas!$A$10 | B29: =IF(A29="","",SUMIF(Enero!$O$4:$O$103,A29,Enero!$E$4:$E$103)) | C29: =IF(A29="","",SUMIF(Enero!$O$4:$O$103,A29,Enero!$J$4:$J$103)) | D29: =IF(A29="","",Marcas!$B$10) | E29: =IF(A29="","",C29*D29) | F29: =IF(A29="","",SUMIF(Enero!$O$4:$O$103,A29,Enero!$G$4:$G$103))
A30: =Marcas!$A$11 | B30: =IF(A30="","",SUMIF(Enero!$O$4:$O$103,A30,Enero!$E$4:$E$103)) | C30: =IF(A30="","",SUMIF(Enero!$O$4:$O$103,A30,Enero!$J$4:$J$103)) | D30: =IF(A30="","",Marcas!$B$11) | E30: =IF(A30="","",C30*D30) | F30: =IF(A30="","",SUMIF(Enero!$O$4:$O$103,A30,Enero!$G$4:$G$103))
A34: Resumen Tienda - Febrero
A35: Concepto | B35: Valor (CLP)
A36: Neto total tienda (todas las ventas) | B36: =SUM(Febrero!$M$4:Febrero!$M$103) -> 2546018.7
A37: Neto prendas 'Tienda' (propietario) | B37: =SUMIF(Febrero!$C$4:$C$103,"Tienda",Febrero!$M$4:$M$103) -> 727487.89
A38: Neto prendas 'Consignacion' (propietario) | B38: =SUMIF(Febrero!$C$4:$C$103,"Consignacion",Febrero!$M$4:$M$103) -> 363200
A39: Total gastos fijos | B39: =Febrero!$B$130 -> 1751960
A40: Gasto fijo por integrante (÷5) | B40: =Febrero!$B$131 -> 350392
A42: Pagos fundadores - Febrero
A43: Integrante | B43: Neto prendas propias | C43: Cuota gastos fijos | D43: Saldo final (a pagar / a depositar)
A44: Aaron | B44: =SUMIF(Febrero!$C$4:$C$103,A44,Febrero!$M$4:$M$103) -> 186000 | C44: =$B$40 -> 350392 | D44: =B44-C44 -> -164392
A45: Benja R | B45: =SUMIF(Febrero!$C$4:$C$103,A45,Febrero!$M$4:$M$103) -> 969870.8 | C45: =$B$40 -> 350392 | D45: =B45-C45 -> 619478.8
A46: Benja M | B46: =SUMIF(Febrero!$C$4:$C$103,A46,Febrero!$M$4:$M$103) -> 0 | C46: =$B$40 -> 350392 | D46: =B46-C46 -> -350392
A47: Juanito | B47: =SUMIF(Febrero!$C$4:$C$103,A47,Febrero!$M$4:$M$103) -> 0 | C47: =$B$40 -> 350392 | D47: =B47-C47 -> -350392
A48: Fabio | B48: =SUMIF(Febrero!$C$4:$C$103,A48,Febrero!$M$4:$M$103) -> 299460 | C48: =$B$40 -> 350392 | D48: =B48-C48 -> -50932
A50: Marcas externas - Febrero
A51: Marca | B51: Ventas brutas marca | C51: Base comisión tienda (neto base) | D51: % comisión tienda | E51: Comisión tienda ($) | F51: IVA total marca
A52: =Marcas!$A$2 -> Nube | B52: =IF(A52="","",SUMIF(Febrero!$O$4:$O$103,A52,Febrero!$E$4:$E$103)) -> 0 | C52: =IF(A52="","",SUMIF(Febrero!$O$4:$O$103,A52,Febrero!$J$4:$J$103)) -> 0 | D52: =IF(A52="","",Marcas!$B$2) -> 0.25 | E52: =IF(A52="","",C52*D52) -> 0 | F52: =IF(A52="","",SUMIF(Febrero!$O$4:$O$103,A52,Febrero!$G$4:$G$103)) -> 0
A53: =Marcas!$A$3 -> Season Archive | B53: =IF(A53="","",SUMIF(Febrero!$O$4:$O$103,A53,Febrero!$E$4:$E$103)) -> 0 | C53: =IF(A53="","",SUMIF(Febrero!$O$4:$O$103,A53,Febrero!$J$4:$J$103)) -> 0 | D53: =IF(A53="","",Marcas!$B$3) -> 0.25 | E53: =IF(A53="","",C53*D53) -> 0 | F53: =IF(A53="","",SUMIF(Febrero!$O$4:$O$103,A53,Febrero!$G$4:$G$103)) -> 0
A54: =Marcas!$A$4 -> Gelattos | B54: =IF(A54="","",SUMIF(Febrero!$O$4:$O$103,A54,Febrero!$E$4:$E$103)) -> 290000 | C54: =IF(A54="","",SUMIF(Febrero!$O$4:$O$103,A54,Febrero!$J$4:$J$103)) -> 290000 | D54: =IF(A54="","",Marcas!$B$4) -> 0.25 | E54: =IF(A54="","",C54*D54) -> 72500 | F54: =IF(A54="","",SUMIF(Febrero!$O$4:$O$103,A54,Febrero!$G$4:$G$103)) -> 0
A55: =Marcas!$A$5 -> Tienda | B55: =IF(A55="","",SUMIF(Febrero!$O$4:$O$103,A55,Febrero!$E$4:$E$103)) -> 2098600 | C55: =IF(A55="","",SUMIF(Febrero!$O$4:$O$103,A55,Febrero!$J$4:$J$103)) -> 2088306 | D55: =IF(A55="","",Marcas!$B$5) -> 0 | E55: =IF(A55="","",C55*D55) -> 0 | F55: =IF(A55="","",SUMIF(Febrero!$O$4:$O$103,A55,Febrero!$G$4:$G$103)) -> 8781.5126
A56: =Marcas!$A$6 -> Pop disaster | B56: =IF(A56="","",SUMIF(Febrero!$O$4:$O$103,A56,Febrero!$E$4:$E$103)) -> 75000 | C56: =IF(A56="","",SUMIF(Febrero!$O$4:$O$103,A56,Febrero!$J$4:$J$103)) -> 75000 | D56: =IF(A56="","",Marcas!$B$6) -> 0.25 | E56: =IF(A56="","",C56*D56) -> 18750 | F56: =IF(A56="","",SUMIF(Febrero!$O$4:$O$103,A56,Febrero!$G$4:$G$103)) -> 0
A57: =Marcas!$A$7 -> Pedritos | B57: =IF(A57="","",SUMIF(Febrero!$O$4:$O$103,A57,Febrero!$E$4:$E$103)) -> 178000 | C57: =IF(A57="","",SUMIF(Febrero!$O$4:$O$103,A57,Febrero!$J$4:$J$103)) -> 178000 | D57: =IF(A57="","",Marcas!$B$7) -> 0.25 | E57: =IF(A57="","",C57*D57) -> 44500 | F57: =IF(A57="","",SUMIF(Febrero!$O$4:$O$103,A57,Febrero!$G$4:$G$103)) -> 0
A58: =Marcas!$A$8 | B58: =IF(A58="","",SUMIF(Febrero!$O$4:$O$103,A58,Febrero!$E$4:$E$103)) | C58: =IF(A58="","",SUMIF(Febrero!$O$4:$O$103,A58,Febrero!$J$4:$J$103)) | D58: =IF(A58="","",Marcas!$B$8) | E58: =IF(A58="","",C58*D58) | F58: =IF(A58="","",SUMIF(Febrero!$O$4:$O$103,A58,Febrero!$G$4:$G$103))
A59: =Marcas!$A$9 | B59: =IF(A59="","",SUMIF(Febrero!$O$4:$O$103,A59,Febrero!$E$4:$E$103)) | C59: =IF(A59="","",SUMIF(Febrero!$O$4:$O$103,A59,Febrero!$J$4:$J$103)) | D59: =IF(A59="","",Marcas!$B$9) | E59: =IF(A59="","",C59*D59) | F59: =IF(A59="","",SUMIF(Febrero!$O$4:$O$103,A59,Febrero!$G$4:$G$103))
A60: =Marcas!$A$10 | B60: =IF(A60="","",SUMIF(Febrero!$O$4:$O$103,A60,Febrero!$E$4:$E$103)) | C60: =IF(A60="","",SUMIF(Febrero!$O$4:$O$103,A60,Febrero!$J$4:$J$103)) | D60: =IF(A60="","",Marcas!$B$10) | E60: =IF(A60="","",C60*D60) | F60: =IF(A60="","",SUMIF(Febrero!$O$4:$O$103,A60,Febrero!$G$4:$G$103))
A61: =Marcas!$A$11 | B61: =IF(A61="","",SUMIF(Febrero!$O$4:$O$103,A61,Febrero!$E$4:$E$103)) | C61: =IF(A61="","",SUMIF(Febrero!$O$4:$O$103,A61,Febrero!$J$4:$J$103)) | D61: =IF(A61="","",Marcas!$B$11) | E61: =IF(A61="","",C61*D61) | F61: =IF(A61="","",SUMIF(Febrero!$O$4:$O$103,A61,Febrero!$G$4:$G$103))
A65: Resumen Tienda - Marzo
A66: Concepto | B66: Valor (CLP)
A67: Neto total tienda (todas las ventas) | B67: =SUM(Marzo!$M$4:Marzo!$M$103) -> 8911812.1
A68: Neto prendas 'Tienda' (propietario) | B68: =SUMIF(Marzo!$C$4:$C$103,"Tienda",Marzo!$M$4:$M$103) -> 7011930
A69: Neto prendas 'Consignacion' (propietario) | B69: =SUMIF(Marzo!$C$4:$C$103,"Consignacion",Marzo!$M$4:$M$103) -> 651000
A70: Total gastos fijos | B70: =Marzo!$B$130 -> 1751960
A71: Gasto fijo por integrante (÷5) | B71: =Marzo!$B$131 -> 350392
A73: Pagos fundadores - Marzo
A74: Integrante | B74: Neto prendas propias | C74: Cuota gastos fijos | D74: Saldo final (a pagar / a depositar)
A75: Aaron | B75: =SUMIF(Marzo!$C$4:$C$103,A75,Marzo!$M$4:$M$103) -> 182054.86 | C75: =$B$71 -> 350392 | D75: =B75-C75 -> -168337.14
A76: Benja R | B76: =SUMIF(Marzo!$C$4:$C$103,A76,Marzo!$M$4:$M$103) -> 665936.8 | C76: =$B$71 -> 350392 | D76: =B76-C76 -> 315544.8
A77: Benja M | B77: =SUMIF(Marzo!$C$4:$C$103,A77,Marzo!$M$4:$M$103) -> 0 | C77: =$B$71 -> 350392 | D77: =B77-C77 -> -350392
A78: Juanito | B78: =SUMIF(Marzo!$C$4:$C$103,A78,Marzo!$M$4:$M$103) -> 0 | C78: =$B$71 -> 350392 | D78: =B78-C78 -> -350392
A79: Fabio | B79: =SUMIF(Marzo!$C$4:$C$103,A79,Marzo!$M$4:$M$103) -> 400890.4 | C79: =$B$71 -> 350392 | D79: =B79-C79 -> 50498.404
A81: Marcas externas - Marzo
A82: Marca | B82: Ventas brutas marca | C82: Base comisión tienda (neto base) | D82: % comisión tienda | E82: Comisión tienda ($) | F82: IVA total marca
A83: =Marcas!$A$2 -> Nube | B83: =IF(A83="","",SUMIF(Marzo!$O$4:$O$103,A83,Marzo!$E$4:$E$103)) -> 0 | C83: =IF(A83="","",SUMIF(Marzo!$O$4:$O$103,A83,Marzo!$J$4:$J$103)) -> 0 | D83: =IF(A83="","",Marcas!$B$2) -> 0.25 | E83: =IF(A83="","",C83*D83) -> 0 | F83: =IF(A83="","",SUMIF(Marzo!$O$4:$O$103,A83,Marzo!$G$4:$G$103)) -> 0
A84: =Marcas!$A$3 -> Season Archive | B84: =IF(A84="","",SUMIF(Marzo!$O$4:$O$103,A84,Marzo!$E$4:$E$103)) -> 1595000 | C84: =IF(A84="","",SUMIF(Marzo!$O$4:$O$103,A84,Marzo!$J$4:$J$103)) -> 1595000 | D84: =IF(A84="","",Marcas!$B$3) -> 0.25 | E84: =IF(A84="","",C84*D84) -> 398750 | F84: =IF(A84="","",SUMIF(Marzo!$O$4:$O$103,A84,Marzo!$G$4:$G$103)) -> 0
A85: =Marcas!$A$4 -> Gelattos | B85: =IF(A85="","",SUMIF(Marzo!$O$4:$O$103,A85,Marzo!$E$4:$E$103)) -> 0 | C85: =IF(A85="","",SUMIF(Marzo!$O$4:$O$103,A85,Marzo!$J$4:$J$103)) -> 0 | D85: =IF(A85="","",Marcas!$B$4) -> 0.25 | E85: =IF(A85="","",C85*D85) -> 0 | F85: =IF(A85="","",SUMIF(Marzo!$O$4:$O$103,A85,Marzo!$G$4:$G$103)) -> 0
A86: =Marcas!$A$5 -> Tienda | B86: =IF(A86="","",SUMIF(Marzo!$O$4:$O$103,A86,Marzo!$E$4:$E$103)) -> 7790000 | C86: =IF(A86="","",SUMIF(Marzo!$O$4:$O$103,A86,Marzo!$J$4:$J$103)) -> 7714118 | D86: =IF(A86="","",Marcas!$B$5) -> 0 | E86: =IF(A86="","",C86*D86) -> 0 | F86: =IF(A86="","",SUMIF(Marzo!$O$4:$O$103,A86,Marzo!$G$4:$G$103)) -> 26344.538
A87: =Marcas!$A$6 -> Pop disaster | B87: =IF(A87="","",SUMIF(Marzo!$O$4:$O$103,A87,Marzo!$E$4:$E$103)) -> 65000 | C87: =IF(A87="","",SUMIF(Marzo!$O$4:$O$103,A87,Marzo!$J$4:$J$103)) -> 65000 | D87: =IF(A87="","",Marcas!$B$6) -> 0.25 | E87: =IF(A87="","",C87*D87) -> 16250 | F87: =IF(A87="","",SUMIF(Marzo!$O$4:$O$103,A87,Marzo!$G$4:$G$103)) -> 0
A88: =Marcas!$A$7 -> Pedritos | B88: =IF(A88="","",SUMIF(Marzo!$O$4:$O$103,A88,Marzo!$E$4:$E$103)) -> 75000 | C88: =IF(A88="","",SUMIF(Marzo!$O$4:$O$103,A88,Marzo!$J$4:$J$103)) -> 75000 | D88: =IF(A88="","",Marcas!$B$7) -> 0.25 | E88: =IF(A88="","",C88*D88) -> 18750 | F88: =IF(A88="","",SUMIF(Marzo!$O$4:$O$103,A88,Marzo!$G$4:$G$103)) -> 0
A89: =Marcas!$A$8 | B89: =IF(A89="","",SUMIF(Marzo!$O$4:$O$103,A89,Marzo!$E$4:$E$103)) | C89: =IF(A89="","",SUMIF(Marzo!$O$4:$O$103,A89,Marzo!$J$4:$J$103)) | D89: =IF(A89="","",Marcas!$B$8) | E89: =IF(A89="","",C89*D89) | F89: =IF(A89="","",SUMIF(Marzo!$O$4:$O$103,A89,Marzo!$G$4:$G$103))
A90: =Marcas!$A$9 | B90: =IF(A90="","",SUMIF(Marzo!$O$4:$O$103,A90,Marzo!$E$4:$E$103)) | C90: =IF(A90="","",SUMIF(Marzo!$O$4:$O$103,A90,Marzo!$J$4:$J$103)) | D90: =IF(A90="","",Marcas!$B$9) | E90: =IF(A90="","",C90*D90) | F90: =IF(A90="","",SUMIF(Marzo!$O$4:$O$103,A90,Marzo!$G$4:$G$103))
A91: =Marcas!$A$10 | B91: =IF(A91="","",SUMIF(Marzo!$O$4:$O$103,A91,Marzo!$E$4:$E$103)) | C91: =IF(A91="","",SUMIF(Marzo!$O$4:$O$103,A91,Marzo!$J$4:$J$103)) | D91: =IF(A91="","",Marcas!$B$10) | E91: =IF(A91="","",C91*D91) | F91: =IF(A91="","",SUMIF(Marzo!$O$4:$O$103,A91,Marzo!$G$4:$G$103))
A92: =Marcas!$A$11 | B92: =IF(A92="","",SUMIF(Marzo!$O$4:$O$103,A92,Marzo!$E$4:$E$103)) | C92: =IF(A92="","",SUMIF(Marzo!$O$4:$O$103,A92,Marzo!$J$4:$J$103)) | D92: =IF(A92="","",Marcas!$B$11) | E92: =IF(A92="","",C92*D92) | F92: =IF(A92="","",SUMIF(Marzo!$O$4:$O$103,A92,Marzo!$G$4:$G$103))
A96: Resumen Tienda - Abril
A97: Concepto | B97: Valor (CLP)
A98: Neto total tienda (todas las ventas) | B98: =SUM(Abril!$M$4:Abril!$M$103) -> 3643451.6
A99: Neto prendas 'Tienda' (propietario) | B99: =SUMIF(Abril!$C$4:$C$103,"Tienda",Abril!$M$4:$M$103) -> 2480716.8
A100: Neto prendas 'Consignacion' (propietario) | B100: =SUMIF(Abril!$C$4:$C$103,"Consignacion",Abril!$M$4:$M$103) -> 267150
A101: Total gastos fijos | B101: =Abril!$B$130 -> 1751960
A102: Gasto fijo por integrante (÷5) | B102: =Abril!$B$131 -> 350392
A104: Pagos fundadores - Abril
A105: Integrante | B105: Neto prendas propias | C105: Cuota gastos fijos | D105: Saldo final (a pagar / a depositar)
A106: Aaron | B106: =SUMIF(Abril!$C$4:$C$103,A106,Abril!$M$4:$M$103) -> 378750 | C106: =$B$102 -> 350392 | D106: =B106-C106 -> 28358
A107: Benja R | B107: =SUMIF(Abril!$C$4:$C$103,A107,Abril!$M$4:$M$103) -> 209934.86 | C107: =$B$102 -> 350392 | D107: =B107-C107 -> -140457.14
A108: Benja M | B108: =SUMIF(Abril!$C$4:$C$103,A108,Abril!$M$4:$M$103) -> 0 | C108: =$B$102 -> 350392 | D108: =B108-C108 -> -350392
A109: Juanito | B109: =SUMIF(Abril!$C$4:$C$103,A109,Abril!$M$4:$M$103) -> 0 | C109: =$B$102 -> 350392 | D109: =B109-C109 -> -350392
A110: Fabio | B110: =SUMIF(Abril!$C$4:$C$103,A110,Abril!$M$4:$M$103) -> 306900 | C110: =$B$102 -> 350392 | D110: =B110-C110 -> -43492
A112: Marcas externas - Abril
A113: Marca | B113: Ventas brutas marca | C113: Base comisión tienda (neto base) | D113: % comisión tienda | E113: Comisión tienda ($) | F113: IVA total marca
A114: =Marcas!$A$2 -> Nube | B114: =IF(A114="","",SUMIF(Abril!$O$4:$O$103,A114,Abril!$E$4:$E$103)) -> 0 | C114: =IF(A114="","",SUMIF(Abril!$O$4:$O$103,A114,Abril!$J$4:$J$103)) -> 0 | D114: =IF(A114="","",Marcas!$B$2) -> 0.25 | E114: =IF(A114="","",C114*D114) -> 0 | F114: =IF(A114="","",SUMIF(Abril!$O$4:$O$103,A114,Abril!$G$4:$G$103)) -> 0
A115: =Marcas!$A$3 -> Season Archive | B115: =IF(A115="","",SUMIF(Abril!$O$4:$O$103,A115,Abril!$E$4:$E$103)) -> 300000 | C115: =IF(A115="","",SUMIF(Abril!$O$4:$O$103,A115,Abril!$J$4:$J$103)) -> 300000 | D115: =IF(A115="","",Marcas!$B$3) -> 0.25 | E115: =IF(A115="","",C115*D115) -> 75000 | F115: =IF(A115="","",SUMIF(Abril!$O$4:$O$103,A115,Abril!$G$4:$G$103)) -> 0
A116: =Marcas!$A$4 -> Gelattos | B116: =IF(A116="","",SUMIF(Abril!$O$4:$O$103,A116,Abril!$E$4:$E$103)) -> 30000 | C116: =IF(A116="","",SUMIF(Abril!$O$4:$O$103,A116,Abril!$J$4:$J$103)) -> 30000 | D116: =IF(A116="","",Marcas!$B$4) -> 0.25 | E116: =IF(A116="","",C116*D116) -> 7500 | F116: =IF(A116="","",SUMIF(Abril!$O$4:$O$103,A116,Abril!$G$4:$G$103)) -> 0
A117: =Marcas!$A$5 -> Tienda | B117: =IF(A117="","",SUMIF(Abril!$O$4:$O$103,A117,Abril!$E$4:$E$103)) -> 3221000 | C117: =IF(A117="","",SUMIF(Abril!$O$4:$O$103,A117,Abril!$J$4:$J$103)) -> 3179584 | D117: =IF(A117="","",Marcas!$B$5) -> 0 | E117: =IF(A117="","",C117*D117) -> 0 | F117: =IF(A117="","",SUMIF(Abril!$O$4:$O$103,A117,Abril!$G$4:$G$103)) -> 35126.05
A118: =Marcas!$A$6 -> Pop disaster | B118: =IF(A118="","",SUMIF(Abril!$O$4:$O$103,A118,Abril!$E$4:$E$103)) -> 0 | C118: =IF(A118="","",SUMIF(Abril!$O$4:$O$103,A118,Abril!$J$4:$J$103)) -> 0 | D118: =IF(A118="","",Marcas!$B$6) -> 0.25 | E118: =IF(A118="","",C118*D118) -> 0 | F118: =IF(A118="","",SUMIF(Abril!$O$4:$O$103,A118,Abril!$G$4:$G$103)) -> 0
...

Sheet Gastos_Personales
A1: Mes | B1: Fecha | C1: Concepto | D1: Monto CLP | E1: Pagado por
A2: noviembre | C2: Computador ventas | D2: 50000 | E2: no

Sheet Comisiones
A1: Comisiones por vendedor y mes
A3: Comisiones - Enero
A4: Vendedor | B4: Total bruto ventas | C4: Total IVA | D4: Total comisiones bancarias | E4: Total comisiones vendedor | F4: Total neto tienda | G4: Nº ventas | H4: Ticket prom (bruto)
A5: Aaron | B5: =SUMIF(Enero!$D$4:Enero!$D$103,A5,Enero!$E$4:Enero!$E$103) -> 0 | C5: =SUMIF(Enero!$D$4:Enero!$D$103,A5,Enero!$G$4:Enero!$G$103) -> 0 | D5: =SUMIF(Enero!$D$4:Enero!$D$103,A5,Enero!$I$4:Enero!$I$103) -> 0 | E5: =SUMIF(Enero!$D$4:Enero!$D$103,A5,Enero!$L$4:Enero!$L$103) -> 0 | F5: =SUMIF(Enero!$D$4:Enero!$D$103,A5,Enero!$M$4:Enero!$M$103) -> 0 | G5: =COUNTIF(Enero!$D$4:Enero!$D$103,A5) -> 0 | H5: =IF(G5=0,0,B5/G5) -> 0
A6: Benja R | B6: =SUMIF(Enero!$D$4:Enero!$D$103,A6,Enero!$E$4:Enero!$E$103) -> 0 | C6: =SUMIF(Enero!$D$4:Enero!$D$103,A6,Enero!$G$4:Enero!$G$103) -> 0 | D6: =SUMIF(Enero!$D$4:Enero!$D$103,A6,Enero!$I$4:Enero!$I$103) -> 0 | E6: =SUMIF(Enero!$D$4:Enero!$D$103,A6,Enero!$L$4:Enero!$L$103) -> 0 | F6: =SUMIF(Enero!$D$4:Enero!$D$103,A6,Enero!$M$4:Enero!$M$103) -> 0 | G6: =COUNTIF(Enero!$D$4:Enero!$D$103,A6) -> 0 | H6: =IF(G6=0,0,B6/G6) -> 0
A7: Benja M | B7: =SUMIF(Enero!$D$4:Enero!$D$103,A7,Enero!$E$4:Enero!$E$103) -> 0 | C7: =SUMIF(Enero!$D$4:Enero!$D$103,A7,Enero!$G$4:Enero!$G$103) -> 0 | D7: =SUMIF(Enero!$D$4:Enero!$D$103,A7,Enero!$I$4:Enero!$I$103) -> 0 | E7: =SUMIF(Enero!$D$4:Enero!$D$103,A7,Enero!$L$4:Enero!$L$103) -> 0 | F7: =SUMIF(Enero!$D$4:Enero!$D$103,A7,Enero!$M$4:Enero!$M$103) -> 0 | G7: =COUNTIF(Enero!$D$4:Enero!$D$103,A7) -> 0 | H7: =IF(G7=0,0,B7/G7) -> 0
A8: Juanito | B8: =SUMIF(Enero!$D$4:Enero!$D$103,A8,Enero!$E$4:Enero!$E$103) -> 0 | C8: =SUMIF(Enero!$D$4:Enero!$D$103,A8,Enero!$G$4:Enero!$G$103) -> 0 | D8: =SUMIF(Enero!$D$4:Enero!$D$103,A8,Enero!$I$4:Enero!$I$103) -> 0 | E8: =SUMIF(Enero!$D$4:Enero!$D$103,A8,Enero!$L$4:Enero!$L$103) -> 0 | F8: =SUMIF(Enero!$D$4:Enero!$D$103,A8,Enero!$M$4:Enero!$M$103) -> 0 | G8: =COUNTIF(Enero!$D$4:Enero!$D$103,A8) -> 0 | H8: =IF(G8=0,0,B8/G8) -> 0
A9: Fabio | B9: =SUMIF(Enero!$D$4:Enero!$D$103,A9,Enero!$E$4:Enero!$E$103) -> 0 | C9: =SUMIF(Enero!$D$4:Enero!$D$103,A9,Enero!$G$4:Enero!$G$103) -> 0 | D9: =SUMIF(Enero!$D$4:Enero!$D$103,A9,Enero!$I$4:Enero!$I$103) -> 0 | E9: =SUMIF(Enero!$D$4:Enero!$D$103,A9,Enero!$L$4:Enero!$L$103) -> 0 | F9: =SUMIF(Enero!$D$4:Enero!$D$103,A9,Enero!$M$4:Enero!$M$103) -> 0 | G9: =COUNTIF(Enero!$D$4:Enero!$D$103,A9) -> 0 | H9: =IF(G9=0,0,B9/G9) -> 0
A10: Marenna | B10: =SUMIF(Enero!$D$4:Enero!$D$103,A10,Enero!$E$4:Enero!$E$103) -> 0 | C10: =SUMIF(Enero!$D$4:Enero!$D$103,A10,Enero!$G$4:Enero!$G$103) -> 0 | D10: =SUMIF(Enero!$D$4:Enero!$D$103,A10,Enero!$I$4:Enero!$I$103) -> 0 | E10: =SUMIF(Enero!$D$4:Enero!$D$103,A10,Enero!$L$4:Enero!$L$103) -> 0 | F10: =SUMIF(Enero!$D$4:Enero!$D$103,A10,Enero!$M$4:Enero!$M$103) -> 0 | G10: =COUNTIF(Enero!$D$4:Enero!$D$103,A10) -> 0 | H10: =IF(G10=0,0,B10/G10) -> 0
A11: Juan | B11: =SUMIF(Enero!$D$4:Enero!$D$103,A11,Enero!$E$4:Enero!$E$103) -> 0 | C11: =SUMIF(Enero!$D$4:Enero!$D$103,A11,Enero!$G$4:Enero!$G$103) -> 0 | D11: =SUMIF(Enero!$D$4:Enero!$D$103,A11,Enero!$I$4:Enero!$I$103) -> 0 | E11: =SUMIF(Enero!$D$4:Enero!$D$103,A11,Enero!$L$4:Enero!$L$103) -> 0 | F11: =SUMIF(Enero!$D$4:Enero!$D$103,A11,Enero!$M$4:Enero!$M$103) -> 0 | G11: =COUNTIF(Enero!$D$4:Enero!$D$103,A11) -> 0 | H11: =IF(G11=0,0,B11/G11) -> 0
A12: TOTAL | B12: =SUM(B5:B11) -> 0 | C12: =SUM(C5:C11) -> 0 | D12: =SUM(D5:D11) -> 0 | E12: =SUM(E5:E11) -> 0 | F12: =SUM(F5:F11) -> 0 | G12: =SUM(G5:G11) -> 0 | H12: =SUM(H5:H11) -> 0
A15: Comisiones - Febrero
A16: Vendedor | B16: Total bruto ventas | C16: Total IVA | D16: Total comisiones bancarias | E16: Total comisiones vendedor | F16: Total neto tienda | G16: Nº ventas | H16: Ticket prom (bruto)
A17: Aaron | B17: =SUMIF(Febrero!$D$4:Febrero!$D$103,A17,Febrero!$E$4:Febrero!$E$103) -> 175800 | C17: =SUMIF(Febrero!$D$4:Febrero!$D$103,A17,Febrero!$G$4:Febrero!$G$103) -> 0 | D17: =SUMIF(Febrero!$D$4:Febrero!$D$103,A17,Febrero!$I$4:Febrero!$I$103) -> 0 | E17: =SUMIF(Febrero!$D$4:Febrero!$D$103,A17,Febrero!$L$4:Febrero!$L$103) -> 12306 | F17: =SUMIF(Febrero!$D$4:Febrero!$D$103,A17,Febrero!$M$4:Febrero!$M$103) -> 163494 | G17: =COUNTIF(Febrero!$D$4:Febrero!$D$103,A17) -> 5 | H17: =IF(G17=0,0,B17/G17) -> 35160
A18: Benja R | B18: =SUMIF(Febrero!$D$4:Febrero!$D$103,A18,Febrero!$E$4:Febrero!$E$103) -> 1055800 | C18: =SUMIF(Febrero!$D$4:Febrero!$D$103,A18,Febrero!$G$4:Febrero!$G$103) -> 0 | D18: =SUMIF(Febrero!$D$4:Febrero!$D$103,A18,Febrero!$I$4:Febrero!$I$103) -> 0 | E18: =SUMIF(Febrero!$D$4:Febrero!$D$103,A18,Febrero!$L$4:Febrero!$L$103) -> 63756 | F18: =SUMIF(Febrero!$D$4:Febrero!$D$103,A18,Febrero!$M$4:Febrero!$M$103) -> 992044 | G18: =COUNTIF(Febrero!$D$4:Febrero!$D$103,A18) -> 27 | H18: =IF(G18=0,0,B18/G18) -> 39103.704
A19: Benja M | B19: =SUMIF(Febrero!$D$4:Febrero!$D$103,A19,Febrero!$E$4:Febrero!$E$103) -> 0 | C19: =SUMIF(Febrero!$D$4:Febrero!$D$103,A19,Febrero!$G$4:Febrero!$G$103) -> 0 | D19: =SUMIF(Febrero!$D$4:Febrero!$D$103,A19,Febrero!$I$4:Febrero!$I$103) -> 0 | E19: =SUMIF(Febrero!$D$4:Febrero!$D$103,A19,Febrero!$L$4:Febrero!$L$103) -> 0 | F19: =SUMIF(Febrero!$D$4:Febrero!$D$103,A19,Febrero!$M$4:Febrero!$M$103) -> 0 | G19: =COUNTIF(Febrero!$D$4:Febrero!$D$103,A19) -> 0 | H19: =IF(G19=0,0,B19/G19) -> 0
A20: Juanito | B20: =SUMIF(Febrero!$D$4:Febrero!$D$103,A20,Febrero!$E$4:Febrero!$E$103) -> 0 | C20: =SUMIF(Febrero!$D$4:Febrero!$D$103,A20,Febrero!$G$4:Febrero!$G$103) -> 0 | D20: =SUMIF(Febrero!$D$4:Febrero!$D$103,A20,Febrero!$I$4:Febrero!$I$103) -> 0 | E20: =SUMIF(Febrero!$D$4:Febrero!$D$103,A20,Febrero!$L$4:Febrero!$L$103) -> 0 | F20: =SUMIF(Febrero!$D$4:Febrero!$D$103,A20,Febrero!$M$4:Febrero!$M$103) -> 0 | G20: =COUNTIF(Febrero!$D$4:Febrero!$D$103,A20) -> 0 | H20: =IF(G20=0,0,B20/G20) -> 0
A21: Fabio | B21: =SUMIF(Febrero!$D$4:Febrero!$D$103,A21,Febrero!$E$4:Febrero!$E$103) -> 733000 | C21: =SUMIF(Febrero!$D$4:Febrero!$D$103,A21,Febrero!$G$4:Febrero!$G$103) -> 8781.5126 | D21: =SUMIF(Febrero!$D$4:Febrero!$D$103,A21,Febrero!$I$4:Febrero!$I$103) -> 1512.5 | E21: =SUMIF(Febrero!$D$4:Febrero!$D$103,A21,Febrero!$L$4:Febrero!$L$103) -> 23935.299 | F21: =SUMIF(Febrero!$D$4:Febrero!$D$103,A21,Febrero!$M$4:Febrero!$M$103) -> 698770.69 | G21: =COUNTIF(Febrero!$D$4:Febrero!$D$103,A21) -> 12 | H21: =IF(G21=0,0,B21/G21) -> 61083.333
A22: Marenna | B22: =SUMIF(Febrero!$D$4:Febrero!$D$103,A22,Febrero!$E$4:Febrero!$E$103) -> 737000 | C22: =SUMIF(Febrero!$D$4:Febrero!$D$103,A22,Febrero!$G$4:Febrero!$G$103) -> 0 | D22: =SUMIF(Febrero!$D$4:Febrero!$D$103,A22,Febrero!$I$4:Febrero!$I$103) -> 0 | E22: =SUMIF(Febrero!$D$4:Febrero!$D$103,A22,Febrero!$L$4:Febrero!$L$103) -> 45290 | F22: =SUMIF(Febrero!$D$4:Febrero!$D$103,A22,Febrero!$M$4:Febrero!$M$103) -> 691710 | G22: =COUNTIF(Febrero!$D$4:Febrero!$D$103,A22) -> 15 | H22: =IF(G22=0,0,B22/G22) -> 49133.333
A23: Juan | B23: =SUMIF(Febrero!$D$4:Febrero!$D$103,A23,Febrero!$E$4:Febrero!$E$103) -> 0 | C23: =SUMIF(Febrero!$D$4:Febrero!$D$103,A23,Febrero!$G$4:Febrero!$G$103) -> 0 | D23: =SUMIF(Febrero!$D$4:Febrero!$D$103,A23,Febrero!$I$4:Febrero!$I$103) -> 0 | E23: =SUMIF(Febrero!$D$4:Febrero!$D$103,A23,Febrero!$L$4:Febrero!$L$103) -> 0 | F23: =SUMIF(Febrero!$D$4:Febrero!$D$103,A23,Febrero!$M$4:Febrero!$M$103) -> 0 | G23: =COUNTIF(Febrero!$D$4:Febrero!$D$103,A23) -> 0 | H23: =IF(G23=0,0,B23/G23) -> 0
A24: TOTAL | B24: =SUM(B17:B23) -> 2701600 | C24: =SUM(C17:C23) -> 8781.5126 | D24: =SUM(D17:D23) -> 1512.5 | E24: =SUM(E17:E23) -> 145287.3 | F24: =SUM(F17:F23) -> 2546018.7 | G24: =SUM(G17:G23) -> 59 | H24: =SUM(H17:H23) -> 184480.37
A27: Comisiones - Marzo
A28: Vendedor | B28: Total bruto ventas | C28: Total IVA | D28: Total comisiones bancarias | E28: Total comisiones vendedor | F28: Total neto tienda | G28: Nº ventas | H28: Ticket prom (bruto)
A29: Aaron | B29: =SUMIF(Marzo!$D$4:Marzo!$D$103,A29,Marzo!$E$4:Marzo!$E$103) -> 55000 | C29: =SUMIF(Marzo!$D$4:Marzo!$D$103,A29,Marzo!$G$4:Marzo!$G$103) -> 5588.2353 | D29: =SUMIF(Marzo!$D$4:Marzo!$D$103,A29,Marzo!$I$4:Marzo!$I$103) -> 962.5 | E29: =SUMIF(Marzo!$D$4:Marzo!$D$103,A29,Marzo!$L$4:Marzo!$L$103) -> 1422.4632 | F29: =SUMIF(Marzo!$D$4:Marzo!$D$103,A29,Marzo!$M$4:Marzo!$M$103) -> 47026.801 | G29: =COUNTIF(Marzo!$D$4:Marzo!$D$103,A29) -> 2 | H29: =IF(G29=0,0,B29/G29) -> 27500
A30: Benja R | B30: =SUMIF(Marzo!$D$4:Marzo!$D$103,A30,Marzo!$E$4:Marzo!$E$103) -> 7355000 | C30: =SUMIF(Marzo!$D$4:Marzo!$D$103,A30,Marzo!$G$4:Marzo!$G$103) -> 11176.471 | D30: =SUMIF(Marzo!$D$4:Marzo!$D$103,A30,Marzo!$I$4:Marzo!$I$103) -> 1925 | E30: =SUMIF(Marzo!$D$4:Marzo!$D$103,A30,Marzo!$L$4:Marzo!$L$103) -> 407794.93 | F30: =SUMIF(Marzo!$D$4:Marzo!$D$103,A30,Marzo!$M$4:Marzo!$M$103) -> 6889103.6 | G30: =COUNTIF(Marzo!$D$4:Marzo!$D$103,A30) -> 62 | H30: =IF(G30=0,0,B30/G30) -> 118629.03
A31: Benja M | B31: =SUMIF(Marzo!$D$4:Marzo!$D$103,A31,Marzo!$E$4:Marzo!$E$103) -> 0 | C31: =SUMIF(Marzo!$D$4:Marzo!$D$103,A31,Marzo!$G$4:Marzo!$G$103) -> 0 | D31: =SUMIF(Marzo!$D$4:Marzo!$D$103,A31,Marzo!$I$4:Marzo!$I$103) -> 0 | E31: =SUMIF(Marzo!$D$4:Marzo!$D$103,A31,Marzo!$L$4:Marzo!$L$103) -> 0 | F31: =SUMIF(Marzo!$D$4:Marzo!$D$103,A31,Marzo!$M$4:Marzo!$M$103) -> 0 | G31: =COUNTIF(Marzo!$D$4:Marzo!$D$103,A31) -> 0 | H31: =IF(G31=0,0,B31/G31) -> 0
A32: Juanito | B32: =SUMIF(Marzo!$D$4:Marzo!$D$103,A32,Marzo!$E$4:Marzo!$E$103) -> 0 | C32: =SUMIF(Marzo!$D$4:Marzo!$D$103,A32,Marzo!$G$4:Marzo!$G$103) -> 0 | D32: =SUMIF(Marzo!$D$4:Marzo!$D$103,A32,Marzo!$I$4:Marzo!$I$103) -> 0 | E32: =SUMIF(Marzo!$D$4:Marzo!$D$103,A32,Marzo!$L$4:Marzo!$L$103) -> 0 | F32: =SUMIF(Marzo!$D$4:Marzo!$D$103,A32,Marzo!$M$4:Marzo!$M$103) -> 0 | G32: =COUNTIF(Marzo!$D$4:Marzo!$D$103,A32) -> 0 | H32: =IF(G32=0,0,B32/G32) -> 0
A33: Fabio | B33: =SUMIF(Marzo!$D$4:Marzo!$D$103,A33,Marzo!$E$4:Marzo!$E$103) -> 1525000 | C33: =SUMIF(Marzo!$D$4:Marzo!$D$103,A33,Marzo!$G$4:Marzo!$G$103) -> 9579.8319 | D33: =SUMIF(Marzo!$D$4:Marzo!$D$103,A33,Marzo!$I$4:Marzo!$I$103) -> 1650 | E33: =SUMIF(Marzo!$D$4:Marzo!$D$103,A33,Marzo!$L$4:Marzo!$L$103) -> 92388.508 | F33: =SUMIF(Marzo!$D$4:Marzo!$D$103,A33,Marzo!$M$4:Marzo!$M$103) -> 1421381.7 | G33: =COUNTIF(Marzo!$D$4:Marzo!$D$103,A33) -> 14 | H33: =IF(G33=0,0,B33/G33) -> 108928.57
A34: Marenna | B34: =SUMIF(Marzo!$D$4:Marzo!$D$103,A34,Marzo!$E$4:Marzo!$E$103) -> 590000 | C34: =SUMIF(Marzo!$D$4:Marzo!$D$103,A34,Marzo!$G$4:Marzo!$G$103) -> 0 | D34: =SUMIF(Marzo!$D$4:Marzo!$D$103,A34,Marzo!$I$4:Marzo!$I$103) -> 0 | E34: =SUMIF(Marzo!$D$4:Marzo!$D$103,A34,Marzo!$L$4:Marzo!$L$103) -> 35700 | F34: =SUMIF(Marzo!$D$4:Marzo!$D$103,A34,Marzo!$M$4:Marzo!$M$103) -> 554300 | G34: =COUNTIF(Marzo!$D$4:Marzo!$D$103,A34) -> 14 | H34: =IF(G34=0,0,B34/G34) -> 42142.857
A35: Juan | B35: =SUMIF(Marzo!$D$4:Marzo!$D$103,A35,Marzo!$E$4:Marzo!$E$103) -> 0 | C35: =SUMIF(Marzo!$D$4:Marzo!$D$103,A35,Marzo!$G$4:Marzo!$G$103) -> 0 | D35: =SUMIF(Marzo!$D$4:Marzo!$D$103,A35,Marzo!$I$4:Marzo!$I$103) -> 0 | E35: =SUMIF(Marzo!$D$4:Marzo!$D$103,A35,Marzo!$L$4:Marzo!$L$103) -> 0 | F35: =SUMIF(Marzo!$D$4:Marzo!$D$103,A35,Marzo!$M$4:Marzo!$M$103) -> 0 | G35: =COUNTIF(Marzo!$D$4:Marzo!$D$103,A35) -> 0 | H35: =IF(G35=0,0,B35/G35) -> 0
A36: TOTAL | B36: =SUM(B29:B35) -> 9525000 | C36: =SUM(C29:C35) -> 26344.538 | D36: =SUM(D29:D35) -> 4537.5 | E36: =SUM(E29:E35) -> 537305.9 | F36: =SUM(F29:F35) -> 8911812.1 | G36: =SUM(G29:G35) -> 92 | H36: =SUM(H29:H35) -> 297200.46
A39: Comisiones - Abril
A40: Vendedor | B40: Total bruto ventas | C40: Total IVA | D40: Total comisiones bancarias | E40: Total comisiones vendedor | F40: Total neto tienda | G40: Nº ventas | H40: Ticket prom (bruto)
A41: Aaron | B41: =SUMIF(Abril!$D$4:Abril!$D$103,A41,Abril!$E$4:Abril!$E$103) -> 160000 | C41: =SUMIF(Abril!$D$4:Abril!$D$103,A41,Abril!$G$4:Abril!$G$103) -> 12773.109 | D41: =SUMIF(Abril!$D$4:Abril!$D$103,A41,Abril!$I$4:Abril!$I$103) -> 2360 | E41: =SUMIF(Abril!$D$4:Abril!$D$103,A41,Abril!$L$4:Abril!$L$103) -> 0 | F41: =SUMIF(Abril!$D$4:Abril!$D$103,A41,Abril!$M$4:Abril!$M$103) -> 144866.89 | G41: =COUNTIF(Abril!$D$4:Abril!$D$103,A41) -> 3 | H41: =IF(G41=0,0,B41/G41) -> 53333.333
A42: Benja R | B42: =SUMIF(Abril!$D$4:Abril!$D$103,A42,Abril!$E$4:Abril!$E$103) -> 1878000 | C42: =SUMIF(Abril!$D$4:Abril!$D$103,A42,Abril!$G$4:Abril!$G$103) -> 31932.773 | D42: =SUMIF(Abril!$D$4:Abril!$D$103,A42,Abril!$I$4:Abril!$I$103) -> 5740 | E42: =SUMIF(Abril!$D$4:Abril!$D$103,A42,Abril!$L$4:Abril!$L$103) -> 101216.36 | F42: =SUMIF(Abril!$D$4:Abril!$D$103,A42,Abril!$M$4:Abril!$M$103) -> 1739110.9 | G42: =COUNTIF(Abril!$D$4:Abril!$D$103,A42) -> 23 | H42: =IF(G42=0,0,B42/G42) -> 81652.174
A43: Benja M | B43: =SUMIF(Abril!$D$4:Abril!$D$103,A43,Abril!$E$4:Abril!$E$103) -> 0 | C43: =SUMIF(Abril!$D$4:Abril!$D$103,A43,Abril!$G$4:Abril!$G$103) -> 0 | D43: =SUMIF(Abril!$D$4:Abril!$D$103,A43,Abril!$I$4:Abril!$I$103) -> 0 | E43: =SUMIF(Abril!$D$4:Abril!$D$103,A43,Abril!$L$4:Abril!$L$103) -> 0 | F43: =SUMIF(Abril!$D$4:Abril!$D$103,A43,Abril!$M$4:Abril!$M$103) -> 0 | G43: =COUNTIF(Abril!$D$4:Abril!$D$103,A43) -> 0 | H43: =IF(G43=0,0,B43/G43) -> 0
A44: Juanito | B44: =SUMIF(Abril!$D$4:Abril!$D$103,A44,Abril!$E$4:Abril!$E$103) -> 0 | C44: =SUMIF(Abril!$D$4:Abril!$D$103,A44,Abril!$G$4:Abril!$G$103) -> 0 | D44: =SUMIF(Abril!$D$4:Abril!$D$103,A44,Abril!$I$4:Abril!$I$103) -> 0 | E44: =SUMIF(Abril!$D$4:Abril!$D$103,A44,Abril!$L$4:Abril!$L$103) -> 0 | F44: =SUMIF(Abril!$D$4:Abril!$D$103,A44,Abril!$M$4:Abril!$M$103) -> 0 | G44: =COUNTIF(Abril!$D$4:Abril!$D$103,A44) -> 0 | H44: =IF(G44=0,0,B44/G44) -> 0
A45: Fabio | B45: =SUMIF(Abril!$D$4:Abril!$D$103,A45,Abril!$E$4:Abril!$E$103) -> 1350000 | C45: =SUMIF(Abril!$D$4:Abril!$D$103,A45,Abril!$G$4:Abril!$G$103) -> 0 | D45: =SUMIF(Abril!$D$4:Abril!$D$103,A45,Abril!$I$4:Abril!$I$103) -> 0 | E45: =SUMIF(Abril!$D$4:Abril!$D$103,A45,Abril!$L$4:Abril!$L$103) -> 86800 | F45: =SUMIF(Abril!$D$4:Abril!$D$103,A45,Abril!$M$4:Abril!$M$103) -> 1263200 | G45: =COUNTIF(Abril!$D$4:Abril!$D$103,A45) -> 16 | H45: =IF(G45=0,0,B45/G45) -> 84375
A46: Marenna | B46: =SUMIF(Abril!$D$4:Abril!$D$103,A46,Abril!$E$4:Abril!$E$103) -> 531000 | C46: =SUMIF(Abril!$D$4:Abril!$D$103,A46,Abril!$G$4:Abril!$G$103) -> 3193.2773 | D46: =SUMIF(Abril!$D$4:Abril!$D$103,A46,Abril!$I$4:Abril!$I$103) -> 550 | E46: =SUMIF(Abril!$D$4:Abril!$D$103,A46,Abril!$L$4:Abril!$L$103) -> 30982.836 | F46: =SUMIF(Abril!$D$4:Abril!$D$103,A46,Abril!$M$4:Abril!$M$103) -> 496273.89 | G46: =COUNTIF(Abril!$D$4:Abril!$D$103,A46) -> 13 | H46: =IF(G46=0,0,B46/G46) -> 40846.154
A47: Juan | B47: =SUMIF(Abril!$D$4:Abril!$D$103,A47,Abril!$E$4:Abril!$E$103) -> 0 | C47: =SUMIF(Abril!$D$4:Abril!$D$103,A47,Abril!$G$4:Abril!$G$103) -> 0 | D47: =SUMIF(Abril!$D$4:Abril!$D$103,A47,Abril!$I$4:Abril!$I$103) -> 0 | E47: =SUMIF(Abril!$D$4:Abril!$D$103,A47,Abril!$L$4:Abril!$L$103) -> 0 | F47: =SUMIF(Abril!$D$4:Abril!$D$103,A47,Abril!$M$4:Abril!$M$103) -> 0 | G47: =COUNTIF(Abril!$D$4:Abril!$D$103,A47) -> 0 | H47: =IF(G47=0,0,B47/G47) -> 0
A48: TOTAL | B48: =SUM(B41:B47) -> 3919000 | C48: =SUM(C41:C47) -> 47899.16 | D48: =SUM(D41:D47) -> 8650 | E48: =SUM(E41:E47) -> 218999.2 | F48: =SUM(F41:F47) -> 3643451.6 | G48: =SUM(G41:G47) -> 55 | H48: =SUM(H41:H47) -> 260206.66
A51: Comisiones - Mayo
A52: Vendedor | B52: Total bruto ventas | C52: Total IVA | D52: Total comisiones bancarias | E52: Total comisiones vendedor | F52: Total neto tienda | G52: Nº ventas | H52: Ticket prom (bruto)
A53: Aaron | B53: =SUMIF(Mayo!$D$4:Mayo!$D$103,A53,Mayo!$E$4:Mayo!$E$103) -> 360000 | C53: =SUMIF(Mayo!$D$4:Mayo!$D$103,A53,Mayo!$G$4:Mayo!$G$103) -> 0 | D53: =SUMIF(Mayo!$D$4:Mayo!$D$103,A53,Mayo!$I$4:Mayo!$I$103) -> 0 | E53: =SUMIF(Mayo!$D$4:Mayo!$D$103,A53,Mayo!$L$4:Mayo!$L$103) -> 25200 | F53: =SUMIF(Mayo!$D$4:Mayo!$D$103,A53,Mayo!$M$4:Mayo!$M$103) -> 334800 | G53: =COUNTIF(Mayo!$D$4:Mayo!$D$103,A53) -> 3 | H53: =IF(G53=0,0,B53/G53) -> 120000
A54: Benja R | B54: =SUMIF(Mayo!$D$4:Mayo!$D$103,A54,Mayo!$E$4:Mayo!$E$103) -> 1680000 | C54: =SUMIF(Mayo!$D$4:Mayo!$D$103,A54,Mayo!$G$4:Mayo!$G$103) -> 18361.345 | D54: =SUMIF(Mayo!$D$4:Mayo!$D$103,A54,Mayo!$I$4:Mayo!$I$103) -> 550 | E54: =SUMIF(Mayo!$D$4:Mayo!$D$103,A54,Mayo!$L$4:Mayo!$L$103) -> 86912.836 | F54: =SUMIF(Mayo!$D$4:Mayo!$D$103,A54,Mayo!$M$4:Mayo!$M$103) -> 1574175.8 | G54: =COUNTIF(Mayo!$D$4:Mayo!$D$103,A54) -> 16 | H54: =IF(G54=0,0,B54/G54) -> 105000
A55: Benja M | B55: =SUMIF(Mayo!$D$4:Mayo!$D$103,A55,Mayo!$E$4:Mayo!$E$103) -> 0 | C55: =SUMIF(Mayo!$D$4:Mayo!$D$103,A55,Mayo!$G$4:Mayo!$G$103) -> 0 | D55: =SUMIF(Mayo!$D$4:Mayo!$D$103,A55,Mayo!$I$4:Mayo!$I$103) -> 0 | E55: =SUMIF(Mayo!$D$4:Mayo!$D$103,A55,Mayo!$L$4:Mayo!$L$103) -> 0 | F55: =SUMIF(Mayo!$D$4:Mayo!$D$103,A55,Mayo!$M$4:Mayo!$M$103) -> 0 | G55: =COUNTIF(Mayo!$D$4:Mayo!$D$103,A55) -> 0 | H55: =IF(G55=0,0,B55/G55) -> 0
A56: Juanito | B56: =SUMIF(Mayo!$D$4:Mayo!$D$103,A56,Mayo!$E$4:Mayo!$E$103) -> 0 | C56: =SUMIF(Mayo!$D$4:Mayo!$D$103,A56,Mayo!$G$4:Mayo!$G$103) -> 0 | D56: =SUMIF(Mayo!$D$4:Mayo!$D$103,A56,Mayo!$I$4:Mayo!$I$103) -> 0 | E56: =SUMIF(Mayo!$D$4:Mayo!$D$103,A56,Mayo!$L$4:Mayo!$L$103) -> 0 | F56: =SUMIF(Mayo!$D$4:Mayo!$D$103,A56,Mayo!$M$4:Mayo!$M$103) -> 0 | G56: =COUNTIF(Mayo!$D$4:Mayo!$D$103,A56) -> 0 | H56: =IF(G56=0,0,B56/G56) -> 0
A57: Fabio | B57: =SUMIF(Mayo!$D$4:Mayo!$D$103,A57,Mayo!$E$4:Mayo!$E$103) -> 350000 | C57: =SUMIF(Mayo!$D$4:Mayo!$D$103,A57,Mayo!$G$4:Mayo!$G$103) -> 0 | D57: =SUMIF(Mayo!$D$4:Mayo!$D$103,A57,Mayo!$I$4:Mayo!$I$103) -> 0 | E57: =SUMIF(Mayo!$D$4:Mayo!$D$103,A57,Mayo!$L$4:Mayo!$L$103) -> 24500 | F57: =SUMIF(Mayo!$D$4:Mayo!$D$103,A57,Mayo!$M$4:Mayo!$M$103) -> 325500 | G57: =COUNTIF(Mayo!$D$4:Mayo!$D$103,A57) -> 1 | H57: =IF(G57=0,0,B57/G57) -> 350000
A58: Marenna | B58: =SUMIF(Mayo!$D$4:Mayo!$D$103,A58,Mayo!$E$4:Mayo!$E$103) -> 285000 | C58: =SUMIF(Mayo!$D$4:Mayo!$D$103,A58,Mayo!$G$4:Mayo!$G$103) -> 0 | D58: =SUMIF(Mayo!$D$4:Mayo!$D$103,A58,Mayo!$I$4:Mayo!$I$103) -> 0 | E58: =SUMIF(Mayo!$D$4:Mayo!$D$103,A58,Mayo!$L$4:Mayo!$L$103) -> 11550 | F58: =SUMIF(Mayo!$D$4:Mayo!$D$103,A58,Mayo!$M$4:Mayo!$M$103) -> 273450 | G58: =COUNTIF(Mayo!$D$4:Mayo!$D$103,A58) -> 6 | H58: =IF(G58=0,0,B58/G58) -> 47500
A59: Juan | B59: =SUMIF(Mayo!$D$4:Mayo!$D$103,A59,Mayo!$E$4:Mayo!$E$103) -> 0 | C59: =SUMIF(Mayo!$D$4:Mayo!$D$103,A59,Mayo!$G$4:Mayo!$G$103) -> 0 | D59: =SUMIF(Mayo!$D$4:Mayo!$D$103,A59,Mayo!$I$4:Mayo!$I$103) -> 0 | E59: =SUMIF(Mayo!$D$4:Mayo!$D$103,A59,Mayo!$L$4:Mayo!$L$103) -> 0 | F59: =SUMIF(Mayo!$D$4:Mayo!$D$103,A59,Mayo!$M$4:Mayo!$M$103) -> 0 | G59: =COUNTIF(Mayo!$D$4:Mayo!$D$103,A59) -> 0 | H59: =IF(G59=0,0,B59/G59) -> 0
A60: TOTAL | B60: =SUM(B53:B59) -> 2675000 | C60: =SUM(C53:C59) -> 18361.345 | D60: =SUM(D53:D59) -> 550 | E60: =SUM(E53:E59) -> 148162.84 | F60: =SUM(F53:F59) -> 2507925.8 | G60: =SUM(G53:G59) -> 26 | H60: =SUM(H53:H59) -> 622500
A63: Comisiones - Junio
A64: Vendedor | B64: Total bruto ventas | C64: Total IVA | D64: Total comisiones bancarias | E64: Total comisiones vendedor | F64: Total neto tienda | G64: Nº ventas | H64: Ticket prom (bruto)
A65: Aaron | B65: =SUMIF(Junio!$D$4:Junio!$D$103,A65,Junio!$E$4:Junio!$E$103) -> 0 | C65: =SUMIF(Junio!$D$4:Junio!$D$103,A65,Junio!$G$4:Junio!$G$103) -> 0 | D65: =SUMIF(Junio!$D$4:Junio!$D$103,A65,Junio!$I$4:Junio!$I$103) -> 0 | E65: =SUMIF(Junio!$D$4:Junio!$D$103,A65,Junio!$L$4:Junio!$L$103) -> 0 | F65: =SUMIF(Junio!$D$4:Junio!$D$103,A65,Junio!$M$4:Junio!$M$103) -> 0 | G65: =COUNTIF(Junio!$D$4:Junio!$D$103,A65) -> 0 | H65: =IF(G65=0,0,B65/G65) -> 0
A66: Benja R | B66: =SUMIF(Junio!$D$4:Junio!$D$103,A66,Junio!$E$4:Junio!$E$103) -> 0 | C66: =SUMIF(Junio!$D$4:Junio!$D$103,A66,Junio!$G$4:Junio!$G$103) -> 0 | D66: =SUMIF(Junio!$D$4:Junio!$D$103,A66,Junio!$I$4:Junio!$I$103) -> 0 | E66: =SUMIF(Junio!$D$4:Junio!$D$103,A66,Junio!$L$4:Junio!$L$103) -> 0 | F66: =SUMIF(Junio!$D$4:Junio!$D$103,A66,Junio!$M$4:Junio!$M$103) -> 0 | G66: =COUNTIF(Junio!$D$4:Junio!$D$103,A66) -> 0 | H66: =IF(G66=0,0,B66/G66) -> 0
A67: Benja M | B67: =SUMIF(Junio!$D$4:Junio!$D$103,A67,Junio!$E$4:Junio!$E$103) -> 0 | C67: =SUMIF(Junio!$D$4:Junio!$D$103,A67,Junio!$G$4:Junio!$G$103) -> 0 | D67: =SUMIF(Junio!$D$4:Junio!$D$103,A67,Junio!$I$4:Junio!$I$103) -> 0 | E67: =SUMIF(Junio!$D$4:Junio!$D$103,A67,Junio!$L$4:Junio!$L$103) -> 0 | F67: =SUMIF(Junio!$D$4:Junio!$D$103,A67,Junio!$M$4:Junio!$M$103) -> 0 | G67: =COUNTIF(Junio!$D$4:Junio!$D$103,A67) -> 0 | H67: =IF(G67=0,0,B67/G67) -> 0
A68: Juanito | B68: =SUMIF(Junio!$D$4:Junio!$D$103,A68,Junio!$E$4:Junio!$E$103) -> 0 | C68: =SUMIF(Junio!$D$4:Junio!$D$103,A68,Junio!$G$4:Junio!$G$103) -> 0 | D68: =SUMIF(Junio!$D$4:Junio!$D$103,A68,Junio!$I$4:Junio!$I$103) -> 0 | E68: =SUMIF(Junio!$D$4:Junio!$D$103,A68,Junio!$L$4:Junio!$L$103) -> 0 | F68: =SUMIF(Junio!$D$4:Junio!$D$103,A68,Junio!$M$4:Junio!$M$103) -> 0 | G68: =COUNTIF(Junio!$D$4:Junio!$D$103,A68) -> 0 | H68: =IF(G68=0,0,B68/G68) -> 0
A69: Fabio | B69: =SUMIF(Junio!$D$4:Junio!$D$103,A69,Junio!$E$4:Junio!$E$103) -> 0 | C69: =SUMIF(Junio!$D$4:Junio!$D$103,A69,Junio!$G$4:Junio!$G$103) -> 0 | D69: =SUMIF(Junio!$D$4:Junio!$D$103,A69,Junio!$I$4:Junio!$I$103) -> 0 | E69: =SUMIF(Junio!$D$4:Junio!$D$103,A69,Junio!$L$4:Junio!$L$103) -> 0 | F69: =SUMIF(Junio!$D$4:Junio!$D$103,A69,Junio!$M$4:Junio!$M$103) -> 0 | G69: =COUNTIF(Junio!$D$4:Junio!$D$103,A69) -> 0 | H69: =IF(G69=0,0,B69/G69) -> 0
A70: Marenna | B70: =SUMIF(Junio!$D$4:Junio!$D$103,A70,Junio!$E$4:Junio!$E$103) -> 0 | C70: =SUMIF(Junio!$D$4:Junio!$D$103,A70,Junio!$G$4:Junio!$G$103) -> 0 | D70: =SUMIF(Junio!$D$4:Junio!$D$103,A70,Junio!$I$4:Junio!$I$103) -> 0 | E70: =SUMIF(Junio!$D$4:Junio!$D$103,A70,Junio!$L$4:Junio!$L$103) -> 0 | F70: =SUMIF(Junio!$D$4:Junio!$D$103,A70,Junio!$M$4:Junio!$M$103) -> 0 | G70: =COUNTIF(Junio!$D$4:Junio!$D$103,A70) -> 0 | H70: =IF(G70=0,0,B70/G70) -> 0
A71: Juan | B71: =SUMIF(Junio!$D$4:Junio!$D$103,A71,Junio!$E$4:Junio!$E$103) -> 0 | C71: =SUMIF(Junio!$D$4:Junio!$D$103,A71,Junio!$G$4:Junio!$G$103) -> 0 | D71: =SUMIF(Junio!$D$4:Junio!$D$103,A71,Junio!$I$4:Junio!$I$103) -> 0 | E71: =SUMIF(Junio!$D$4:Junio!$D$103,A71,Junio!$L$4:Junio!$L$103) -> 0 | F71: =SUMIF(Junio!$D$4:Junio!$D$103,A71,Junio!$M$4:Junio!$M$103) -> 0 | G71: =COUNTIF(Junio!$D$4:Junio!$D$103,A71) -> 0 | H71: =IF(G71=0,0,B71/G71) -> 0
A72: TOTAL | B72: =SUM(B65:B71) -> 0 | C72: =SUM(C65:C71) -> 0 | D72: =SUM(D65:D71) -> 0 | E72: =SUM(E65:E71) -> 0 | F72: =SUM(F65:F71) -> 0 | G72: =SUM(G65:G71) -> 0 | H72: =SUM(H65:H71) -> 0
A75: Comisiones - Julio
A76: Vendedor | B76: Total bruto ventas | C76: Total IVA | D76: Total comisiones bancarias | E76: Total comisiones vendedor | F76: Total neto tienda | G76: Nº ventas | H76: Ticket prom (bruto)
A77: Aaron | B77: =SUMIF(Julio!$D$4:Julio!$D$103,A77,Julio!$E$4:Julio!$E$103) -> 0 | C77: =SUMIF(Julio!$D$4:Julio!$D$103,A77,Julio!$G$4:Julio!$G$103) -> 0 | D77: =SUMIF(Julio!$D$4:Julio!$D$103,A77,Julio!$I$4:Julio!$I$103) -> 0 | E77: =SUMIF(Julio!$D$4:Julio!$D$103,A77,Julio!$L$4:Julio!$L$103) -> 0 | F77: =SUMIF(Julio!$D$4:Julio!$D$103,A77,Julio!$M$4:Julio!$M$103) -> 0 | G77: =COUNTIF(Julio!$D$4:Julio!$D$103,A77) -> 0 | H77: =IF(G77=0,0,B77/G77) -> 0
A78: Benja R | B78: =SUMIF(Julio!$D$4:Julio!$D$103,A78,Julio!$E$4:Julio!$E$103) -> 0 | C78: =SUMIF(Julio!$D$4:Julio!$D$103,A78,Julio!$G$4:Julio!$G$103) -> 0 | D78: =SUMIF(Julio!$D$4:Julio!$D$103,A78,Julio!$I$4:Julio!$I$103) -> 0 | E78: =SUMIF(Julio!$D$4:Julio!$D$103,A78,Julio!$L$4:Julio!$L$103) -> 0 | F78: =SUMIF(Julio!$D$4:Julio!$D$103,A78,Julio!$M$4:Julio!$M$103) -> 0 | G78: =COUNTIF(Julio!$D$4:Julio!$D$103,A78) -> 0 | H78: =IF(G78=0,0,B78/G78) -> 0
A79: Benja M | B79: =SUMIF(Julio!$D$4:Julio!$D$103,A79,Julio!$E$4:Julio!$E$103) -> 0 | C79: =SUMIF(Julio!$D$4:Julio!$D$103,A79,Julio!$G$4:Julio!$G$103) -> 0 | D79: =SUMIF(Julio!$D$4:Julio!$D$103,A79,Julio!$I$4:Julio!$I$103) -> 0 | E79: =SUMIF(Julio!$D$4:Julio!$D$103,A79,Julio!$L$4:Julio!$L$103) -> 0 | F79: =SUMIF(Julio!$D$4:Julio!$D$103,A79,Julio!$M$4:Julio!$M$103) -> 0 | G79: =COUNTIF(Julio!$D$4:Julio!$D$103,A79) -> 0 | H79: =IF(G79=0,0,B79/G79) -> 0
A80: Juanito | B80: =SUMIF(Julio!$D$4:Julio!$D$103,A80,Julio!$E$4:Julio!$E$103) -> 0 | C80: =SUMIF(Julio!$D$4:Julio!$D$103,A80,Julio!$G$4:Julio!$G$103) -> 0 | D80: =SUMIF(Julio!$D$4:Julio!$D$103,A80,Julio!$I$4:Julio!$I$103) -> 0 | E80: =SUMIF(Julio!$D$4:Julio!$D$103,A80,Julio!$L$4:Julio!$L$103) -> 0 | F80: =SUMIF(Julio!$D$4:Julio!$D$103,A80,Julio!$M$4:Julio!$M$103) -> 0 | G80: =COUNTIF(Julio!$D$4:Julio!$D$103,A80) -> 0 | H80: =IF(G80=0,0,B80/G80) -> 0
A81: Fabio | B81: =SUMIF(Julio!$D$4:Julio!$D$103,A81,Julio!$E$4:Julio!$E$103) -> 0 | C81: =SUMIF(Julio!$D$4:Julio!$D$103,A81,Julio!$G$4:Julio!$G$103) -> 0 | D81: =SUMIF(Julio!$D$4:Julio!$D$103,A81,Julio!$I$4:Julio!$I$103) -> 0 | E81: =SUMIF(Julio!$D$4:Julio!$D$103,A81,Julio!$L$4:Julio!$L$103) -> 0 | F81: =SUMIF(Julio!$D$4:Julio!$D$103,A81,Julio!$M$4:Julio!$M$103) -> 0 | G81: =COUNTIF(Julio!$D$4:Julio!$D$103,A81) -> 0 | H81: =IF(G81=0,0,B81/G81) -> 0
A82: Marenna | B82: =SUMIF(Julio!$D$4:Julio!$D$103,A82,Julio!$E$4:Julio!$E$103) -> 0 | C82: =SUMIF(Julio!$D$4:Julio!$D$103,A82,Julio!$G$4:Julio!$G$103) -> 0 | D82: =SUMIF(Julio!$D$4:Julio!$D$103,A82,Julio!$I$4:Julio!$I$103) -> 0 | E82: =SUMIF(Julio!$D$4:Julio!$D$103,A82,Julio!$L$4:Julio!$L$103) -> 0 | F82: =SUMIF(Julio!$D$4:Julio!$D$103,A82,Julio!$M$4:Julio!$M$103) -> 0 | G82: =COUNTIF(Julio!$D$4:Julio!$D$103,A82) -> 0 | H82: =IF(G82=0,0,B82/G82) -> 0
A83: Juan | B83: =SUMIF(Julio!$D$4:Julio!$D$103,A83,Julio!$E$4:Julio!$E$103) -> 0 | C83: =SUMIF(Julio!$D$4:Julio!$D$103,A83,Julio!$G$4:Julio!$G$103) -> 0 | D83: =SUMIF(Julio!$D$4:Julio!$D$103,A83,Julio!$I$4:Julio!$I$103) -> 0 | E83: =SUMIF(Julio!$D$4:Julio!$D$103,A83,Julio!$L$4:Julio!$L$103) -> 0 | F83: =SUMIF(Julio!$D$4:Julio!$D$103,A83,Julio!$M$4:Julio!$M$103) -> 0 | G83: =COUNTIF(Julio!$D$4:Julio!$D$103,A83) -> 0 | H83: =IF(G83=0,0,B83/G83) -> 0
A84: TOTAL | B84: =SUM(B77:B83) -> 0 | C84: =SUM(C77:C83) -> 0 | D84: =SUM(D77:D83) -> 0 | E84: =SUM(E77:E83) -> 0 | F84: =SUM(F77:F83) -> 0 | G84: =SUM(G77:G83) -> 0 | H84: =SUM(H77:H83) -> 0
A87: Comisiones - Agosto
A88: Vendedor | B88: Total bruto ventas | C88: Total IVA | D88: Total comisiones bancarias | E88: Total comisiones vendedor | F88: Total neto tienda | G88: Nº ventas | H88: Ticket prom (bruto)
A89: Aaron | B89: =SUMIF(Agosto!$D$4:Agosto!$D$103,A89,Agosto!$E$4:Agosto!$E$103) -> 0 | C89: =SUMIF(Agosto!$D$4:Agosto!$D$103,A89,Agosto!$G$4:Agosto!$G$103) -> 0 | D89: =SUMIF(Agosto!$D$4:Agosto!$D$103,A89,Agosto!$I$4:Agosto!$I$103) -> 0 | E89: =SUMIF(Agosto!$D$4:Agosto!$D$103,A89,Agosto!$L$4:Agosto!$L$103) -> 0 | F89: =SUMIF(Agosto!$D$4:Agosto!$D$103,A89,Agosto!$M$4:Agosto!$M$103) -> 0 | G89: =COUNTIF(Agosto!$D$4:Agosto!$D$103,A89) -> 0 | H89: =IF(G89=0,0,B89/G89) -> 0
A90: Benja R | B90: =SUMIF(Agosto!$D$4:Agosto!$D$103,A90,Agosto!$E$4:Agosto!$E$103) -> 0 | C90: =SUMIF(Agosto!$D$4:Agosto!$D$103,A90,Agosto!$G$4:Agosto!$G$103) -> 0 | D90: =SUMIF(Agosto!$D$4:Agosto!$D$103,A90,Agosto!$I$4:Agosto!$I$103) -> 0 | E90: =SUMIF(Agosto!$D$4:Agosto!$D$103,A90,Agosto!$L$4:Agosto!$L$103) -> 0 | F90: =SUMIF(Agosto!$D$4:Agosto!$D$103,A90,Agosto!$M$4:Agosto!$M$103) -> 0 | G90: =COUNTIF(Agosto!$D$4:Agosto!$D$103,A90) -> 0 | H90: =IF(G90=0,0,B90/G90) -> 0
A91: Benja M | B91: =SUMIF(Agosto!$D$4:Agosto!$D$103,A91,Agosto!$E$4:Agosto!$E$103) -> 0 | C91: =SUMIF(Agosto!$D$4:Agosto!$D$103,A91,Agosto!$G$4:Agosto!$G$103) -> 0 | D91: =SUMIF(Agosto!$D$4:Agosto!$D$103,A91,Agosto!$I$4:Agosto!$I$103) -> 0 | E91: =SUMIF(Agosto!$D$4:Agosto!$D$103,A91,Agosto!$L$4:Agosto!$L$103) -> 0 | F91: =SUMIF(Agosto!$D$4:Agosto!$D$103,A91,Agosto!$M$4:Agosto!$M$103) -> 0 | G91: =COUNTIF(Agosto!$D$4:Agosto!$D$103,A91) -> 0 | H91: =IF(G91=0,0,B91/G91) -> 0
A92: Juanito | B92: =SUMIF(Agosto!$D$4:Agosto!$D$103,A92,Agosto!$E$4:Agosto!$E$103) -> 0 | C92: =SUMIF(Agosto!$D$4:Agosto!$D$103,A92,Agosto!$G$4:Agosto!$G$103) -> 0 | D92: =SUMIF(Agosto!$D$4:Agosto!$D$103,A92,Agosto!$I$4:Agosto!$I$103) -> 0 | E92: =SUMIF(Agosto!$D$4:Agosto!$D$103,A92,Agosto!$L$4:Agosto!$L$103) -> 0 | F92: =SUMIF(Agosto!$D$4:Agosto!$D$103,A92,Agosto!$M$4:Agosto!$M$103) -> 0 | G92: =COUNTIF(Agosto!$D$4:Agosto!$D$103,A92) -> 0 | H92: =IF(G92=0,0,B92/G92) -> 0
A93: Fabio | B93: =SUMIF(Agosto!$D$4:Agosto!$D$103,A93,Agosto!$E$4:Agosto!$E$103) -> 0 | C93: =SUMIF(Agosto!$D$4:Agosto!$D$103,A93,Agosto!$G$4:Agosto!$G$103) -> 0 | D93: =SUMIF(Agosto!$D$4:Agosto!$D$103,A93,Agosto!$I$4:Agosto!$I$103) -> 0 | E93: =SUMIF(Agosto!$D$4:Agosto!$D$103,A93,Agosto!$L$4:Agosto!$L$103) -> 0 | F93: =SUMIF(Agosto!$D$4:Agosto!$D$103,A93,Agosto!$M$4:Agosto!$M$103) -> 0 | G93: =COUNTIF(Agosto!$D$4:Agosto!$D$103,A93) -> 0 | H93: =IF(G93=0,0,B93/G93) -> 0
A94: Marenna | B94: =SUMIF(Agosto!$D$4:Agosto!$D$103,A94,Agosto!$E$4:Agosto!$E$103) -> 0 | C94: =SUMIF(Agosto!$D$4:Agosto!$D$103,A94,Agosto!$G$4:Agosto!$G$103) -> 0 | D94: =SUMIF(Agosto!$D$4:Agosto!$D$103,A94,Agosto!$I$4:Agosto!$I$103) -> 0 | E94: =SUMIF(Agosto!$D$4:Agosto!$D$103,A94,Agosto!$L$4:Agosto!$L$103) -> 0 | F94: =SUMIF(Agosto!$D$4:Agosto!$D$103,A94,Agosto!$M$4:Agosto!$M$103) -> 0 | G94: =COUNTIF(Agosto!$D$4:Agosto!$D$103,A94) -> 0 | H94: =IF(G94=0,0,B94/G94) -> 0
A95: Juan | B95: =SUMIF(Agosto!$D$4:Agosto!$D$103,A95,Agosto!$E$4:Agosto!$E$103) -> 0 | C95: =SUMIF(Agosto!$D$4:Agosto!$D$103,A95,Agosto!$G$4:Agosto!$G$103) -> 0 | D95: =SUMIF(Agosto!$D$4:Agosto!$D$103,A95,Agosto!$I$4:Agosto!$I$103) -> 0 | E95: =SUMIF(Agosto!$D$4:Agosto!$D$103,A95,Agosto!$L$4:Agosto!$L$103) -> 0 | F95: =SUMIF(Agosto!$D$4:Agosto!$D$103,A95,Agosto!$M$4:Agosto!$M$103) -> 0 | G95: =COUNTIF(Agosto!$D$4:Agosto!$D$103,A95) -> 0 | H95: =IF(G95=0,0,B95/G95) -> 0
A96: TOTAL | B96: =SUM(B89:B95) -> 0 | C96: =SUM(C89:C95) -> 0 | D96: =SUM(D89:D95) -> 0 | E96: =SUM(E89:E95) -> 0 | F96: =SUM(F89:F95) -> 0 | G96: =SUM(G89:G95) -> 0 | H96: =SUM(H89:H95) -> 0
A99: Comisiones - Septiembre
A100: Vendedor | B100: Total bruto ventas | C100: Total IVA | D100: Total comisiones bancarias | E100: Total comisiones vendedor | F100: Total neto tienda | G100: Nº ventas | H100: Ticket prom (bruto)
A101: Aaron | B101: =SUMIF(Septiembre!$D$4:Septiembre!$D$103,A101,Septiembre!$E$4:Septiembre!$E$103) -> 0 | C101: =SUMIF(Septiembre!$D$4:Septiembre!$D$103,A101,Septiembre!$G$4:Septiembre!$G$103) -> 0 | D101: =SUMIF(Septiembre!$D$4:Septiembre!$D$103,A101,Septiembre!$I$4:Septiembre!$I$103) -> 0 | E101: =SUMIF(Septiembre!$D$4:Septiembre!$D$103,A101,Septiembre!$L$4:Septiembre!$L$103) -> 0 | F101: =SUMIF(Septiembre!$D$4:Septiembre!$D$103,A101,Septiembre!$M$4:Septiembre!$M$103) -> 0 | G101: =COUNTIF(Septiembre!$D$4:Septiembre!$D$103,A101) -> 0 | H101: =IF(G101=0,0,B101/G101) -> 0
A102: Benja R | B102: =SUMIF(Septiembre!$D$4:Septiembre!$D$103,A102,Septiembre!$E$4:Septiembre!$E$103) -> 0 | C102: =SUMIF(Septiembre!$D$4:Septiembre!$D$103,A102,Septiembre!$G$4:Septiembre!$G$103) -> 0 | D102: =SUMIF(Septiembre!$D$4:Septiembre!$D$103,A102,Septiembre!$I$4:Septiembre!$I$103) -> 0 | E102: =SUMIF(Septiembre!$D$4:Septiembre!$D$103,A102,Septiembre!$L$4:Septiembre!$L$103) -> 0 | F102: =SUMIF(Septiembre!$D$4:Septiembre!$D$103,A102,Septiembre!$M$4:Septiembre!$M$103) -> 0 | G102: =COUNTIF(Septiembre!$D$4:Septiembre!$D$103,A102) -> 0 | H102: =IF(G102=0,0,B102/G102) -> 0
A103: Benja M | B103: =SUMIF(Septiembre!$D$4:Septiembre!$D$103,A103,Septiembre!$E$4:Septiembre!$E$103) -> 0 | C103: =SUMIF(Septiembre!$D$4:Septiembre!$D$103,A103,Septiembre!$G$4:Septiembre!$G$103) -> 0 | D103: =SUMIF(Septiembre!$D$4:Septiembre!$D$103,A103,Septiembre!$I$4:Septiembre!$I$103) -> 0 | E103: =SUMIF(Septiembre!$D$4:Septiembre!$D$103,A103,Septiembre!$L$4:Septiembre!$L$103) -> 0 | F103: =SUMIF(Septiembre!$D$4:Septiembre!$D$103,A103,Septiembre!$M$4:Septiembre!$M$103) -> 0 | G103: =COUNTIF(Septiembre!$D$4:Septiembre!$D$103,A103) -> 0 | H103: =IF(G103=0,0,B103/G103) -> 0
A104: Juanito | B104: =SUMIF(Septiembre!$D$4:Septiembre!$D$103,A104,Septiembre!$E$4:Septiembre!$E$103) -> 0 | C104: =SUMIF(Septiembre!$D$4:Septiembre!$D$103,A104,Septiembre!$G$4:Septiembre!$G$103) -> 0 | D104: =SUMIF(Septiembre!$D$4:Septiembre!$D$103,A104,Septiembre!$I$4:Septiembre!$I$103) -> 0 | E104: =SUMIF(Septiembre!$D$4:Septiembre!$D$103,A104,Septiembre!$L$4:Septiembre!$L$103) -> 0 | F104: =SUMIF(Septiembre!$D$4:Septiembre!$D$103,A104,Septiembre!$M$4:Septiembre!$M$103) -> 0 | G104: =COUNTIF(Septiembre!$D$4:Septiembre!$D$103,A104) -> 0 | H104: =IF(G104=0,0,B104/G104) -> 0
A105: Fabio | B105: =SUMIF(Septiembre!$D$4:Septiembre!$D$103,A105,Septiembre!$E$4:Septiembre!$E$103) -> 0 | C105: =SUMIF(Septiembre!$D$4:Septiembre!$D$103,A105,Septiembre!$G$4:Septiembre!$G$103) -> 0 | D105: =SUMIF(Septiembre!$D$4:Septiembre!$D$103,A105,Septiembre!$I$4:Septiembre!$I$103) -> 0 | E105: =SUMIF(Septiembre!$D$4:Septiembre!$D$103,A105,Septiembre!$L$4:Septiembre!$L$103) -> 0 | F105: =SUMIF(Septiembre!$D$4:Septiembre!$D$103,A105,Septiembre!$M$4:Septiembre!$M$103) -> 0 | G105: =COUNTIF(Septiembre!$D$4:Septiembre!$D$103,A105) -> 0 | H105: =IF(G105=0,0,B105/G105) -> 0
A106: Marenna | B106: =SUMIF(Septiembre!$D$4:Septiembre!$D$103,A106,Septiembre!$E$4:Septiembre!$E$103) -> 0 | C106: =SUMIF(Septiembre!$D$4:Septiembre!$D$103,A106,Septiembre!$G$4:Septiembre!$G$103) -> 0 | D106: =SUMIF(Septiembre!$D$4:Septiembre!$D$103,A106,Septiembre!$I$4:Septiembre!$I$103) -> 0 | E106: =SUMIF(Septiembre!$D$4:Septiembre!$D$103,A106,Septiembre!$L$4:Septiembre!$L$103) -> 0 | F106: =SUMIF(Septiembre!$D$4:Septiembre!$D$103,A106,Septiembre!$M$4:Septiembre!$M$103) -> 0 | G106: =COUNTIF(Septiembre!$D$4:Septiembre!$D$103,A106) -> 0 | H106: =IF(G106=0,0,B106/G106) -> 0
A107: Juan | B107: =SUMIF(Septiembre!$D$4:Septiembre!$D$103,A107,Septiembre!$E$4:Septiembre!$E$103) -> 0 | C107: =SUMIF(Septiembre!$D$4:Septiembre!$D$103,A107,Septiembre!$G$4:Septiembre!$G$103) -> 0 | D107: =SUMIF(Septiembre!$D$4:Septiembre!$D$103,A107,Septiembre!$I$4:Septiembre!$I$103) -> 0 | E107: =SUMIF(Septiembre!$D$4:Septiembre!$D$103,A107,Septiembre!$L$4:Septiembre!$L$103) -> 0 | F107: =SUMIF(Septiembre!$D$4:Septiembre!$D$103,A107,Septiembre!$M$4:Septiembre!$M$103) -> 0 | G107: =COUNTIF(Septiembre!$D$4:Septiembre!$D$103,A107) -> 0 | H107: =IF(G107=0,0,B107/G107) -> 0
A108: TOTAL | B108: =SUM(B101:B107) -> 0 | C108: =SUM(C101:C107) -> 0 | D108: =SUM(D101:D107) -> 0 | E108: =SUM(E101:E107) -> 0 | F108: =SUM(F101:F107) -> 0 | G108: =SUM(G101:G107) -> 0 | H108: =SUM(H101:H107) -> 0
A111: Comisiones - Octubre
A112: Vendedor | B112: Total bruto ventas | C112: Total IVA | D112: Total comisiones bancarias | E112: Total comisiones vendedor | F112: Total neto tienda | G112: Nº ventas | H112: Ticket prom (bruto)
A113: Aaron | B113: =SUMIF(Octubre!$D$4:Octubre!$D$103,A113,Octubre!$E$4:Octubre!$E$103) -> 355000 | C113: =SUMIF(Octubre!$D$4:Octubre!$D$103,A113,Octubre!$G$4:Octubre!$G$103) -> 56680.672 | D113: =SUMIF(Octubre!$D$4:Octubre!$D$103,A113,Octubre!$I$4:Octubre!$I$103) -> 9852.5 | E113: =SUMIF(Octubre!$D$4:Octubre!$D$103,A113,Octubre!$L$4:Octubre!$L$103) -> 5278.9349 | F113: =SUMIF(Octubre!$D$4:Octubre!$D$103,A113,Octubre!$M$4:Octubre!$M$103) -> 283187.89 | G113: =COUNTIF(Octubre!$D$4:Octubre!$D$103,A113) -> 8 | H113: =IF(G113=0,0,B113/G113) -> 44375
A114: Benja R | B114: =SUMIF(Octubre!$D$4:Octubre!$D$103,A114,Octubre!$E$4:Octubre!$E$103) -> 848000 | C114: =SUMIF(Octubre!$D$4:Octubre!$D$103,A114,Octubre!$G$4:Octubre!$G$103) -> 29537.815 | D114: =SUMIF(Octubre!$D$4:Octubre!$D$103,A114,Octubre!$I$4:Octubre!$I$103) -> 5087.5 | E114: =SUMIF(Octubre!$D$4:Octubre!$D$103,A114,Octubre!$L$4:Octubre!$L$103) -> 43400 | F114: =SUMIF(Octubre!$D$4:Octubre!$D$103,A114,Octubre!$M$4:Octubre!$M$103) -> 769974.68 | G114: =COUNTIF(Octubre!$D$4:Octubre!$D$103,A114) -> 7 | H114: =IF(G114=0,0,B114/G114) -> 121142.86
A115: Benja M | B115: =SUMIF(Octubre!$D$4:Octubre!$D$103,A115,Octubre!$E$4:Octubre!$E$103) -> 279000 | C115: =SUMIF(Octubre!$D$4:Octubre!$D$103,A115,Octubre!$G$4:Octubre!$G$103) -> 19957.983 | D115: =SUMIF(Octubre!$D$4:Octubre!$D$103,A115,Octubre!$I$4:Octubre!$I$103) -> 3597.5 | E115: =SUMIF(Octubre!$D$4:Octubre!$D$103,A115,Octubre!$L$4:Octubre!$L$103) -> 5763.3445 | F115: =SUMIF(Octubre!$D$4:Octubre!$D$103,A115,Octubre!$M$4:Octubre!$M$103) -> 249681.17 | G115: =COUNTIF(Octubre!$D$4:Octubre!$D$103,A115) -> 5 | H115: =IF(G115=0,0,B115/G115) -> 55800
A116: Juanito | B116: =SUMIF(Octubre!$D$4:Octubre!$D$103,A116,Octubre!$E$4:Octubre!$E$103) -> 178000 | C116: =SUMIF(Octubre!$D$4:Octubre!$D$103,A116,Octubre!$G$4:Octubre!$G$103) -> 14050.42 | D116: =SUMIF(Octubre!$D$4:Octubre!$D$103,A116,Octubre!$I$4:Octubre!$I$103) -> 2420 | E116: =SUMIF(Octubre!$D$4:Octubre!$D$103,A116,Octubre!$L$4:Octubre!$L$103) -> 3150 | F116: =SUMIF(Octubre!$D$4:Octubre!$D$103,A116,Octubre!$M$4:Octubre!$M$103) -> 158379.58 | G116: =COUNTIF(Octubre!$D$4:Octubre!$D$103,A116) -> 4 | H116: =IF(G116=0,0,B116/G116) -> 44500
A117: Fabio | B117: =SUMIF(Octubre!$D$4:Octubre!$D$103,A117,Octubre!$E$4:Octubre!$E$103) -> 487000 | C117: =SUMIF(Octubre!$D$4:Octubre!$D$103,A117,Octubre!$G$4:Octubre!$G$103) -> 26663.866 | D117: =SUMIF(Octubre!$D$4:Octubre!$D$103,A117,Octubre!$I$4:Octubre!$I$103) -> 4692.5 | E117: =SUMIF(Octubre!$D$4:Octubre!$D$103,A117,Octubre!$L$4:Octubre!$L$103) -> 13396.345 | F117: =SUMIF(Octubre!$D$4:Octubre!$D$103,A117,Octubre!$M$4:Octubre!$M$103) -> 442247.29 | G117: =COUNTIF(Octubre!$D$4:Octubre!$D$103,A117) -> 11 | H117: =IF(G117=0,0,B117/G117) -> 44272.727
A118: Marenna | B118: =SUMIF(Octubre!$D$4:Octubre!$D$103,A118,Octubre!$E$4:Octubre!$E$103) -> 1304000 | C118: =SUMIF(Octubre!$D$4:Octubre!$D$103,A118,Octubre!$G$4:Octubre!$G$103) -> 112403.36 | D118: =SUMIF(Octubre!$D$4:Octubre!$D$103,A118,Octubre!$I$4:Octubre!$I$103) -> 20504 | E118: =SUMIF(Octubre!$D$4:Octubre!$D$103,A118,Octubre!$L$4:Octubre!$L$103) -> 70554.632 | F118: =SUMIF(Octubre!$D$4:Octubre!$D$103,A118,Octubre!$M$4:Octubre!$M$103) -> 1100538 | G118: =COUNTIF(Octubre!$D$4:Octubre!$D$103,A118) -> 15 | H118: =IF(G118=0,0,B118/G118) -> 86933.333
A119: Juan | B119: =SUMIF(Octubre!$D$4:Octubre!$D$103,A119,Octubre!$E$4:Octubre!$E$103) -> 25000 | C119: =SUMIF(Octubre!$D$4:Octubre!$D$103,A119,Octubre!$G$4:Octubre!$G$103) -> 0 | D119: =SUMIF(Octubre!$D$4:Octubre!$D$103,A119,Octubre!$I$4:Octubre!$I$103) -> 0 | E119: =SUMIF(Octubre!$D$4:Octubre!$D$103,A119,Octubre!$L$4:Octubre!$L$103) -> 0 | F119: =SUMIF(Octubre!$D$4:Octubre!$D$103,A119,Octubre!$M$4:Octubre!$M$103) -> 25000 | G119: =COUNTIF(Octubre!$D$4:Octubre!$D$103,A119) -> 1 | H119: =IF(G119=0,0,B119/G119) -> 25000
...

Sheet Mayo
A1: Mayo - Ingresos
P2: Total ventas brutas | Q2: =SUM(E4:E103) -> 2795000
A3: Nombre prenda | B3: Talla | C3: Propietario prenda | D3: Vendedor | E3: Precio venta (BRUTO) | F3: Tipo de pago | G3: IVA (19%) | H3: % comisión bancaria | I3: $ comisión bancaria | J3: Base comisión vendedor | K3: % comisión vendedor | L3: $ comisión vendedor | M3: Neto tienda | N3: Observaciones | O3: Marca (Tienda/externa) | P3: Total IVA ventas | Q3: =SUM(G4:G103) -> 18361.345
A4: bufanda burberry | B4: os | C4: Tienda | D4: Benja R | E4: 95000 | F4: Transferencia | G4: =IF(OR(F4="Débito",F4="Crédito",F4="Internet(Shopify)"),E4*19/119,0) -> 0 | H4: =IF(F4="Débito",0.0275,IF(F4="Crédito",0.0295,0)) -> 0 | I4: =E4*H4 -> 0 | J4: =E4-G4-I4 -> 95000 | K4: =IF($O4<>"Tienda",0,IF(OR($F4="Débito",$F4="Crédito"),0.05,IF(OR($F4="Efectivo",$F4="Transferencia"),0.07,0))) -> 0.07 | L4: =IF($O4<>"Tienda",0,$J4*$K4) -> 6650 | M4: =E4-G4-I4-L4 -> 88350 | N4: pagar 50.000 | O4: Tienda | P4: Total comisiones bancarias | Q4: =SUM(I4:I103) -> 550
A5: ballerinas ferragamo | B5: 38 | C5: Tienda | D5: Benja R | E5: 80000 | F5: Transferencia | G5: =IF(OR(F5="Débito",F5="Crédito",F5="Internet(Shopify)"),E5*19/119,0) -> 0 | H5: =IF(F5="Débito",0.0275,IF(F5="Crédito",0.0295,0)) -> 0 | I5: =E5*H5 -> 0 | J5: =E5-G5-I5 -> 80000 | K5: =IF($O5<>"Tienda",0,IF(OR($F5="Débito",$F5="Crédito"),0.05,IF(OR($F5="Efectivo",$F5="Transferencia"),0.07,0))) -> 0.07 | L5: =IF($O5<>"Tienda",0,$J5*$K5) -> 5600 | M5: =E5-G5-I5-L5 -> 74400 | N5: pagar benja 15.000 | O5: Tienda | P5: Total comisiones vendedores (NO se divide) | Q5: =SUM(L4:L103) -> 156562.84
A6: lentes louis vuitton | B6: os | C6: Tienda | D6: Benja R | E6: 180000 | F6: Transferencia | G6: =IF(OR(F6="Débito",F6="Crédito",F6="Internet(Shopify)"),E6*19/119,0) -> 0 | H6: =IF(F6="Débito",0.0275,IF(F6="Crédito",0.0295,0)) -> 0 | I6: =E6*H6 -> 0 | J6: =E6-G6-I6 -> 180000 | K6: =IF($O6<>"Tienda",0,IF(OR($F6="Débito",$F6="Crédito"),0.05,IF(OR($F6="Efectivo",$F6="Transferencia"),0.07,0))) -> 0 | L6: =IF($O6<>"Tienda",0,$J6*$K6) -> 0 | M6: =E6-G6-I6-L6 -> 180000 | P6: Total neto tienda (NO se divide) | Q6: =SUM(M4:M103) -> 2619525.8
A7: zapatillas comme des garcon | B7: 37 | C7: Tienda | D7: Benja R | E7: 80000 | F7: Transferencia | G7: =IF(OR(F7="Débito",F7="Crédito",F7="Internet(Shopify)"),E7*19/119,0) -> 0 | H7: =IF(F7="Débito",0.0275,IF(F7="Crédito",0.0295,0)) -> 0 | I7: =E7*H7 -> 0 | J7: =E7-G7-I7 -> 80000 | K7: =IF($O7<>"Tienda",0,IF(OR($F7="Débito",$F7="Crédito"),0.05,IF(OR($F7="Efectivo",$F7="Transferencia"),0.07,0))) -> 0 | L7: =IF($O7<>"Tienda",0,$J7*$K7) -> 0 | M7: =E7-G7-I7-L7 -> 80000 | P7: Número de ventas | Q7: =COUNTA(E4:E103) -> 28
A8: polera jpg mesh | B8: L | C8: Tienda | D8: Benja R | E8: 95000 | F8: Transferencia | G8: =IF(OR(F8="Débito",F8="Crédito",F8="Internet(Shopify)"),E8*19/119,0) -> 0 | H8: =IF(F8="Débito",0.0275,IF(F8="Crédito",0.0295,0)) -> 0 | I8: =E8*H8 -> 0 | J8: =E8-G8-I8 -> 95000 | K8: =IF($O8<>"Tienda",0,IF(OR($F8="Débito",$F8="Crédito"),0.05,IF(OR($F8="Efectivo",$F8="Transferencia"),0.07,0))) -> 0.07 | L8: =IF($O8<>"Tienda",0,$J8*$K8) -> 6650 | M8: =E8-G8-I8-L8 -> 88350 | N8: pagar 40.000 vicente | O8: Tienda | P8: Ticket promedio (NETO) | Q8: =IF(Q7=0,0,Q6/Q7) -> 93554.494
A9: Cartera LV | C9: Tienda | D9: Benja R | E9: 95000 | F9: Internet(Shopify) | G9: =IF(OR(F9="Débito",F9="Crédito",F9="Internet(Shopify)"),E9*19/119,0) -> 15168.067 | H9: =IF(F9="Débito",0.0275,IF(F9="Crédito",0.0295,0)) -> 0 | I9: =E9*H9 -> 0 | J9: =E9-G9-I9 -> 79831.933 | K9: =IF($O9<>"Tienda",0,IF(OR($F9="Débito",$F9="Crédito"),0.05,IF(OR($F9="Efectivo",$F9="Transferencia"),0.07,0))) -> 0 | L9: =IF($O9<>"Tienda",0,$J9*$K9) -> 0 | M9: =E9-G9-I9-L9 -> 79831.933 | O9: Tienda | P9: Ventas débito (neto) | Q9: =SUMIF(F4:F103,"Débito",M4:M103) -> 15443.887
A10: Lentes Dior | C10: Tienda | D10: Benja R | E10: 280000 | F10: Transferencia | G10: =IF(OR(F10="Débito",F10="Crédito",F10="Internet(Shopify)"),E10*19/119,0) -> 0 | H10: =IF(F10="Débito",0.0275,IF(F10="Crédito",0.0295,0)) -> 0 | I10: =E10*H10 -> 0 | J10: =E10-G10-I10 -> 280000 | K10: =IF($O10<>"Tienda",0,IF(OR($F10="Débito",$F10="Crédito"),0.05,IF(OR($F10="Efectivo",$F10="Transferencia"),0.07,0))) -> 0.07 | L10: =IF($O10<>"Tienda",0,$J10*$K10) -> 19600 | M10: =E10-G10-I10-L10 -> 260400 | O10: Tienda | P10: Ventas crédito (neto) | Q10: =SUMIF(F4:F103,"Crédito",M4:M103) -> 0
A11: Lentes LV | C11: Tienda | D11: Fabio | E11: 350000 | F11: Transferencia | G11: =IF(OR(F11="Débito",F11="Crédito",F11="Internet(Shopify)"),E11*19/119,0) -> 0 | H11: =IF(F11="Débito",0.0275,IF(F11="Crédito",0.0295,0)) -> 0 | I11: =E11*H11 -> 0 | J11: =E11-G11-I11 -> 350000 | K11: =IF($O11<>"Tienda",0,IF(OR($F11="Débito",$F11="Crédito"),0.05,IF(OR($F11="Efectivo",$F11="Transferencia"),0.07,0))) -> 0.07 | L11: =IF($O11<>"Tienda",0,$J11*$K11) -> 24500 | M11: =E11-G11-I11-L11 -> 325500 | N11: Moai Influencer 220.000 | O11: Tienda | P11: Ventas efectivo (neto) | Q11: =SUMIF(F4:F103,"Efectivo",M4:M103) -> 0
A12: Billetera VVW | C12: Fabio | D12: Benja R | E12: 120000 | F12: Transferencia | G12: =IF(OR(F12="Débito",F12="Crédito",F12="Internet(Shopify)"),E12*19/119,0) -> 0 | H12: =IF(F12="Débito",0.0275,IF(F12="Crédito",0.0295,0)) -> 0 | I12: =E12*H12 -> 0 | J12: =E12-G12-I12 -> 120000 | K12: =IF($O12<>"Tienda",0,IF(OR($F12="Débito",$F12="Crédito"),0.05,IF(OR($F12="Efectivo",$F12="Transferencia"),0.07,0))) -> 0.07 | L12: =IF($O12<>"Tienda",0,$J12*$K12) -> 8400 | M12: =E12-G12-I12-L12 -> 111600 | O12: Tienda | P12: Ventas transferencia (neto) | Q12: =SUMIF(F4:F103,"Transferencia",M4:M103) -> 2524250
A13: Billetera VVW | C13: Tienda | D13: Benja R | E13: 60000 | F13: Transferencia | G13: =IF(OR(F13="Débito",F13="Crédito",F13="Internet(Shopify)"),E13*19/119,0) -> 0 | H13: =IF(F13="Débito",0.0275,IF(F13="Crédito",0.0295,0)) -> 0 | I13: =E13*H13 -> 0 | J13: =E13-G13-I13 -> 60000 | K13: =IF($O13<>"Tienda",0,IF(OR($F13="Débito",$F13="Crédito"),0.05,IF(OR($F13="Efectivo",$F13="Transferencia"),0.07,0))) -> 0.07 | L13: =IF($O13<>"Tienda",0,$J13*$K13) -> 4200 | M13: =E13-G13-I13-L13 -> 55800 | O13: Tienda | P13: Ventas Internet(Shopify) (neto) | Q13: =SUMIF(F4:F103,"Internet(Shopify)",M4:M103) -> 79831.933
A14: Polera Bully | B14: M | C14: Tienda | D14: Benja R | E14: 25000 | F14: Transferencia | G14: =IF(OR(F14="Débito",F14="Crédito",F14="Internet(Shopify)"),E14*19/119,0) -> 0 | H14: =IF(F14="Débito",0.0275,IF(F14="Crédito",0.0295,0)) -> 0 | I14: =E14*H14 -> 0 | J14: =E14-G14-I14 -> 25000 | K14: =IF($O14<>"Tienda",0,IF(OR($F14="Débito",$F14="Crédito"),0.05,IF(OR($F14="Efectivo",$F14="Transferencia"),0.07,0))) -> 0 | L14: =IF($O14<>"Tienda",0,$J14*$K14) -> 0 | M14: =E14-G14-I14-L14 -> 25000 | N14: Pop Disaster 18.750 | O14: Pop disaster | P14: Ventas cuenta común (D+C+T) NETO | Q14: =SUMIF(F4:F103,"Débito",M4:M103)+SUMIF(F4:F103,"Crédito",M4:M103)+SUMIF(F4:F103,"Transferencia",M4:M103) -> 2539693.9
A15: Jacket Y-3 | C15: Consignacion | D15: Aaron | E15: 95000 | F15: Transferencia | G15: =IF(OR(F15="Débito",F15="Crédito",F15="Internet(Shopify)"),E15*19/119,0) -> 0 | H15: =IF(F15="Débito",0.0275,IF(F15="Crédito",0.0295,0)) -> 0 | I15: =E15*H15 -> 0 | J15: =E15-G15-I15 -> 95000 | K15: =IF($O15<>"Tienda",0,IF(OR($F15="Débito",$F15="Crédito"),0.05,IF(OR($F15="Efectivo",$F15="Transferencia"),0.07,0))) -> 0.07 | L15: =IF($O15<>"Tienda",0,$J15*$K15) -> 6650 | M15: =E15-G15-I15-L15 -> 88350 | N15: Pagar 20.000 amigo Julian | O15: Tienda | P15: IVA compras (manual)
A16: Polera Evisu | C16: Tienda | D16: Aaron | E16: 15000 | F16: Transferencia | G16: =IF(OR(F16="Débito",F16="Crédito",F16="Internet(Shopify)"),E16*19/119,0) -> 0 | H16: =IF(F16="Débito",0.0275,IF(F16="Crédito",0.0295,0)) -> 0 | I16: =E16*H16 -> 0 | J16: =E16-G16-I16 -> 15000 | K16: =IF($O16<>"Tienda",0,IF(OR($F16="Débito",$F16="Crédito"),0.05,IF(OR($F16="Efectivo",$F16="Transferencia"),0.07,0))) -> 0.07 | L16: =IF($O16<>"Tienda",0,$J16*$K16) -> 1050 | M16: =E16-G16-I16-L16 -> 13950 | O16: Tienda | P16: IVA neto (ventas - compras) | Q16: =Q3-Q15 -> 18361.345
A17: Sweater MMG Maison Margiela | B17: M | C17: Tienda | D17: Benja R | E17: 300000 | F17: Transferencia | G17: =IF(OR(F17="Débito",F17="Crédito",F17="Internet(Shopify)"),E17*19/119,0) -> 0 | H17: =IF(F17="Débito",0.0275,IF(F17="Crédito",0.0295,0)) -> 0 | I17: =E17*H17 -> 0 | J17: =E17-G17-I17 -> 300000 | K17: =IF($O17<>"Tienda",0,IF(OR($F17="Débito",$F17="Crédito"),0.05,IF(OR($F17="Efectivo",$F17="Transferencia"),0.07,0))) -> 0.07 | L17: =IF($O17<>"Tienda",0,$J17*$K17) -> 21000 | M17: =E17-G17-I17-L17 -> 279000 | O17: Tienda | P17: TOTAL PAGOS/CONSIGNACION/MARCAS | Q17: =50000+15000+40000+220000+18750+20000+15000+22500+45000+15000 -> 461250
A18: Chaqueta Diesel | B18: L | C18: Tienda | D18: Benja R | E18: 80000 | F18: Transferencia | G18: =IF(OR(F18="Débito",F18="Crédito",F18="Internet(Shopify)"),E18*19/119,0) -> 0 | H18: =IF(F18="Débito",0.0275,IF(F18="Crédito",0.0295,0)) -> 0 | I18: =E18*H18 -> 0 | J18: =E18-G18-I18 -> 80000 | K18: =IF($O18<>"Tienda",0,IF(OR($F18="Débito",$F18="Crédito"),0.05,IF(OR($F18="Efectivo",$F18="Transferencia"),0.07,0))) -> 0.07 | L18: =IF($O18<>"Tienda",0,$J18*$K18) -> 5600 | M18: =E18-G18-I18-L18 -> 74400 | O18: Tienda | P18: Total Liquido | Q18: =Q6-Q17 -> 2158275.8
A19: Camiseta Dormund | C19: Fabio | D19: Benja R | E19: 20000 | F19: Débito | G19: =IF(OR(F19="Débito",F19="Crédito",F19="Internet(Shopify)"),E19*19/119,0) -> 3193.2773 | H19: =IF(F19="Débito",0.0275,IF(F19="Crédito",0.0295,0)) -> 0.0275 | I19: =E19*H19 -> 550 | J19: =E19-G19-I19 -> 16256.723 | K19: =IF($O19<>"Tienda",0,IF(OR($F19="Débito",$F19="Crédito"),0.05,IF(OR($F19="Efectivo",$F19="Transferencia"),0.07,0))) -> 0.05 | L19: =IF($O19<>"Tienda",0,$J19*$K19) -> 812.83613 | M19: =E19-G19-I19-L19 -> 15443.887 | O19: Tienda
A20: Cinturon D&G | C20: Tienda | D20: Benja R | E20: 120000 | F20: Transferencia | G20: =IF(OR(F20="Débito",F20="Crédito",F20="Internet(Shopify)"),E20*19/119,0) -> 0 | H20: =IF(F20="Débito",0.0275,IF(F20="Crédito",0.0295,0)) -> 0 | I20: =E20*H20 -> 0 | J20: =E20-G20-I20 -> 120000 | K20: =IF($O20<>"Tienda",0,IF(OR($F20="Débito",$F20="Crédito"),0.05,IF(OR($F20="Efectivo",$F20="Transferencia"),0.07,0))) -> 0.07 | L20: =IF($O20<>"Tienda",0,$J20*$K20) -> 8400 | M20: =E20-G20-I20-L20 -> 111600 | O20: Tienda
A21: Bufanda Gris Negra | B21: s | C21: Tienda | D21: Benja R | E21: 20000 | F21: Transferencia | G21: =IF(OR(F21="Débito",F21="Crédito",F21="Internet(Shopify)"),E21*19/119,0) -> 0 | H21: =IF(F21="Débito",0.0275,IF(F21="Crédito",0.0295,0)) -> 0 | I21: =E21*H21 -> 0 | J21: =E21-G21-I21 -> 20000 | K21: =IF($O21<>"Tienda",0,IF(OR($F21="Débito",$F21="Crédito"),0.05,IF(OR($F21="Efectivo",$F21="Transferencia"),0.07,0))) -> 0 | L21: =IF($O21<>"Tienda",0,$J21*$K21) -> 0 | M21: =E21-G21-I21-L21 -> 20000 | N21: Pop Disaster 15.000 | O21: Pop disaster
A22: Polera Sin Mangas | B22: s | C22: Tienda | D22: Benja R | E22: 30000 | F22: Transferencia | G22: =IF(OR(F22="Débito",F22="Crédito",F22="Internet(Shopify)"),E22*19/119,0) -> 0 | H22: =IF(F22="Débito",0.0275,IF(F22="Crédito",0.0295,0)) -> 0 | I22: =E22*H22 -> 0 | J22: =E22-G22-I22 -> 30000 | K22: =IF($O22<>"Tienda",0,IF(OR($F22="Débito",$F22="Crédito"),0.05,IF(OR($F22="Efectivo",$F22="Transferencia"),0.07,0))) -> 0 | L22: =IF($O22<>"Tienda",0,$J22*$K22) -> 0 | M22: =E22-G22-I22-L22 -> 30000 | N22: Pedritos 22.500 | O22: Pedritos
A23: Crewneck Acne Studio | B23: Xl | C23: Tienda | E23: 90000 | F23: Transferencia | G23: =IF(OR(F23="Débito",F23="Crédito",F23="Internet(Shopify)"),E23*19/119,0) -> 0 | H23: =IF(F23="Débito",0.0275,IF(F23="Crédito",0.0295,0)) -> 0 | I23: =E23*H23 -> 0 | J23: =E23-G23-I23 -> 90000 | K23: =IF($O23<>"Tienda",0,IF(OR($F23="Débito",$F23="Crédito"),0.05,IF(OR($F23="Efectivo",$F23="Transferencia"),0.07,0))) -> 0.07 | L23: =IF($O23<>"Tienda",0,$J23*$K23) -> 6300 | M23: =E23-G23-I23-L23 -> 83700 | N23: Michelle | O23: Tienda
A24: Pulsera Plata | B24: os | C24: Fabio | E24: 30000 | F24: Transferencia | G24: =IF(OR(F24="Débito",F24="Crédito",F24="Internet(Shopify)"),E24*19/119,0) -> 0 | H24: =IF(F24="Débito",0.0275,IF(F24="Crédito",0.0295,0)) -> 0 | I24: =E24*H24 -> 0 | J24: =E24-G24-I24 -> 30000 | K24: =IF($O24<>"Tienda",0,IF(OR($F24="Débito",$F24="Crédito"),0.05,IF(OR($F24="Efectivo",$F24="Transferencia"),0.07,0))) -> 0.07 | L24: =IF($O24<>"Tienda",0,$J24*$K24) -> 2100 | M24: =E24-G24-I24-L24 -> 27900 | N24: Michelle | O24: Tienda
A25: Jack Cactus Polera | B25: L | C25: Tienda | D25: Marenna | E25: 30000 | F25: Transferencia | G25: =IF(OR(F25="Débito",F25="Crédito",F25="Internet(Shopify)"),E25*19/119,0) -> 0 | H25: =IF(F25="Débito",0.0275,IF(F25="Crédito",0.0295,0)) -> 0 | I25: =E25*H25 -> 0 | J25: =E25-G25-I25 -> 30000 | K25: =IF($O25<>"Tienda",0,IF(OR($F25="Débito",$F25="Crédito"),0.05,IF(OR($F25="Efectivo",$F25="Transferencia"),0.07,0))) -> 0.07 | L25: =IF($O25<>"Tienda",0,$J25*$K25) -> 2100 | M25: =E25-G25-I25-L25 -> 27900 | O25: Tienda
A26: Blaizer Maison Margiela | C26: Tienda | D26: Aaron | E26: 250000 | F26: Transferencia | G26: =IF(OR(F26="Débito",F26="Crédito",F26="Internet(Shopify)"),E26*19/119,0) -> 0 | H26: =IF(F26="Débito",0.0275,IF(F26="Crédito",0.0295,0)) -> 0 | I26: =E26*H26 -> 0 | J26: =E26-G26-I26 -> 250000 | K26: =IF($O26<>"Tienda",0,IF(OR($F26="Débito",$F26="Crédito"),0.05,IF(OR($F26="Efectivo",$F26="Transferencia"),0.07,0))) -> 0.07 | L26: =IF($O26<>"Tienda",0,$J26*$K26) -> 17500 | M26: =E26-G26-I26-L26 -> 232500 | O26: Tienda
A27: Poleron Encaje S.Archive | B27: s | C27: Tienda | D27: Marenna | E27: 60000 | F27: Transferencia | G27: =IF(OR(F27="Débito",F27="Crédito",F27="Internet(Shopify)"),E27*19/119,0) -> 0 | H27: =IF(F27="Débito",0.0275,IF(F27="Crédito",0.0295,0)) -> 0 | I27: =E27*H27 -> 0 | J27: =E27-G27-I27 -> 60000 | K27: =IF($O27<>"Tienda",0,IF(OR($F27="Débito",$F27="Crédito"),0.05,IF(OR($F27="Efectivo",$F27="Transferencia"),0.07,0))) -> 0 | L27: =IF($O27<>"Tienda",0,$J27*$K27) -> 0 | M27: =E27-G27-I27-L27 -> 60000 | N27: Season Archive 45.000 | O27: Season Archive
A28: Pusera Fabinho | B28: os | C28: Fabio | D28: Marenna | E28: 25000 | F28: Transferencia | G28: =IF(OR(F28="Débito",F28="Crédito",F28="Internet(Shopify)"),E28*19/119,0) -> 0 | H28: =IF(F28="Débito",0.0275,IF(F28="Crédito",0.0295,0)) -> 0 | I28: =E28*H28 -> 0 | J28: =E28-G28-I28 -> 25000 | K28: =IF($O28<>"Tienda",0,IF(OR($F28="Débito",$F28="Crédito"),0.05,IF(OR($F28="Efectivo",$F28="Transferencia"),0.07,0))) -> 0.07 | L28: =IF($O28<>"Tienda",0,$J28*$K28) -> 1750 | M28: =E28-G28-I28-L28 -> 23250 | O28: Tienda
A29: Lentes Chanel | C29: Benja R | D29: Marenna | E29: 110000 | F29: Transferencia | G29: =IF(OR(F29="Débito",F29="Crédito",F29="Internet(Shopify)"),E29*19/119,0) -> 0 | H29: =IF(F29="Débito",0.0275,IF(F29="Crédito",0.0295,0)) -> 0 | I29: =E29*H29 -> 0 | J29: =E29-G29-I29 -> 110000 | K29: =IF($O29<>"Tienda",0,IF(OR($F29="Débito",$F29="Crédito"),0.05,IF(OR($F29="Efectivo",$F29="Transferencia"),0.07,0))) -> 0.07 | L29: =IF($O29<>"Tienda",0,$J29*$K29) -> 7700 | M29: =E29-G29-I29-L29 -> 102300 | O29: Tienda
A30: Bufanda P. Disaster | C30: Tienda | D30: Marenna | E30: 20000 | F30: Transferencia | G30: =IF(OR(F30="Débito",F30="Crédito",F30="Internet(Shopify)"),E30*19/119,0) -> 0 | H30: =IF(F30="Débito",0.0275,IF(F30="Crédito",0.0295,0)) -> 0 | I30: =E30*H30 -> 0 | J30: =E30-G30-I30 -> 20000 | K30: =IF($O30<>"Tienda",0,IF(OR($F30="Débito",$F30="Crédito"),0.05,IF(OR($F30="Efectivo",$F30="Transferencia"),0.07,0))) -> 0 | L30: =IF($O30<>"Tienda",0,$J30*$K30) -> 0 | M30: =E30-G30-I30-L30 -> 20000 | N30: Pop Disaster 15.000 | O30: Pop disaster
A31: Billetera Lv | C31: Tienda | D31: Marenna | E31: 40000 | F31: Transferencia | G31: =IF(OR(F31="Débito",F31="Crédito",F31="Internet(Shopify)"),E31*19/119,0) -> 0 | H31: =IF(F31="Débito",0.0275,IF(F31="Crédito",0.0295,0)) -> 0 | I31: =E31*H31 -> 0 | J31: =E31-G31-I31 -> 40000 | K31: =IF($O31<>"Tienda",0,IF(OR($F31="Débito",$F31="Crédito"),0.05,IF(OR($F31="Efectivo",$F31="Transferencia"),0.07,0))) -> 0 | L31: =IF($O31<>"Tienda",0,$J31*$K31) -> 0 | M31: =E31-G31-I31-L31 -> 40000
G32: =IF(OR(F32="Débito",F32="Crédito",F32="Internet(Shopify)"),E32*19/119,0) -> 0 | H32: =IF(F32="Débito",0.0275,IF(F32="Crédito",0.0295,0)) -> 0 | I32: =E32*H32 -> 0 | J32: =E32-G32-I32 -> 0 | K32: =IF($O32<>"Tienda",0,IF(OR($F32="Débito",$F32="Crédito"),0.05,IF(OR($F32="Efectivo",$F32="Transferencia"),0.07,0))) -> 0 | L32: =IF($O32<>"Tienda",0,$J32*$K32) -> 0 | M32: =E32-G32-I32-L32 -> 0
G33: =IF(OR(F33="Débito",F33="Crédito",F33="Internet(Shopify)"),E33*19/119,0) -> 0 | H33: =IF(F33="Débito",0.0275,IF(F33="Crédito",0.0295,0)) -> 0 | I33: =E33*H33 -> 0 | J33: =E33-G33-I33 -> 0 | K33: =IF($O33<>"Tienda",0,IF(OR($F33="Débito",$F33="Crédito"),0.05,IF(OR($F33="Efectivo",$F33="Transferencia"),0.07,0))) -> 0 | L33: =IF($O33<>"Tienda",0,$J33*$K33) -> 0 | M33: =E33-G33-I33-L33 -> 0
G34: =IF(OR(F34="Débito",F34="Crédito",F34="Internet(Shopify)"),E34*19/119,0) -> 0 | H34: =IF(F34="Débito",0.0275,IF(F34="Crédito",0.0295,0)) -> 0 | I34: =E34*H34 -> 0 | J34: =E34-G34-I34 -> 0 | K34: =IF($O34<>"Tienda",0,IF(OR($F34="Débito",$F34="Crédito"),0.05,IF(OR($F34="Efectivo",$F34="Transferencia"),0.07,0))) -> 0 | L34: =IF($O34<>"Tienda",0,$J34*$K34) -> 0 | M34: =E34-G34-I34-L34 -> 0
G35: =IF(OR(F35="Débito",F35="Crédito",F35="Internet(Shopify)"),E35*19/119,0) -> 0 | H35: =IF(F35="Débito",0.0275,IF(F35="Crédito",0.0295,0)) -> 0 | I35: =E35*H35 -> 0 | J35: =E35-G35-I35 -> 0 | K35: =IF($O35<>"Tienda",0,IF(OR($F35="Débito",$F35="Crédito"),0.05,IF(OR($F35="Efectivo",$F35="Transferencia"),0.07,0))) -> 0 | L35: =IF($O35<>"Tienda",0,$J35*$K35) -> 0 | M35: =E35-G35-I35-L35 -> 0
G36: =IF(OR(F36="Débito",F36="Crédito",F36="Internet(Shopify)"),E36*19/119,0) -> 0 | H36: =IF(F36="Débito",0.0275,IF(F36="Crédito",0.0295,0)) -> 0 | I36: =E36*H36 -> 0 | J36: =E36-G36-I36 -> 0 | K36: =IF($O36<>"Tienda",0,IF(OR($F36="Débito",$F36="Crédito"),0.05,IF(OR($F36="Efectivo",$F36="Transferencia"),0.07,0))) -> 0 | L36: =IF($O36<>"Tienda",0,$J36*$K36) -> 0 | M36: =E36-G36-I36-L36 -> 0
G37: =IF(OR(F37="Débito",F37="Crédito",F37="Internet(Shopify)"),E37*19/119,0) -> 0 | H37: =IF(F37="Débito",0.0275,IF(F37="Crédito",0.0295,0)) -> 0 | I37: =E37*H37 -> 0 | J37: =E37-G37-I37 -> 0 | K37: =IF($O37<>"Tienda",0,IF(OR($F37="Débito",$F37="Crédito"),0.05,IF(OR($F37="Efectivo",$F37="Transferencia"),0.07,0))) -> 0 | L37: =IF($O37<>"Tienda",0,$J37*$K37) -> 0 | M37: =E37-G37-I37-L37 -> 0
G38: =IF(OR(F38="Débito",F38="Crédito",F38="Internet(Shopify)"),E38*19/119,0) -> 0 | H38: =IF(F38="Débito",0.0275,IF(F38="Crédito",0.0295,0)) -> 0 | I38: =E38*H38 -> 0 | J38: =E38-G38-I38 -> 0 | K38: =IF($O38<>"Tienda",0,IF(OR($F38="Débito",$F38="Crédito"),0.05,IF(OR($F38="Efectivo",$F38="Transferencia"),0.07,0))) -> 0 | L38: =IF($O38<>"Tienda",0,$J38*$K38) -> 0 | M38: =E38-G38-I38-L38 -> 0
G39: =IF(OR(F39="Débito",F39="Crédito",F39="Internet(Shopify)"),E39*19/119,0) -> 0 | H39: =IF(F39="Débito",0.0275,IF(F39="Crédito",0.0295,0)) -> 0 | I39: =E39*H39 -> 0 | J39: =E39-G39-I39 -> 0 | K39: =IF($O39<>"Tienda",0,IF(OR($F39="Débito",$F39="Crédito"),0.05,IF(OR($F39="Efectivo",$F39="Transferencia"),0.07,0))) -> 0 | L39: =IF($O39<>"Tienda",0,$J39*$K39) -> 0 | M39: =E39-G39-I39-L39 -> 0
G40: =IF(OR(F40="Débito",F40="Crédito",F40="Internet(Shopify)"),E40*19/119,0) -> 0 | H40: =IF(F40="Débito",0.0275,IF(F40="Crédito",0.0295,0)) -> 0 | I40: =E40*H40 -> 0 | J40: =E40-G40-I40 -> 0 | K40: =IF($O40<>"Tienda",0,IF(OR($F40="Débito",$F40="Crédito"),0.05,IF(OR($F40="Efectivo",$F40="Transferencia"),0.07,0))) -> 0 | L40: =IF($O40<>"Tienda",0,$J40*$K40) -> 0 | M40: =E40-G40-I40-L40 -> 0
G41: =IF(OR(F41="Débito",F41="Crédito",F41="Internet(Shopify)"),E41*19/119,0) -> 0 | H41: =IF(F41="Débito",0.0275,IF(F41="Crédito",0.0295,0)) -> 0 | I41: =E41*H41 -> 0 | J41: =E41-G41-I41 -> 0 | K41: =IF($O41<>"Tienda",0,IF(OR($F41="Débito",$F41="Crédito"),0.05,IF(OR($F41="Efectivo",$F41="Transferencia"),0.07,0))) -> 0 | L41: =IF($O41<>"Tienda",0,$J41*$K41) -> 0 | M41: =E41-G41-I41-L41 -> 0
G42: =IF(OR(F42="Débito",F42="Crédito",F42="Internet(Shopify)"),E42*19/119,0) -> 0 | H42: =IF(F42="Débito",0.0275,IF(F42="Crédito",0.0295,0)) -> 0 | I42: =E42*H42 -> 0 | J42: =E42-G42-I42 -> 0 | K42: =IF($O42<>"Tienda",0,IF(OR($F42="Débito",$F42="Crédito"),0.05,IF(OR($F42="Efectivo",$F42="Transferencia"),0.07,0))) -> 0 | L42: =IF($O42<>"Tienda",0,$J42*$K42) -> 0 | M42: =E42-G42-I42-L42 -> 0
G43: =IF(OR(F43="Débito",F43="Crédito",F43="Internet(Shopify)"),E43*19/119,0) -> 0 | H43: =IF(F43="Débito",0.0275,IF(F43="Crédito",0.0295,0)) -> 0 | I43: =E43*H43 -> 0 | J43: =E43-G43-I43 -> 0 | K43: =IF($O43<>"Tienda",0,IF(OR($F43="Débito",$F43="Crédito"),0.05,IF(OR($F43="Efectivo",$F43="Transferencia"),0.07,0))) -> 0 | L43: =IF($O43<>"Tienda",0,$J43*$K43) -> 0 | M43: =E43-G43-I43-L43 -> 0
... G103: =IF(OR(F103="Débito",F103="Crédito",F103="Internet(Shopify)"),E103*19/119,0) -> 0 | H103: =IF(F103="Débito",0.0275,IF(F103="Crédito",0.0295,0)) -> 0 | I103: =E103*H103 -> 0 | J103: =E103-G103-I103 -> 0 | K103: =IF($O103<>"Tienda",0,IF(OR($F103="Débito",$F103="Crédito"),0.05,IF(OR($F103="Efectivo",$F103="Transferencia"),0.07,0))) -> 0 | L103: =IF($O103<>"Tienda",0,$J103*$K103) -> 0 | M103: =E103-G103-I103-L103 -> 0
A108: Mayo - Gastos Fijos | G108: Mayo - Gastos Extra
A109: Nombre gasto | B109: Monto (CLP) | C109: Notas | G109: Nombre gasto | H109: Monto (CLP) | I109: Fecha | J109: Notas
A110: Arriendo (CLP calculado con UF) | B110: =Parametros!$B$1*Parametros!$B$2 -> 1463000
A111: Gastos comunes | B111: 70000
A112: ADT | B112: 69000
A113: Internet | B113: 39960
A114: Luz (promedio) | B114: 35000
A115: Agua (promedio) | B115: 25000
A116: Shopify | B116: 50000
A130: Total gastos fijos | B130: =SUM(B110:B129) -> 1751960 | G130: Total gastos extra | H130: =SUM(H110:H129) -> 0
A131: Gasto fijo por integrante (÷5) | B131: =B130/5 -> 350392

Sheet Abril
A1: Abril - Ingresos
P2: Total ventas brutas | Q2: =SUM(E4:E103) -> 3919000
A3: Nombre prenda | B3: Talla | C3: Propietario prenda | D3: Vendedor | E3: Precio venta (BRUTO) | F3: Tipo de pago | G3: IVA (19%) | H3: % comisión bancaria | I3: $ comisión bancaria | J3: Base comisión vendedor | K3: % comisión vendedor | L3: $ comisión vendedor | M3: Neto tienda | N3: Observaciones | O3: Marca (Tienda/externa) | P3: Total IVA ventas | Q3: =SUM(G4:G103) -> 47899.16
A4: POLERON ESSENTIAL ROSADO | B4: - | C4: Tienda | D4: Aaron | E4: 80000 | F4: Crédito | G4: =IF(OR(F4="Débito",F4="Crédito",F4="Internet(Shopify)"),E4*19/119,0) -> 12773.109 | H4: =IF(F4="Débito",0.0275,IF(F4="Crédito",0.0295,0)) -> 0.0295 | I4: =E4*H4 -> 2360 | J4: =E4-G4-I4 -> 64866.891 | K4: =IF($O4<>"Tienda",0,IF(OR($F4="Débito",$F4="Crédito"),0.05,IF(OR($F4="Efectivo",$F4="Transferencia"),0.07,0))) -> 0 | L4: =IF($O4<>"Tienda",0,$J4*$K4) -> 0 | M4: =E4-G4-I4-L4 -> 64866.891 | N4: VENTA EXENTA IVA | P4: Total comisiones bancarias | Q4: =SUM(I4:I103) -> 8650
A5: anillo onyx | B5: - | C5: Tienda | D5: Aaron | E5: 50000 | F5: Transferencia | G5: =IF(OR(F5="Débito",F5="Crédito",F5="Internet(Shopify)"),E5*19/119,0) -> 0 | H5: =IF(F5="Débito",0.0275,IF(F5="Crédito",0.0295,0)) -> 0 | I5: =E5*H5 -> 0 | J5: =E5-G5-I5 -> 50000 | K5: =IF($O5<>"Tienda",0,IF(OR($F5="Débito",$F5="Crédito"),0.05,IF(OR($F5="Efectivo",$F5="Transferencia"),0.07,0))) -> 0 | L5: =IF($O5<>"Tienda",0,$J5*$K5) -> 0 | M5: =E5-G5-I5-L5 -> 50000 | N5: Artista anillo ($37.500) | P5: Total comisiones vendedores (NO se divide) | Q5: =SUM(L4:L103) -> 218999.2
A6: anillo simple | B6: - | C6: Tienda | D6: Aaron | E6: 30000 | F6: Transferencia | G6: =IF(OR(F6="Débito",F6="Crédito",F6="Internet(Shopify)"),E6*19/119,0) -> 0 | H6: =IF(F6="Débito",0.0275,IF(F6="Crédito",0.0295,0)) -> 0 | I6: =E6*H6 -> 0 | J6: =E6-G6-I6 -> 30000 | K6: =IF($O6<>"Tienda",0,IF(OR($F6="Débito",$F6="Crédito"),0.05,IF(OR($F6="Efectivo",$F6="Transferencia"),0.07,0))) -> 0 | L6: =IF($O6<>"Tienda",0,$J6*$K6) -> 0 | M6: =E6-G6-I6-L6 -> 30000 | N6: Artista anillo ($22.500) | P6: Total neto tienda (NO se divide) | Q6: =SUM(M4:M103) -> 3643451.6
A7: poleron burberry | B7: L | C7: Fabio | D7: Marenna | E7: 35000 | F7: Transferencia | G7: =IF(OR(F7="Débito",F7="Crédito",F7="Internet(Shopify)"),E7*19/119,0) -> 0 | H7: =IF(F7="Débito",0.0275,IF(F7="Crédito",0.0295,0)) -> 0 | I7: =E7*H7 -> 0 | J7: =E7-G7-I7 -> 35000 | K7: =IF($O7<>"Tienda",0,IF(OR($F7="Débito",$F7="Crédito"),0.05,IF(OR($F7="Efectivo",$F7="Transferencia"),0.07,0))) -> 0.07 | L7: =IF($O7<>"Tienda",0,$J7*$K7) -> 2450 | M7: =E7-G7-I7-L7 -> 32550 | O7: Tienda | P7: Número de ventas | Q7: =COUNTA(E4:E103) -> 55
A8: Lentes Fendi | C8: Fabio | D8: Marenna | E8: 100000 | F8: Transferencia | G8: =IF(OR(F8="Débito",F8="Crédito",F8="Internet(Shopify)"),E8*19/119,0) -> 0 | H8: =IF(F8="Débito",0.0275,IF(F8="Crédito",0.0295,0)) -> 0 | I8: =E8*H8 -> 0 | J8: =E8-G8-I8 -> 100000 | K8: =IF($O8<>"Tienda",0,IF(OR($F8="Débito",$F8="Crédito"),0.05,IF(OR($F8="Efectivo",$F8="Transferencia"),0.07,0))) -> 0.07 | L8: =IF($O8<>"Tienda",0,$J8*$K8) -> 7000 | M8: =E8-G8-I8-L8 -> 93000 | O8: Tienda | P8: Ticket promedio (NETO) | Q8: =IF(Q7=0,0,Q6/Q7) -> 66244.575
A9: Cartera Burberry | C9: Tienda | D9: Marenna | E9: 60000 | F9: Transferencia | G9: =IF(OR(F9="Débito",F9="Crédito",F9="Internet(Shopify)"),E9*19/119,0) -> 0 | H9: =IF(F9="Débito",0.0275,IF(F9="Crédito",0.0295,0)) -> 0 | I9: =E9*H9 -> 0 | J9: =E9-G9-I9 -> 60000 | K9: =IF($O9<>"Tienda",0,IF(OR($F9="Débito",$F9="Crédito"),0.05,IF(OR($F9="Efectivo",$F9="Transferencia"),0.07,0))) -> 0.07 | L9: =IF($O9<>"Tienda",0,$J9*$K9) -> 4200 | M9: =E9-G9-I9-L9 -> 55800 | O9: Tienda | P9: Ventas débito (neto) | Q9: =SUMIF(F4:F103,"Débito",M4:M103) -> 77219.433
A10: Falda Diesel | B10: 34 | G10: =IF(OR(F10="Débito",F10="Crédito",F10="Internet(Shopify)"),E10*19/119,0) -> 0 | H10: =IF(F10="Débito",0.0275,IF(F10="Crédito",0.0295,0)) -> 0 | I10: =E10*H10 -> 0 | J10: =E10-G10-I10 -> 0 | K10: =IF($O10<>"Tienda",0,IF(OR($F10="Débito",$F10="Crédito"),0.05,IF(OR($F10="Efectivo",$F10="Transferencia"),0.07,0))) -> 0 | L10: =IF($O10<>"Tienda",0,$J10*$K10) -> 0 | M10: =E10-G10-I10-L10 -> 0 | P10: Ventas crédito (neto) | Q10: =SUMIF(F4:F103,"Crédito",M4:M103) -> 157302.21
A11: Falda Diesel | B11: 34 | C11: Benja R | D11: Marenna | E11: 20000 | F11: Transferencia | G11: =IF(OR(F11="Débito",F11="Crédito",F11="Internet(Shopify)"),E11*19/119,0) -> 0 | H11: =IF(F11="Débito",0.0275,IF(F11="Crédito",0.0295,0)) -> 0 | I11: =E11*H11 -> 0 | J11: =E11-G11-I11 -> 20000 | K11: =IF($O11<>"Tienda",0,IF(OR($F11="Débito",$F11="Crédito"),0.05,IF(OR($F11="Efectivo",$F11="Transferencia"),0.07,0))) -> 0.07 | L11: =IF($O11<>"Tienda",0,$J11*$K11) -> 1400 | M11: =E11-G11-I11-L11 -> 18600 | N11: pagar michelle 20.000 | O11: Tienda | P11: Ventas efectivo (neto) | Q11: =SUMIF(F4:F103,"Efectivo",M4:M103) -> 111600
A12: vest raro | B12: os | C12: Fabio | D12: Marenna | E12: 35000 | F12: Transferencia | G12: =IF(OR(F12="Débito",F12="Crédito",F12="Internet(Shopify)"),E12*19/119,0) -> 0 | H12: =IF(F12="Débito",0.0275,IF(F12="Crédito",0.0295,0)) -> 0 | I12: =E12*H12 -> 0 | J12: =E12-G12-I12 -> 35000 | K12: =IF($O12<>"Tienda",0,IF(OR($F12="Débito",$F12="Crédito"),0.05,IF(OR($F12="Efectivo",$F12="Transferencia"),0.07,0))) -> 0.07 | L12: =IF($O12<>"Tienda",0,$J12*$K12) -> 2450 | M12: =E12-G12-I12-L12 -> 32550 | O12: Tienda | P12: Ventas transferencia (neto) | Q12: =SUMIF(F4:F103,"Transferencia",M4:M103) -> 3297330
A13: polera heron | B13: os | C13: Benja R | D13: Marenna | E13: 8000 | F13: Transferencia | G13: =IF(OR(F13="Débito",F13="Crédito",F13="Internet(Shopify)"),E13*19/119,0) -> 0 | H13: =IF(F13="Débito",0.0275,IF(F13="Crédito",0.0295,0)) -> 0 | I13: =E13*H13 -> 0 | J13: =E13-G13-I13 -> 8000 | K13: =IF($O13<>"Tienda",0,IF(OR($F13="Débito",$F13="Crédito"),0.05,IF(OR($F13="Efectivo",$F13="Transferencia"),0.07,0))) -> 0.07 | L13: =IF($O13<>"Tienda",0,$J13*$K13) -> 560 | M13: =E13-G13-I13-L13 -> 7440 | O13: Tienda | P13: Ventas Internet(Shopify) (neto) | Q13: =SUMIF(F4:F103,"Internet(Shopify)",M4:M103) -> 0
A14: polera stussy | B14: m | C14: Aaron | D14: Benja R | E14: 30000 | F14: Transferencia | G14: =IF(OR(F14="Débito",F14="Crédito",F14="Internet(Shopify)"),E14*19/119,0) -> 0 | H14: =IF(F14="Débito",0.0275,IF(F14="Crédito",0.0295,0)) -> 0 | I14: =E14*H14 -> 0 | J14: =E14-G14-I14 -> 30000 | K14: =IF($O14<>"Tienda",0,IF(OR($F14="Débito",$F14="Crédito"),0.05,IF(OR($F14="Efectivo",$F14="Transferencia"),0.07,0))) -> 0 | L14: =IF($O14<>"Tienda",0,$J14*$K14) -> 0 | M14: =E14-G14-I14-L14 -> 30000 | N14: mivhelle | P14: Ventas cuenta común (D+C+T) NETO | Q14: =SUMIF(F4:F103,"Débito",M4:M103)+SUMIF(F4:F103,"Crédito",M4:M103)+SUMIF(F4:F103,"Transferencia",M4:M103) -> 3531851.6
A15: polera ed hardy | B15: s | C15: Benja R | D15: Benja R | E15: 13000 | F15: Transferencia | G15: =IF(OR(F15="Débito",F15="Crédito",F15="Internet(Shopify)"),E15*19/119,0) -> 0 | H15: =IF(F15="Débito",0.0275,IF(F15="Crédito",0.0295,0)) -> 0 | I15: =E15*H15 -> 0 | J15: =E15-G15-I15 -> 13000 | K15: =IF($O15<>"Tienda",0,IF(OR($F15="Débito",$F15="Crédito"),0.05,IF(OR($F15="Efectivo",$F15="Transferencia"),0.07,0))) -> 0 | L15: =IF($O15<>"Tienda",0,$J15*$K15) -> 0 | M15: =E15-G15-I15-L15 -> 13000 | N15: michelle | P15: IVA compras (manual)
A16: 3 poleras vintage benja | C16: Benja R | D16: Fabio | E16: 30000 | F16: Transferencia | G16: =IF(OR(F16="Débito",F16="Crédito",F16="Internet(Shopify)"),E16*19/119,0) -> 0 | H16: =IF(F16="Débito",0.0275,IF(F16="Crédito",0.0295,0)) -> 0 | I16: =E16*H16 -> 0 | J16: =E16-G16-I16 -> 30000 | K16: =IF($O16<>"Tienda",0,IF(OR($F16="Débito",$F16="Crédito"),0.05,IF(OR($F16="Efectivo",$F16="Transferencia"),0.07,0))) -> 0.07 | L16: =IF($O16<>"Tienda",0,$J16*$K16) -> 2100 | M16: =E16-G16-I16-L16 -> 27900 | O16: Tienda | P16: IVA neto (ventas - compras) | Q16: =Q3-Q15 -> 47899.16
A17: Polera IQ | C17: Consignacion | D17: Fabio | E17: 30000 | F17: Transferencia | G17: =IF(OR(F17="Débito",F17="Crédito",F17="Internet(Shopify)"),E17*19/119,0) -> 0 | H17: =IF(F17="Débito",0.0275,IF(F17="Crédito",0.0295,0)) -> 0 | I17: =E17*H17 -> 0 | J17: =E17-G17-I17 -> 30000 | K17: =IF($O17<>"Tienda",0,IF(OR($F17="Débito",$F17="Crédito"),0.05,IF(OR($F17="Efectivo",$F17="Transferencia"),0.07,0))) -> 0 | L17: =IF($O17<>"Tienda",0,$J17*$K17) -> 0 | M17: =E17-G17-I17-L17 -> 30000 | N17: Gelattos (22.500) | O17: Gelattos | P17: INGRESOS 05 DE C/MES | Q17: =SUM(E4:E26) -> 959000
A18: Moto con fuego mangalarga | C18: Aaron | D18: Marenna | E18: 15000 | F18: Transferencia | G18: =IF(OR(F18="Débito",F18="Crédito",F18="Internet(Shopify)"),E18*19/119,0) -> 0 | H18: =IF(F18="Débito",0.0275,IF(F18="Crédito",0.0295,0)) -> 0 | I18: =E18*H18 -> 0 | J18: =E18-G18-I18 -> 15000 | K18: =IF($O18<>"Tienda",0,IF(OR($F18="Débito",$F18="Crédito"),0.05,IF(OR($F18="Efectivo",$F18="Transferencia"),0.07,0))) -> 0.07 | L18: =IF($O18<>"Tienda",0,$J18*$K18) -> 1050 | M18: =E18-G18-I18-L18 -> 13950 | O18: Tienda | P18: INGRESO REAL DE ESTE MES | Q18: =SUM(E27:E560) -> 2960000
A19: Polera Acne marca en cuello | C19: Aaron | D19: Marenna | E19: 40000 | F19: Transferencia | G19: =IF(OR(F19="Débito",F19="Crédito",F19="Internet(Shopify)"),E19*19/119,0) -> 0 | H19: =IF(F19="Débito",0.0275,IF(F19="Crédito",0.0295,0)) -> 0 | I19: =E19*H19 -> 0 | J19: =E19-G19-I19 -> 40000 | K19: =IF($O19<>"Tienda",0,IF(OR($F19="Débito",$F19="Crédito"),0.05,IF(OR($F19="Efectivo",$F19="Transferencia"),0.07,0))) -> 0.07 | L19: =IF($O19<>"Tienda",0,$J19*$K19) -> 2800 | M19: =E19-G19-I19-L19 -> 37200 | O19: Tienda
A20: Polera Supreme | B20: m | C20: Aaron | D20: Benja R | E20: 20000 | F20: Transferencia | G20: =IF(OR(F20="Débito",F20="Crédito",F20="Internet(Shopify)"),E20*19/119,0) -> 0 | H20: =IF(F20="Débito",0.0275,IF(F20="Crédito",0.0295,0)) -> 0 | I20: =E20*H20 -> 0 | J20: =E20-G20-I20 -> 20000 | K20: =IF($O20<>"Tienda",0,IF(OR($F20="Débito",$F20="Crédito"),0.05,IF(OR($F20="Efectivo",$F20="Transferencia"),0.07,0))) -> 0.07 | L20: =IF($O20<>"Tienda",0,$J20*$K20) -> 1400 | M20: =E20-G20-I20-L20 -> 18600 | N20: michelle | O20: Tienda
A21: Polera Stussy | B21: m | C21: Benja R | D21: Marenna | E21: 28000 | F21: Transferencia | G21: =IF(OR(F21="Débito",F21="Crédito",F21="Internet(Shopify)"),E21*19/119,0) -> 0 | H21: =IF(F21="Débito",0.0275,IF(F21="Crédito",0.0295,0)) -> 0 | I21: =E21*H21 -> 0 | J21: =E21-G21-I21 -> 28000 | K21: =IF($O21<>"Tienda",0,IF(OR($F21="Débito",$F21="Crédito"),0.05,IF(OR($F21="Efectivo",$F21="Transferencia"),0.07,0))) -> 0.07 | L21: =IF($O21<>"Tienda",0,$J21*$K21) -> 1960 | M21: =E21-G21-I21-L21 -> 26040 | O21: Tienda
A22: Zapato Jeffery West | B22: 43 | C22: Consignacion | D22: Fabio | E22: 180000 | F22: Transferencia | G22: =IF(OR(F22="Débito",F22="Crédito",F22="Internet(Shopify)"),E22*19/119,0) -> 0 | H22: =IF(F22="Débito",0.0275,IF(F22="Crédito",0.0295,0)) -> 0 | I22: =E22*H22 -> 0 | J22: =E22-G22-I22 -> 180000 | K22: =IF($O22<>"Tienda",0,IF(OR($F22="Débito",$F22="Crédito"),0.05,IF(OR($F22="Efectivo",$F22="Transferencia"),0.07,0))) -> 0.07 | L22: =IF($O22<>"Tienda",0,$J22*$K22) -> 12600 | M22: =E22-G22-I22-L22 -> 167400 | N22: Federico( | O22: Tienda
A23: Polera futbol adidas | B23: l | C23: Fabio | D23: Marenna | E23: 35000 | F23: Transferencia | G23: =IF(OR(F23="Débito",F23="Crédito",F23="Internet(Shopify)"),E23*19/119,0) -> 0 | H23: =IF(F23="Débito",0.0275,IF(F23="Crédito",0.0295,0)) -> 0 | I23: =E23*H23 -> 0 | J23: =E23-G23-I23 -> 35000 | K23: =IF($O23<>"Tienda",0,IF(OR($F23="Débito",$F23="Crédito"),0.05,IF(OR($F23="Efectivo",$F23="Transferencia"),0.07,0))) -> 0.07 | L23: =IF($O23<>"Tienda",0,$J23*$K23) -> 2450 | M23: =E23-G23-I23-L23 -> 32550 | O23: Tienda
A24: Sudadera JPG Jeans Flecos | B24: m | C24: Tienda | D24: Marenna | E24: 55000 | F24: Transferencia | G24: =IF(OR(F24="Débito",F24="Crédito",F24="Internet(Shopify)"),E24*19/119,0) -> 0 | H24: =IF(F24="Débito",0.0275,IF(F24="Crédito",0.0295,0)) -> 0 | I24: =E24*H24 -> 0 | J24: =E24-G24-I24 -> 55000 | K24: =IF($O24<>"Tienda",0,IF(OR($F24="Débito",$F24="Crédito"),0.05,IF(OR($F24="Efectivo",$F24="Transferencia"),0.07,0))) -> 0.07 | L24: =IF($O24<>"Tienda",0,$J24*$K24) -> 3850 | M24: =E24-G24-I24-L24 -> 51150 | O24: Tienda
A25: Poleron Sandro | B25: m | C25: Tienda | D25: Fabio | E25: 25000 | F25: Transferencia | G25: =IF(OR(F25="Débito",F25="Crédito",F25="Internet(Shopify)"),E25*19/119,0) -> 0 | H25: =IF(F25="Débito",0.0275,IF(F25="Crédito",0.0295,0)) -> 0 | I25: =E25*H25 -> 0 | J25: =E25-G25-I25 -> 25000 | K25: =IF($O25<>"Tienda",0,IF(OR($F25="Débito",$F25="Crédito"),0.05,IF(OR($F25="Efectivo",$F25="Transferencia"),0.07,0))) -> 0.07 | L25: =IF($O25<>"Tienda",0,$J25*$K25) -> 1750 | M25: =E25-G25-I25-L25 -> 23250 | O25: Tienda
A26: Short Dolce* | B26: M | C26: Aaron | D26: Fabio | E26: 40000 | F26: Transferencia | G26: =IF(OR(F26="Débito",F26="Crédito",F26="Internet(Shopify)"),E26*19/119,0) -> 0 | H26: =IF(F26="Débito",0.0275,IF(F26="Crédito",0.0295,0)) -> 0 | I26: =E26*H26 -> 0 | J26: =E26-G26-I26 -> 40000 | K26: =IF($O26<>"Tienda",0,IF(OR($F26="Débito",$F26="Crédito"),0.05,IF(OR($F26="Efectivo",$F26="Transferencia"),0.07,0))) -> 0.07 | L26: =IF($O26<>"Tienda",0,$J26*$K26) -> 2800 | M26: =E26-G26-I26-L26 -> 37200 | O26: Tienda
A27: polera supreme big logo | B27: L | C27: Aaron | D27: Benja R | E27: 35000 | F27: Transferencia | G27: =IF(OR(F27="Débito",F27="Crédito",F27="Internet(Shopify)"),E27*19/119,0) -> 0 | H27: =IF(F27="Débito",0.0275,IF(F27="Crédito",0.0295,0)) -> 0 | I27: =E27*H27 -> 0 | J27: =E27-G27-I27 -> 35000 | K27: =IF($O27<>"Tienda",0,IF(OR($F27="Débito",$F27="Crédito"),0.05,IF(OR($F27="Efectivo",$F27="Transferencia"),0.07,0))) -> 0.07 | L27: =IF($O27<>"Tienda",0,$J27*$K27) -> 2450 | M27: =E27-G27-I27-L27 -> 32550 | O27: Tienda
A28: polerA OFF WHITE | B28: L | C28: Tienda | D28: Benja R | E28: 40000 | F28: Transferencia | G28: =IF(OR(F28="Débito",F28="Crédito",F28="Internet(Shopify)"),E28*19/119,0) -> 0 | H28: =IF(F28="Débito",0.0275,IF(F28="Crédito",0.0295,0)) -> 0 | I28: =E28*H28 -> 0 | J28: =E28-G28-I28 -> 40000 | K28: =IF($O28<>"Tienda",0,IF(OR($F28="Débito",$F28="Crédito"),0.05,IF(OR($F28="Efectivo",$F28="Transferencia"),0.07,0))) -> 0.07 | L28: =IF($O28<>"Tienda",0,$J28*$K28) -> 2800 | M28: =E28-G28-I28-L28 -> 37200 | O28: Tienda
A29: aros fab | B29: op | C29: Fabio | D29: Fabio | E29: 20000 | F29: Transferencia | G29: =IF(OR(F29="Débito",F29="Crédito",F29="Internet(Shopify)"),E29*19/119,0) -> 0 | H29: =IF(F29="Débito",0.0275,IF(F29="Crédito",0.0295,0)) -> 0 | I29: =E29*H29 -> 0 | J29: =E29-G29-I29 -> 20000 | K29: =IF($O29<>"Tienda",0,IF(OR($F29="Débito",$F29="Crédito"),0.05,IF(OR($F29="Efectivo",$F29="Transferencia"),0.07,0))) -> 0.07 | L29: =IF($O29<>"Tienda",0,$J29*$K29) -> 1400 | M29: =E29-G29-I29-L29 -> 18600 | O29: Tienda
A30: hoodie Helmut Blanco | B30: M | C30: Aaron | D30: Fabio | E30: 70000 | F30: Transferencia | G30: =IF(OR(F30="Débito",F30="Crédito",F30="Internet(Shopify)"),E30*19/119,0) -> 0 | H30: =IF(F30="Débito",0.0275,IF(F30="Crédito",0.0295,0)) -> 0 | I30: =E30*H30 -> 0 | J30: =E30-G30-I30 -> 70000 | K30: =IF($O30<>"Tienda",0,IF(OR($F30="Débito",$F30="Crédito"),0.05,IF(OR($F30="Efectivo",$F30="Transferencia"),0.07,0))) -> 0.07 | L30: =IF($O30<>"Tienda",0,$J30*$K30) -> 4900 | M30: =E30-G30-I30-L30 -> 65100 | O30: Tienda
A31: Polera Hiddien | B31: l | C31: Fabio | D31: Fabio | E31: 45000 | F31: Transferencia | G31: =IF(OR(F31="Débito",F31="Crédito",F31="Internet(Shopify)"),E31*19/119,0) -> 0 | H31: =IF(F31="Débito",0.0275,IF(F31="Crédito",0.0295,0)) -> 0 | I31: =E31*H31 -> 0 | J31: =E31-G31-I31 -> 45000 | K31: =IF($O31<>"Tienda",0,IF(OR($F31="Débito",$F31="Crédito"),0.05,IF(OR($F31="Efectivo",$F31="Transferencia"),0.07,0))) -> 0.07 | L31: =IF($O31<>"Tienda",0,$J31*$K31) -> 3150 | M31: =E31-G31-I31-L31 -> 41850 | O31: Tienda
A32: vest jil sander | B32: s | C32: Aaron | D32: Fabio | E32: 75000 | F32: Transferencia | G32: =IF(OR(F32="Débito",F32="Crédito",F32="Internet(Shopify)"),E32*19/119,0) -> 0 | H32: =IF(F32="Débito",0.0275,IF(F32="Crédito",0.0295,0)) -> 0 | I32: =E32*H32 -> 0 | J32: =E32-G32-I32 -> 75000 | K32: =IF($O32<>"Tienda",0,IF(OR($F32="Débito",$F32="Crédito"),0.05,IF(OR($F32="Efectivo",$F32="Transferencia"),0.07,0))) -> 0.07 | L32: =IF($O32<>"Tienda",0,$J32*$K32) -> 5250 | M32: =E32-G32-I32-L32 -> 69750 | O32: Tienda
A33: gorro NY | B33: Unica | C33: Fabio | D33: Benja R | E33: 25000 | F33: Transferencia | G33: =IF(OR(F33="Débito",F33="Crédito",F33="Internet(Shopify)"),E33*19/119,0) -> 0 | H33: =IF(F33="Débito",0.0275,IF(F33="Crédito",0.0295,0)) -> 0 | I33: =E33*H33 -> 0 | J33: =E33-G33-I33 -> 25000 | K33: =IF($O33<>"Tienda",0,IF(OR($F33="Débito",$F33="Crédito"),0.05,IF(OR($F33="Efectivo",$F33="Transferencia"),0.07,0))) -> 0.07 | L33: =IF($O33<>"Tienda",0,$J33*$K33) -> 1750 | M33: =E33-G33-I33-L33 -> 23250 | N33: MICHELLE | O33: Tienda
A34: polera APPE | B34: L | C34: Benja R | D34: Benja R | E34: 25000 | F34: Transferencia | G34: =IF(OR(F34="Débito",F34="Crédito",F34="Internet(Shopify)"),E34*19/119,0) -> 0 | H34: =IF(F34="Débito",0.0275,IF(F34="Crédito",0.0295,0)) -> 0 | I34: =E34*H34 -> 0 | J34: =E34-G34-I34 -> 25000 | K34: =IF($O34<>"Tienda",0,IF(OR($F34="Débito",$F34="Crédito"),0.05,IF(OR($F34="Efectivo",$F34="Transferencia"),0.07,0))) -> 0.07 | L34: =IF($O34<>"Tienda",0,$J34*$K34) -> 1750 | M34: =E34-G34-I34-L34 -> 23250 | N34: michelle | O34: Tienda
A35: polera phillip plein | B35: XS | C35: Benja R | D35: Benja R | E35: 25000 | F35: Débito | G35: =IF(OR(F35="Débito",F35="Crédito",F35="Internet(Shopify)"),E35*19/119,0) -> 3991.5966 | H35: =IF(F35="Débito",0.0275,IF(F35="Crédito",0.0295,0)) -> 0.0275 | I35: =E35*H35 -> 687.5 | J35: =E35-G35-I35 -> 20320.903 | K35: =IF($O35<>"Tienda",0,IF(OR($F35="Débito",$F35="Crédito"),0.05,IF(OR($F35="Efectivo",$F35="Transferencia"),0.07,0))) -> 0.05 | L35: =IF($O35<>"Tienda",0,$J35*$K35) -> 1016.0452 | M35: =E35-G35-I35-L35 -> 19304.858 | N35: michelle | O35: Tienda
A36: boxer pedritos | B36: S | C36: Tienda | D36: Benja R | E36: 25000 | F36: Transferencia | G36: =IF(OR(F36="Débito",F36="Crédito",F36="Internet(Shopify)"),E36*19/119,0) -> 0 | H36: =IF(F36="Débito",0.0275,IF(F36="Crédito",0.0295,0)) -> 0 | I36: =E36*H36 -> 0 | J36: =E36-G36-I36 -> 25000 | K36: =IF($O36<>"Tienda",0,IF(OR($F36="Débito",$F36="Crédito"),0.05,IF(OR($F36="Efectivo",$F36="Transferencia"),0.07,0))) -> 0 | L36: =IF($O36<>"Tienda",0,$J36*$K36) -> 0 | M36: =E36-G36-I36-L36 -> 25000 | N36: Pedritos (18.750) | O36: Pedritos
A37: camiseta chile | B37: L | C37: Fabio | D37: Fabio | E37: 35000 | F37: Transferencia | G37: =IF(OR(F37="Débito",F37="Crédito",F37="Internet(Shopify)"),E37*19/119,0) -> 0 | H37: =IF(F37="Débito",0.0275,IF(F37="Crédito",0.0295,0)) -> 0 | I37: =E37*H37 -> 0 | J37: =E37-G37-I37 -> 35000 | K37: =IF($O37<>"Tienda",0,IF(OR($F37="Débito",$F37="Crédito"),0.05,IF(OR($F37="Efectivo",$F37="Transferencia"),0.07,0))) -> 0.07 | L37: =IF($O37<>"Tienda",0,$J37*$K37) -> 2450 | M37: =E37-G37-I37-L37 -> 32550 | O37: Tienda
A38: cartera prada | B38: os | C38: Tienda | D38: Benja R | E38: 140000 | F38: Transferencia | G38: =IF(OR(F38="Débito",F38="Crédito",F38="Internet(Shopify)"),E38*19/119,0) -> 0 | H38: =IF(F38="Débito",0.0275,IF(F38="Crédito",0.0295,0)) -> 0 | I38: =E38*H38 -> 0 | J38: =E38-G38-I38 -> 140000 | K38: =IF($O38<>"Tienda",0,IF(OR($F38="Débito",$F38="Crédito"),0.05,IF(OR($F38="Efectivo",$F38="Transferencia"),0.07,0))) -> 0 | L38: =IF($O38<>"Tienda",0,$J38*$K38) -> 0 | M38: =E38-G38-I38-L38 -> 140000 | N38: 70.000 para julian
A39: Poleron Stussy | B39: L | C39: Tienda | D39: Benja R | E39: 120000 | F39: Crédito | G39: =IF(OR(F39="Débito",F39="Crédito",F39="Internet(Shopify)"),E39*19/119,0) -> 19159.664 | H39: =IF(F39="Débito",0.0275,IF(F39="Crédito",0.0295,0)) -> 0.0295 | I39: =E39*H39 -> 3540 | J39: =E39-G39-I39 -> 97300.336 | K39: =IF($O39<>"Tienda",0,IF(OR($F39="Débito",$F39="Crédito"),0.05,IF(OR($F39="Efectivo",$F39="Transferencia"),0.07,0))) -> 0.05 | L39: =IF($O39<>"Tienda",0,$J39*$K39) -> 4865.0168 | M39: =E39-G39-I39-L39 -> 92435.319 | N39: MICHELLE | O39: Tienda
A40: Polera Vivian West | C40: Tienda | D40: Benja R | E40: 100000 | F40: Transferencia | G40: =IF(OR(F40="Débito",F40="Crédito",F40="Internet(Shopify)"),E40*19/119,0) -> 0 | H40: =IF(F40="Débito",0.0275,IF(F40="Crédito",0.0295,0)) -> 0 | I40: =E40*H40 -> 0 | J40: =E40-G40-I40 -> 100000 | K40: =IF($O40<>"Tienda",0,IF(OR($F40="Débito",$F40="Crédito"),0.05,IF(OR($F40="Efectivo",$F40="Transferencia"),0.07,0))) -> 0.07 | L40: =IF($O40<>"Tienda",0,$J40*$K40) -> 7000 | M40: =E40-G40-I40-L40 -> 93000 | O40: Tienda
A41: Chaqueta Season Archive | B41: L | C41: Tienda | D41: Fabio | E41: 80000 | F41: Transferencia | G41: =IF(OR(F41="Débito",F41="Crédito",F41="Internet(Shopify)"),E41*19/119,0) -> 0 | H41: =IF(F41="Débito",0.0275,IF(F41="Crédito",0.0295,0)) -> 0 | I41: =E41*H41 -> 0 | J41: =E41-G41-I41 -> 80000 | K41: =IF($O41<>"Tienda",0,IF(OR($F41="Débito",$F41="Crédito"),0.05,IF(OR($F41="Efectivo",$F41="Transferencia"),0.07,0))) -> 0 | L41: =IF($O41<>"Tienda",0,$J41*$K41) -> 0 | M41: =E41-G41-I41-L41 -> 80000 | N41: Season Archive (60.000) | O41: Season Archive
A42: Chaqueta Season Archive | B42: M | C42: Tienda | D42: Marenna | E42: 80000 | F42: Transferencia | G42: =IF(OR(F42="Débito",F42="Crédito",F42="Internet(Shopify)"),E42*19/119,0) -> 0 | H42: =IF(F42="Débito",0.0275,IF(F42="Crédito",0.0295,0)) -> 0 | I42: =E42*H42 -> 0 | J42: =E42-G42-I42 -> 80000 | K42: =IF($O42<>"Tienda",0,IF(OR($F42="Débito",$F42="Crédito"),0.05,IF(OR($F42="Efectivo",$F42="Transferencia"),0.07,0))) -> 0 | L42: =IF($O42<>"Tienda",0,$J42*$K42) -> 0 | M42: =E42-G42-I42-L42 -> 80000 | N42: Season Archive (60.000) | O42: Season Archive
A43: anillo plata marc chilena | B43: os | C43: Tienda | D43: Benja R | E43: 30000 | F43: Transferencia | G43: =IF(OR(F43="Débito",F43="Crédito",F43="Internet(Shopify)"),E43*19/119,0) -> 0 | H43: =IF(F43="Débito",0.0275,IF(F43="Crédito",0.0295,0)) -> 0 | I43: =E43*H43 -> 0 | J43: =E43-G43-I43 -> 30000 | K43: =IF($O43<>"Tienda",0,IF(OR($F43="Débito",$F43="Crédito"),0.05,IF(OR($F43="Efectivo",$F43="Transferencia"),0.07,0))) -> 0.07 | L43: =IF($O43<>"Tienda",0,$J43*$K43) -> 2100 | M43: =E43-G43-I43-L43 -> 27900 | N43: Anillos ($22.500) | O43: Tienda
A44: poleron season | B44: M | C44: Tienda | D44: Benja R | E44: 55000 | F44: Transferencia | G44: =IF(OR(F44="Débito",F44="Crédito",F44="Internet(Shopify)"),E44*19/119,0) -> 0 | H44: =IF(F44="Débito",0.0275,IF(F44="Crédito",0.0295,0)) -> 0 | I44: =E44*H44 -> 0 | J44: =E44-G44-I44 -> 55000 | K44: =IF($O44<>"Tienda",0,IF(OR($F44="Débito",$F44="Crédito"),0.05,IF(OR($F44="Efectivo",$F44="Transferencia"),0.07,0))) -> 0 | L44: =IF($O44<>"Tienda",0,$J44*$K44) -> 0 | M44: =E44-G44-I44-L44 -> 55000 | N44: Season Archive (41.250) | O44: Season Archive
A45: Aritos Fabio | C45: Tienda | D45: Marenna | E45: 20000 | F45: Débito | G45: =IF(OR(F45="Débito",F45="Crédito",F45="Internet(Shopify)"),E45*19/119,0) -> 3193.2773 | H45: =IF(F45="Débito",0.0275,IF(F45="Crédito",0.0295,0)) -> 0.0275 | I45: =E45*H45 -> 550 | J45: =E45-G45-I45 -> 16256.723 | K45: =IF($O45<>"Tienda",0,IF(OR($F45="Débito",$F45="Crédito"),0.05,IF(OR($F45="Efectivo",$F45="Transferencia"),0.07,0))) -> 0.05 | L45: =IF($O45<>"Tienda",0,$J45*$K45) -> 812.83613 | M45: =E45-G45-I45-L45 -> 15443.887 | N45: Fabio | O45: Tienda
A46: lentes dior | B46: os | C46: Tienda | D46: Benja R | E46: 250000 | F46: Transferencia | G46: =IF(OR(F46="Débito",F46="Crédito",F46="Internet(Shopify)"),E46*19/119,0) -> 0 | H46: =IF(F46="Débito",0.0275,IF(F46="Crédito",0.0295,0)) -> 0 | I46: =E46*H46 -> 0 | J46: =E46-G46-I46 -> 250000 | K46: =IF($O46<>"Tienda",0,IF(OR($F46="Débito",$F46="Crédito"),0.05,IF(OR($F46="Efectivo",$F46="Transferencia"),0.07,0))) -> 0.07 | L46: =IF($O46<>"Tienda",0,$J46*$K46) -> 17500 | M46: =E46-G46-I46-L46 -> 232500 | O46: Tienda
A47: dior vintage | B47: os | C47: Benja R | D47: Benja R | E47: 80000 | F47: Transferencia | G47: =IF(OR(F47="Débito",F47="Crédito",F47="Internet(Shopify)"),E47*19/119,0) -> 0 | H47: =IF(F47="Débito",0.0275,IF(F47="Crédito",0.0295,0)) -> 0 | I47: =E47*H47 -> 0 | J47: =E47-G47-I47 -> 80000 | K47: =IF($O47<>"Tienda",0,IF(OR($F47="Débito",$F47="Crédito"),0.05,IF(OR($F47="Efectivo",$F47="Transferencia"),0.07,0))) -> 0.07 | L47: =IF($O47<>"Tienda",0,$J47*$K47) -> 5600 | M47: =E47-G47-I47-L47 -> 74400 | O47: Tienda
A48: polera pabe shark | B48: s | C48: Tienda | D48: Benja R | E48: 55000 | F48: Débito | G48: =IF(OR(F48="Débito",F48="Crédito",F48="Internet(Shopify)"),E48*19/119,0) -> 8781.5126 | H48: =IF(F48="Débito",0.0275,IF(F48="Crédito",0.0295,0)) -> 0.0275 | I48: =E48*H48 -> 1512.5 | J48: =E48-G48-I48 -> 44705.987 | K48: =IF($O48<>"Tienda",0,IF(OR($F48="Débito",$F48="Crédito"),0.05,IF(OR($F48="Efectivo",$F48="Transferencia"),0.07,0))) -> 0.05 | L48: =IF($O48<>"Tienda",0,$J48*$K48) -> 2235.2994 | M48: =E48-G48-I48-L48 -> 42470.688 | O48: Tienda
A49: lentes gucci | B49: os | C49: Tienda | D49: Benja R | E49: 150000 | F49: Transferencia | G49: =IF(OR(F49="Débito",F49="Crédito",F49="Internet(Shopify)"),E49*19/119,0) -> 0 | H49: =IF(F49="Débito",0.0275,IF(F49="Crédito",0.0295,0)) -> 0 | I49: =E49*H49 -> 0 | J49: =E49-G49-I49 -> 150000 | K49: =IF($O49<>"Tienda",0,IF(OR($F49="Débito",$F49="Crédito"),0.05,IF(OR($F49="Efectivo",$F49="Transferencia"),0.07,0))) -> 0.07 | L49: =IF($O49<>"Tienda",0,$J49*$K49) -> 10500 | M49: =E49-G49-I49-L49 -> 139500 | O49: Tienda
A50: abrigo burberry | B50: M | C50: Tienda | D50: Benja R | E50: 230000 | F50: Transferencia | G50: =IF(OR(F50="Débito",F50="Crédito",F50="Internet(Shopify)"),E50*19/119,0) -> 0 | H50: =IF(F50="Débito",0.0275,IF(F50="Crédito",0.0295,0)) -> 0 | I50: =E50*H50 -> 0 | J50: =E50-G50-I50 -> 230000 | K50: =IF($O50<>"Tienda",0,IF(OR($F50="Débito",$F50="Crédito"),0.05,IF(OR($F50="Efectivo",$F50="Transferencia"),0.07,0))) -> 0.07 | L50: =IF($O50<>"Tienda",0,$J50*$K50) -> 16100 | M50: =E50-G50-I50-L50 -> 213900 | N50: pago consignacion 120000 | O50: Tienda
A51: totebag vivienne | B51: os | C51: Tienda | D51: Benja R | E51: 180000 | F51: Transferencia | G51: =IF(OR(F51="Débito",F51="Crédito",F51="Internet(Shopify)"),E51*19/119,0) -> 0 | H51: =IF(F51="Débito",0.0275,IF(F51="Crédito",0.0295,0)) -> 0 | I51: =E51*H51 -> 0 | J51: =E51-G51-I51 -> 180000 | K51: =IF($O51<>"Tienda",0,IF(OR($F51="Débito",$F51="Crédito"),0.05,IF(OR($F51="Efectivo",$F51="Transferencia"),0.07,0))) -> 0.07 | L51: =IF($O51<>"Tienda",0,$J51*$K51) -> 12600 | M51: =E51-G51-I51-L51 -> 167400 | O51: Tienda
A52: lentes louis vuitton | B52: os | C52: Tienda | D52: Fabio | E52: 140000 | F52: Transferencia | G52: =IF(OR(F52="Débito",F52="Crédito",F52="Internet(Shopify)"),E52*19/119,0) -> 0 | H52: =IF(F52="Débito",0.0275,IF(F52="Crédito",0.0295,0)) -> 0 | I52: =E52*H52 -> 0 | J52: =E52-G52-I52 -> 140000 | K52: =IF($O52<>"Tienda",0,IF(OR($F52="Débito",$F52="Crédito"),0.05,IF(OR($F52="Efectivo",$F52="Transferencia"),0.07,0))) -> 0.07 | L52: =IF($O52<>"Tienda",0,$J52*$K52) -> 9800 | M52: =E52-G52-I52-L52 -> 130200 | N52: consignacion pagar 80000 | O52: Tienda
A53: crewneck stussy | B53: L | C53: Aaron | D53: Benja R | E53: 80000 | F53: Transferencia | G53: =IF(OR(F53="Débito",F53="Crédito",F53="Internet(Shopify)"),E53*19/119,0) -> 0 | H53: =IF(F53="Débito",0.0275,IF(F53="Crédito",0.0295,0)) -> 0 | I53: =E53*H53 -> 0 | J53: =E53-G53-I53 -> 80000 | K53: =IF($O53<>"Tienda",0,IF(OR($F53="Débito",$F53="Crédito"),0.05,IF(OR($F53="Efectivo",$F53="Transferencia"),0.07,0))) -> 0.07 | L53: =IF($O53<>"Tienda",0,$J53*$K53) -> 5600 | M53: =E53-G53-I53-L53 -> 74400 | O53: Tienda
A54: chaqueta season | B54: L | C54: Tienda | D54: Benja R | E54: 85000 | F54: Transferencia | G54: =IF(OR(F54="Débito",F54="Crédito",F54="Internet(Shopify)"),E54*19/119,0) -> 0 | H54: =IF(F54="Débito",0.0275,IF(F54="Crédito",0.0295,0)) -> 0 | I54: =E54*H54 -> 0 | J54: =E54-G54-I54 -> 85000 | K54: =IF($O54<>"Tienda",0,IF(OR($F54="Débito",$F54="Crédito"),0.05,IF(OR($F54="Efectivo",$F54="Transferencia"),0.07,0))) -> 0 | L54: =IF($O54<>"Tienda",0,$J54*$K54) -> 0 | M54: =E54-G54-I54-L54 -> 85000 | N54: Season Archive (63.750) | O54: Season Archive
A55: prta pasaporte prada | B55: os | C55: Tienda | D55: Benja R | E55: 85000 | F55: Transferencia | G55: =IF(OR(F55="Débito",F55="Crédito",F55="Internet(Shopify)"),E55*19/119,0) -> 0 | H55: =IF(F55="Débito",0.0275,IF(F55="Crédito",0.0295,0)) -> 0 | I55: =E55*H55 -> 0 | J55: =E55-G55-I55 -> 85000 | K55: =IF($O55<>"Tienda",0,IF(OR($F55="Débito",$F55="Crédito"),0.05,IF(OR($F55="Efectivo",$F55="Transferencia"),0.07,0))) -> 0.07 | L55: =IF($O55<>"Tienda",0,$J55*$K55) -> 5950 | M55: =E55-G55-I55-L55 -> 79050 | N55: pagar martin $20000 | O55: Tienda
A56: lentes dior | B56: m | C56: Tienda | D56: Fabio | E56: 75000 | F56: Transferencia | G56: =IF(OR(F56="Débito",F56="Crédito",F56="Internet(Shopify)"),E56*19/119,0) -> 0 | H56: =IF(F56="Débito",0.0275,IF(F56="Crédito",0.0295,0)) -> 0 | I56: =E56*H56 -> 0 | J56: =E56-G56-I56 -> 75000 | K56: =IF($O56<>"Tienda",0,IF(OR($F56="Débito",$F56="Crédito"),0.05,IF(OR($F56="Efectivo",$F56="Transferencia"),0.07,0))) -> 0.07 | L56: =IF($O56<>"Tienda",0,$J56*$K56) -> 5250 | M56: =E56-G56-I56-L56 -> 69750 | O56: Tienda
A57: jeans Diesel | B57: 44 | C57: Consignacion | D57: Fabio | E57: 75000 | F57: Transferencia | G57: =IF(OR(F57="Débito",F57="Crédito",F57="Internet(Shopify)"),E57*19/119,0) -> 0 | H57: =IF(F57="Débito",0.0275,IF(F57="Crédito",0.0295,0)) -> 0 | I57: =E57*H57 -> 0 | J57: =E57-G57-I57 -> 75000 | K57: =IF($O57<>"Tienda",0,IF(OR($F57="Débito",$F57="Crédito"),0.05,IF(OR($F57="Efectivo",$F57="Transferencia"),0.07,0))) -> 0.07 | L57: =IF($O57<>"Tienda",0,$J57*$K57) -> 5250 | M57: =E57-G57-I57-L57 -> 69750 | N57: pagar julian 30mil | O57: Tienda
A58: Prada Parkita | B58: M | C58: Tienda | D58: Fabio | E58: 120000 | F58: Efectivo | G58: =IF(OR(F58="Débito",F58="Crédito",F58="Internet(Shopify)"),E58*19/119,0) -> 0 | H58: =IF(F58="Débito",0.0275,IF(F58="Crédito",0.0295,0)) -> 0 | I58: =E58*H58 -> 0 | J58: =E58-G58-I58 -> 120000 | K58: =IF($O58<>"Tienda",0,IF(OR($F58="Débito",$F58="Crédito"),0.05,IF(OR($F58="Efectivo",$F58="Transferencia"),0.07,0))) -> 0.07 | L58: =IF($O58<>"Tienda",0,$J58*$K58) -> 8400 | M58: =E58-G58-I58-L58 -> 111600 | N58: michelle | O58: Tienda
A59: lentes billonare | B59: os | C59: Tienda | D59: Fabio | E59: 310000 | F59: Transferencia | G59: =IF(OR(F59="Débito",F59="Crédito",F59="Internet(Shopify)"),E59*19/119,0) -> 0 | H59: =IF(F59="Débito",0.0275,IF(F59="Crédito",0.0295,0)) -> 0 | I59: =E59*H59 -> 0 | J59: =E59-G59-I59 -> 310000 | K59: =IF($O59<>"Tienda",0,IF(OR($F59="Débito",$F59="Crédito"),0.05,IF(OR($F59="Efectivo",$F59="Transferencia"),0.07,0))) -> 0.07 | L59: =IF($O59<>"Tienda",0,$J59*$K59) -> 21700 | M59: =E59-G59-I59-L59 -> 288300 | N59: pagar 220.0000 | O59: Tienda
G60: =IF(OR(F60="Débito",F60="Crédito",F60="Internet(Shopify)"),E60*19/119,0) -> 0 | H60: =IF(F60="Débito",0.0275,IF(F60="Crédito",0.0295,0)) -> 0 | I60: =E60*H60 -> 0 | J60: =E60-G60-I60 -> 0 | K60: =IF($O60<>"Tienda",0,IF(OR($F60="Débito",$F60="Crédito"),0.05,IF(OR($F60="Efectivo",$F60="Transferencia"),0.07,0))) -> 0 | L60: =IF($O60<>"Tienda",0,$J60*$K60) -> 0 | M60: =E60-G60-I60-L60 -> 0
G61: =IF(OR(F61="Débito",F61="Crédito",F61="Internet(Shopify)"),E61*19/119,0) -> 0 | H61: =IF(F61="Débito",0.0275,IF(F61="Crédito",0.0295,0)) -> 0 | I61: =E61*H61 -> 0 | J61: =E61-G61-I61 -> 0 | K61: =IF($O61<>"Tienda",0,IF(OR($F61="Débito",$F61="Crédito"),0.05,IF(OR($F61="Efectivo",$F61="Transferencia"),0.07,0))) -> 0 | L61: =IF($O61<>"Tienda",0,$J61*$K61) -> 0 | M61: =E61-G61-I61-L61 -> 0
G62: =IF(OR(F62="Débito",F62="Crédito",F62="Internet(Shopify)"),E62*19/119,0) -> 0 | H62: =IF(F62="Débito",0.0275,IF(F62="Crédito",0.0295,0)) -> 0 | I62: =E62*H62 -> 0 | J62: =E62-G62-I62 -> 0 | K62: =IF($O62<>"Tienda",0,IF(OR($F62="Débito",$F62="Crédito"),0.05,IF(OR($F62="Efectivo",$F62="Transferencia"),0.07,0))) -> 0 | L62: =IF($O62<>"Tienda",0,$J62*$K62) -> 0 | M62: =E62-G62-I62-L62 -> 0
G63: =IF(OR(F63="Débito",F63="Crédito",F63="Internet(Shopify)"),E63*19/119,0) -> 0 | H63: =IF(F63="Débito",0.0275,IF(F63="Crédito",0.0295,0)) -> 0 | I63: =E63*H63 -> 0 | J63: =E63-G63-I63 -> 0 | K63: =IF($O63<>"Tienda",0,IF(OR($F63="Débito",$F63="Crédito"),0.05,IF(OR($F63="Efectivo",$F63="Transferencia"),0.07,0))) -> 0 | L63: =IF($O63<>"Tienda",0,$J63*$K63) -> 0 | M63: =E63-G63-I63-L63 -> 0
G64: =IF(OR(F64="Débito",F64="Crédito",F64="Internet(Shopify)"),E64*19/119,0) -> 0 | H64: =IF(F64="Débito",0.0275,IF(F64="Crédito",0.0295,0)) -> 0 | I64: =E64*H64 -> 0 | J64: =E64-G64-I64 -> 0 | K64: =IF($O64<>"Tienda",0,IF(OR($F64="Débito",$F64="Crédito"),0.05,IF(OR($F64="Efectivo",$F64="Transferencia"),0.07,0))) -> 0 | L64: =IF($O64<>"Tienda",0,$J64*$K64) -> 0 | M64: =E64-G64-I64-L64 -> 0
G65: =IF(OR(F65="Débito",F65="Crédito",F65="Internet(Shopify)"),E65*19/119,0) -> 0 | H65: =IF(F65="Débito",0.0275,IF(F65="Crédito",0.0295,0)) -> 0 | I65: =E65*H65 -> 0 | J65: =E65-G65-I65 -> 0 | K65: =IF($O65<>"Tienda",0,IF(OR($F65="Débito",$F65="Crédito"),0.05,IF(OR($F65="Efectivo",$F65="Transferencia"),0.07,0))) -> 0 | L65: =IF($O65<>"Tienda",0,$J65*$K65) -> 0 | M65: =E65-G65-I65-L65 -> 0
G66: =IF(OR(F66="Débito",F66="Crédito",F66="Internet(Shopify)"),E66*19/119,0) -> 0 | H66: =IF(F66="Débito",0.0275,IF(F66="Crédito",0.0295,0)) -> 0 | I66: =E66*H66 -> 0 | J66: =E66-G66-I66 -> 0 | K66: =IF($O66<>"Tienda",0,IF(OR($F66="Débito",$F66="Crédito"),0.05,IF(OR($F66="Efectivo",$F66="Transferencia"),0.07,0))) -> 0 | L66: =IF($O66<>"Tienda",0,$J66*$K66) -> 0 | M66: =E66-G66-I66-L66 -> 0
G67: =IF(OR(F67="Débito",F67="Crédito",F67="Internet(Shopify)"),E67*19/119,0) -> 0 | H67: =IF(F67="Débito",0.0275,IF(F67="Crédito",0.0295,0)) -> 0 | I67: =E67*H67 -> 0 | J67: =E67-G67-I67 -> 0 | K67: =IF($O67<>"Tienda",0,IF(OR($F67="Débito",$F67="Crédito"),0.05,IF(OR($F67="Efectivo",$F67="Transferencia"),0.07,0))) -> 0 | L67: =IF($O67<>"Tienda",0,$J67*$K67) -> 0 | M67: =E67-G67-I67-L67 -> 0
G68: =IF(OR(F68="Débito",F68="Crédito",F68="Internet(Shopify)"),E68*19/119,0) -> 0 | H68: =IF(F68="Débito",0.0275,IF(F68="Crédito",0.0295,0)) -> 0 | I68: =E68*H68 -> 0 | J68: =E68-G68-I68 -> 0 | K68: =IF($O68<>"Tienda",0,IF(OR($F68="Débito",$F68="Crédito"),0.05,IF(OR($F68="Efectivo",$F68="Transferencia"),0.07,0))) -> 0 | L68: =IF($O68<>"Tienda",0,$J68*$K68) -> 0 | M68: =E68-G68-I68-L68 -> 0
G69: =IF(OR(F69="Débito",F69="Crédito",F69="Internet(Shopify)"),E69*19/119,0) -> 0 | H69: =IF(F69="Débito",0.0275,IF(F69="Crédito",0.0295,0)) -> 0 | I69: =E69*H69 -> 0 | J69: =E69-G69-I69 -> 0 | K69: =IF($O69<>"Tienda",0,IF(OR($F69="Débito",$F69="Crédito"),0.05,IF(OR($F69="Efectivo",$F69="Transferencia"),0.07,0))) -> 0 | L69: =IF($O69<>"Tienda",0,$J69*$K69) -> 0 | M69: =E69-G69-I69-L69 -> 0
G70: =IF(OR(F70="Débito",F70="Crédito",F70="Internet(Shopify)"),E70*19/119,0) -> 0 | H70: =IF(F70="Débito",0.0275,IF(F70="Crédito",0.0295,0)) -> 0 | I70: =E70*H70 -> 0 | J70: =E70-G70-I70 -> 0 | K70: =IF($O70<>"Tienda",0,IF(OR($F70="Débito",$F70="Crédito"),0.05,IF(OR($F70="Efectivo",$F70="Transferencia"),0.07,0))) -> 0 | L70: =IF($O70<>"Tienda",0,$J70*$K70) -> 0 | M70: =E70-G70-I70-L70 -> 0
G71: =IF(OR(F71="Débito",F71="Crédito",F71="Internet(Shopify)"),E71*19/119,0) -> 0 | H71: =IF(F71="Débito",0.0275,IF(F71="Crédito",0.0295,0)) -> 0 | I71: =E71*H71 -> 0 | J71: =E71-G71-I71 -> 0 | K71: =IF($O71<>"Tienda",0,IF(OR($F71="Débito",$F71="Crédito"),0.05,IF(OR($F71="Efectivo",$F71="Transferencia"),0.07,0))) -> 0 | L71: =IF($O71<>"Tienda",0,$J71*$K71) -> 0 | M71: =E71-G71-I71-L71 -> 0
... G103: =IF(OR(F103="Débito",F103="Crédito",F103="Internet(Shopify)"),E103*19/119,0) -> 0 | H103: =IF(F103="Débito",0.0275,IF(F103="Crédito",0.0295,0)) -> 0 | I103: =E103*H103 -> 0 | J103: =E103-G103-I103 -> 0 | K103: =IF($O103<>"Tienda",0,IF(OR($F103="Débito",$F103="Crédito"),0.05,IF(OR($F103="Efectivo",$F103="Transferencia"),0.07,0))) -> 0 | L103: =IF($O103<>"Tienda",0,$J103*$K103) -> 0 | M103: =E103-G103-I103-L103 -> 0
A108: Abril - Gastos Fijos | G108: Abril - Gastos Extra
A109: Nombre gasto | B109: Monto (CLP) | C109: Notas | G109: Nombre gasto | H109: Monto (CLP) | I109: Fecha | J109: Notas
A110: Arriendo (CLP calculado con UF) | B110: =Parametros!$B$1*Parametros!$B$2 -> 1463000
A111: Gastos comunes | B111: 70000
A112: ADT | B112: 69000
A113: Internet | B113: 39960
A114: Luz (promedio) | B114: 35000
A115: Agua (promedio) | B115: 25000
A116: Shopify | B116: 50000
A130: Total gastos fijos | B130: =SUM(B110:B129) -> 1751960 | G130: Total gastos extra | H130: =SUM(H110:H129) -> 0
A131: Gasto fijo por integrante (÷5) | B131: =B130/5 -> 350392

Sheet Enero
A1: Enero - Ingresos
P2: Total ventas brutas | Q2: =SUM(E4:E103) -> 0
A3: Nombre prenda | B3: Talla | C3: Propietario prenda | D3: Vendedor | E3: Precio venta (BRUTO) | F3: Tipo de pago | G3: IVA (19%) | H3: % comisión bancaria | I3: $ comisión bancaria | J3: Base comisión vendedor | K3: % comisión vendedor | L3: $ comisión vendedor | M3: Neto tienda | N3: Observaciones | O3: Marca (Tienda/externa) | P3: Total IVA ventas | Q3: =SUM(G4:G103) -> 0
G4: =IF(OR(F4="Débito",F4="Crédito",F4="Internet(Shopify)"),E4*19/119,0) -> 0 | H4: =IF(F4="Débito",0.0275,IF(F4="Crédito",0.0295,0)) -> 0 | I4: =E4*H4 -> 0 | J4: =E4-G4-I4 -> 0 | K4: =IF($O4<>"Tienda",0,IF(OR($F4="Débito",$F4="Crédito"),0.05,IF(OR($F4="Efectivo",$F4="Transferencia"),0.07,0))) -> 0 | L4: =IF($O4<>"Tienda",0,$J4*$K4) -> 0 | M4: =E4-G4-I4-L4 -> 0 | O4: Tienda | P4: Total comisiones bancarias | Q4: =SUM(I4:I103) -> 0
G5: =IF(OR(F5="Débito",F5="Crédito",F5="Internet(Shopify)"),E5*19/119,0) -> 0 | H5: =IF(F5="Débito",0.0275,IF(F5="Crédito",0.0295,0)) -> 0 | I5: =E5*H5 -> 0 | J5: =E5-G5-I5 -> 0 | K5: =IF($O5<>"Tienda",0,IF(OR($F5="Débito",$F5="Crédito"),0.05,IF(OR($F5="Efectivo",$F5="Transferencia"),0.07,0))) -> 0 | L5: =IF($O5<>"Tienda",0,$J5*$K5) -> 0 | M5: =E5-G5-I5-L5 -> 0 | P5: Total comisiones vendedores (NO se divide) | Q5: =SUM(L4:L103) -> 0
G6: =IF(OR(F6="Débito",F6="Crédito",F6="Internet(Shopify)"),E6*19/119,0) -> 0 | H6: =IF(F6="Débito",0.0275,IF(F6="Crédito",0.0295,0)) -> 0 | I6: =E6*H6 -> 0 | J6: =E6-G6-I6 -> 0 | K6: =IF($O6<>"Tienda",0,IF(OR($F6="Débito",$F6="Crédito"),0.05,IF(OR($F6="Efectivo",$F6="Transferencia"),0.07,0))) -> 0 | L6: =IF($O6<>"Tienda",0,$J6*$K6) -> 0 | M6: =E6-G6-I6-L6 -> 0 | P6: Total neto tienda (NO se divide) | Q6: =SUM(M4:M103) -> 0
G7: =IF(OR(F7="Débito",F7="Crédito",F7="Internet(Shopify)"),E7*19/119,0) -> 0 | H7: =IF(F7="Débito",0.0275,IF(F7="Crédito",0.0295,0)) -> 0 | I7: =E7*H7 -> 0 | J7: =E7-G7-I7 -> 0 | K7: =IF($O7<>"Tienda",0,IF(OR($F7="Débito",$F7="Crédito"),0.05,IF(OR($F7="Efectivo",$F7="Transferencia"),0.07,0))) -> 0 | L7: =IF($O7<>"Tienda",0,$J7*$K7) -> 0 | M7: =E7-G7-I7-L7 -> 0 | P7: Número de ventas | Q7: =COUNTA(E4:E103) -> 0
G8: =IF(OR(F8="Débito",F8="Crédito",F8="Internet(Shopify)"),E8*19/119,0) -> 0 | H8: =IF(F8="Débito",0.0275,IF(F8="Crédito",0.0295,0)) -> 0 | I8: =E8*H8 -> 0 | J8: =E8-G8-I8 -> 0 | K8: =IF($O8<>"Tienda",0,IF(OR($F8="Débito",$F8="Crédito"),0.05,IF(OR($F8="Efectivo",$F8="Transferencia"),0.07,0))) -> 0 | L8: =IF($O8<>"Tienda",0,$J8*$K8) -> 0 | M8: =E8-G8-I8-L8 -> 0 | P8: Ticket promedio (NETO) | Q8: =IF(Q7=0,0,Q6/Q7) -> 0
G9: =IF(OR(F9="Débito",F9="Crédito",F9="Internet(Shopify)"),E9*19/119,0) -> 0 | H9: =IF(F9="Débito",0.0275,IF(F9="Crédito",0.0295,0)) -> 0 | I9: =E9*H9 -> 0 | J9: =E9-G9-I9 -> 0 | K9: =IF($O9<>"Tienda",0,IF(OR($F9="Débito",$F9="Crédito"),0.05,IF(OR($F9="Efectivo",$F9="Transferencia"),0.07,0))) -> 0 | L9: =IF($O9<>"Tienda",0,$J9*$K9) -> 0 | M9: =E9-G9-I9-L9 -> 0 | P9: Ventas débito (neto) | Q9: =SUMIF(F4:F103,"Débito",M4:M103) -> 0
G10: =IF(OR(F10="Débito",F10="Crédito",F10="Internet(Shopify)"),E10*19/119,0) -> 0 | H10: =IF(F10="Débito",0.0275,IF(F10="Crédito",0.0295,0)) -> 0 | I10: =E10*H10 -> 0 | J10: =E10-G10-I10 -> 0 | K10: =IF($O10<>"Tienda",0,IF(OR($F10="Débito",$F10="Crédito"),0.05,IF(OR($F10="Efectivo",$F10="Transferencia"),0.07,0))) -> 0 | L10: =IF($O10<>"Tienda",0,$J10*$K10) -> 0 | M10: =E10-G10-I10-L10 -> 0 | P10: Ventas crédito (neto) | Q10: =SUMIF(F4:F103,"Crédito",M4:M103) -> 0
G11: =IF(OR(F11="Débito",F11="Crédito",F11="Internet(Shopify)"),E11*19/119,0) -> 0 | H11: =IF(F11="Débito",0.0275,IF(F11="Crédito",0.0295,0)) -> 0 | I11: =E11*H11 -> 0 | J11: =E11-G11-I11 -> 0 | K11: =IF($O11<>"Tienda",0,IF(OR($F11="Débito",$F11="Crédito"),0.05,IF(OR($F11="Efectivo",$F11="Transferencia"),0.07,0))) -> 0 | L11: =IF($O11<>"Tienda",0,$J11*$K11) -> 0 | M11: =E11-G11-I11-L11 -> 0 | P11: Ventas efectivo (neto) | Q11: =SUMIF(F4:F103,"Efectivo",M4:M103) -> 0
G12: =IF(OR(F12="Débito",F12="Crédito",F12="Internet(Shopify)"),E12*19/119,0) -> 0 | H12: =IF(F12="Débito",0.0275,IF(F12="Crédito",0.0295,0)) -> 0 | I12: =E12*H12 -> 0 | J12: =E12-G12-I12 -> 0 | K12: =IF($O12<>"Tienda",0,IF(OR($F12="Débito",$F12="Crédito"),0.05,IF(OR($F12="Efectivo",$F12="Transferencia"),0.07,0))) -> 0 | L12: =IF($O12<>"Tienda",0,$J12*$K12) -> 0 | M12: =E12-G12-I12-L12 -> 0 | P12: Ventas transferencia (neto) | Q12: =SUMIF(F4:F103,"Transferencia",M4:M103) -> 0
G13: =IF(OR(F13="Débito",F13="Crédito",F13="Internet(Shopify)"),E13*19/119,0) -> 0 | H13: =IF(F13="Débito",0.0275,IF(F13="Crédito",0.0295,0)) -> 0 | I13: =E13*H13 -> 0 | J13: =E13-G13-I13 -> 0 | K13: =IF($O13<>"Tienda",0,IF(OR($F13="Débito",$F13="Crédito"),0.05,IF(OR($F13="Efectivo",$F13="Transferencia"),0.07,0))) -> 0 | L13: =IF($O13<>"Tienda",0,$J13*$K13) -> 0 | M13: =E13-G13-I13-L13 -> 0 | P13: Ventas Internet(Shopify) (neto) | Q13: =SUMIF(F4:F103,"Internet(Shopify)",M4:M103) -> 0
G14: =IF(OR(F14="Débito",F14="Crédito",F14="Internet(Shopify)"),E14*19/119,0) -> 0 | H14: =IF(F14="Débito",0.0275,IF(F14="Crédito",0.0295,0)) -> 0 | I14: =E14*H14 -> 0 | J14: =E14-G14-I14 -> 0 | K14: =IF($O14<>"Tienda",0,IF(OR($F14="Débito",$F14="Crédito"),0.05,IF(OR($F14="Efectivo",$F14="Transferencia"),0.07,0))) -> 0 | L14: =IF($O14<>"Tienda",0,$J14*$K14) -> 0 | M14: =E14-G14-I14-L14 -> 0 | P14: Ventas cuenta común (D+C+T) NETO | Q14: =SUMIF(F4:F103,"Débito",M4:M103)+SUMIF(F4:F103,"Crédito",M4:M103)+SUMIF(F4:F103,"Transferencia",M4:M103) -> 0
G15: =IF(OR(F15="Débito",F15="Crédito",F15="Internet(Shopify)"),E15*19/119,0) -> 0 | H15: =IF(F15="Débito",0.0275,IF(F15="Crédito",0.0295,0)) -> 0 | I15: =E15*H15 -> 0 | J15: =E15-G15-I15 -> 0 | K15: =IF($O15<>"Tienda",0,IF(OR($F15="Débito",$F15="Crédito"),0.05,IF(OR($F15="Efectivo",$F15="Transferencia"),0.07,0))) -> 0 | L15: =IF($O15<>"Tienda",0,$J15*$K15) -> 0 | M15: =E15-G15-I15-L15 -> 0 | P15: IVA compras (manual)
G16: =IF(OR(F16="Débito",F16="Crédito",F16="Internet(Shopify)"),E16*19/119,0) -> 0 | H16: =IF(F16="Débito",0.0275,IF(F16="Crédito",0.0295,0)) -> 0 | I16: =E16*H16 -> 0 | J16: =E16-G16-I16 -> 0 | K16: =IF($O16<>"Tienda",0,IF(OR($F16="Débito",$F16="Crédito"),0.05,IF(OR($F16="Efectivo",$F16="Transferencia"),0.07,0))) -> 0 | L16: =IF($O16<>"Tienda",0,$J16*$K16) -> 0 | M16: =E16-G16-I16-L16 -> 0 | P16: IVA neto (ventas - compras) | Q16: =Q3-Q15 -> 0
G17: =IF(OR(F17="Débito",F17="Crédito",F17="Internet(Shopify)"),E17*19/119,0) -> 0 | H17: =IF(F17="Débito",0.0275,IF(F17="Crédito",0.0295,0)) -> 0 | I17: =E17*H17 -> 0 | J17: =E17-G17-I17 -> 0 | K17: =IF($O17<>"Tienda",0,IF(OR($F17="Débito",$F17="Crédito"),0.05,IF(OR($F17="Efectivo",$F17="Transferencia"),0.07,0))) -> 0 | L17: =IF($O17<>"Tienda",0,$J17*$K17) -> 0 | M17: =E17-G17-I17-L17 -> 0
G18: =IF(OR(F18="Débito",F18="Crédito",F18="Internet(Shopify)"),E18*19/119,0) -> 0 | H18: =IF(F18="Débito",0.0275,IF(F18="Crédito",0.0295,0)) -> 0 | I18: =E18*H18 -> 0 | J18: =E18-G18-I18 -> 0 | K18: =IF($O18<>"Tienda",0,IF(OR($F18="Débito",$F18="Crédito"),0.05,IF(OR($F18="Efectivo",$F18="Transferencia"),0.07,0))) -> 0 | L18: =IF($O18<>"Tienda",0,$J18*$K18) -> 0 | M18: =E18-G18-I18-L18 -> 0
G19: =IF(OR(F19="Débito",F19="Crédito",F19="Internet(Shopify)"),E19*19/119,0) -> 0 | H19: =IF(F19="Débito",0.0275,IF(F19="Crédito",0.0295,0)) -> 0 | I19: =E19*H19 -> 0 | J19: =E19-G19-I19 -> 0 | K19: =IF($O19<>"Tienda",0,IF(OR($F19="Débito",$F19="Crédito"),0.05,IF(OR($F19="Efectivo",$F19="Transferencia"),0.07,0))) -> 0 | L19: =IF($O19<>"Tienda",0,$J19*$K19) -> 0 | M19: =E19-G19-I19-L19 -> 0
G20: =IF(OR(F20="Débito",F20="Crédito",F20="Internet(Shopify)"),E20*19/119,0) -> 0 | H20: =IF(F20="Débito",0.0275,IF(F20="Crédito",0.0295,0)) -> 0 | I20: =E20*H20 -> 0 | J20: =E20-G20-I20 -> 0 | K20: =IF($O20<>"Tienda",0,IF(OR($F20="Débito",$F20="Crédito"),0.05,IF(OR($F20="Efectivo",$F20="Transferencia"),0.07,0))) -> 0 | L20: =IF($O20<>"Tienda",0,$J20*$K20) -> 0 | M20: =E20-G20-I20-L20 -> 0
G21: =IF(OR(F21="Débito",F21="Crédito",F21="Internet(Shopify)"),E21*19/119,0) -> 0 | H21: =IF(F21="Débito",0.0275,IF(F21="Crédito",0.0295,0)) -> 0 | I21: =E21*H21 -> 0 | J21: =E21-G21-I21 -> 0 | K21: =IF($O21<>"Tienda",0,IF(OR($F21="Débito",$F21="Crédito"),0.05,IF(OR($F21="Efectivo",$F21="Transferencia"),0.07,0))) -> 0 | L21: =IF($O21<>"Tienda",0,$J21*$K21) -> 0 | M21: =E21-G21-I21-L21 -> 0
G22: =IF(OR(F22="Débito",F22="Crédito",F22="Internet(Shopify)"),E22*19/119,0) -> 0 | H22: =IF(F22="Débito",0.0275,IF(F22="Crédito",0.0295,0)) -> 0 | I22: =E22*H22 -> 0 | J22: =E22-G22-I22 -> 0 | K22: =IF($O22<>"Tienda",0,IF(OR($F22="Débito",$F22="Crédito"),0.05,IF(OR($F22="Efectivo",$F22="Transferencia"),0.07,0))) -> 0 | L22: =IF($O22<>"Tienda",0,$J22*$K22) -> 0 | M22: =E22-G22-I22-L22 -> 0
G23: =IF(OR(F23="Débito",F23="Crédito",F23="Internet(Shopify)"),E23*19/119,0) -> 0 | H23: =IF(F23="Débito",0.0275,IF(F23="Crédito",0.0295,0)) -> 0 | I23: =E23*H23 -> 0 | J23: =E23-G23-I23 -> 0 | K23: =IF($O23<>"Tienda",0,IF(OR($F23="Débito",$F23="Crédito"),0.05,IF(OR($F23="Efectivo",$F23="Transferencia"),0.07,0))) -> 0 | L23: =IF($O23<>"Tienda",0,$J23*$K23) -> 0 | M23: =E23-G23-I23-L23 -> 0
G24: =IF(OR(F24="Débito",F24="Crédito",F24="Internet(Shopify)"),E24*19/119,0) -> 0 | H24: =IF(F24="Débito",0.0275,IF(F24="Crédito",0.0295,0)) -> 0 | I24: =E24*H24 -> 0 | J24: =E24-G24-I24 -> 0 | K24: =IF($O24<>"Tienda",0,IF(OR($F24="Débito",$F24="Crédito"),0.05,IF(OR($F24="Efectivo",$F24="Transferencia"),0.07,0))) -> 0 | L24: =IF($O24<>"Tienda",0,$J24*$K24) -> 0 | M24: =E24-G24-I24-L24 -> 0
G25: =IF(OR(F25="Débito",F25="Crédito",F25="Internet(Shopify)"),E25*19/119,0) -> 0 | H25: =IF(F25="Débito",0.0275,IF(F25="Crédito",0.0295,0)) -> 0 | I25: =E25*H25 -> 0 | J25: =E25-G25-I25 -> 0 | K25: =IF($O25<>"Tienda",0,IF(OR($F25="Débito",$F25="Crédito"),0.05,IF(OR($F25="Efectivo",$F25="Transferencia"),0.07,0))) -> 0 | L25: =IF($O25<>"Tienda",0,$J25*$K25) -> 0 | M25: =E25-G25-I25-L25 -> 0
G26: =IF(OR(F26="Débito",F26="Crédito",F26="Internet(Shopify)"),E26*19/119,0) -> 0 | H26: =IF(F26="Débito",0.0275,IF(F26="Crédito",0.0295,0)) -> 0 | I26: =E26*H26 -> 0 | J26: =E26-G26-I26 -> 0 | K26: =IF($O26<>"Tienda",0,IF(OR($F26="Débito",$F26="Crédito"),0.05,IF(OR($F26="Efectivo",$F26="Transferencia"),0.07,0))) -> 0 | L26: =IF($O26<>"Tienda",0,$J26*$K26) -> 0 | M26: =E26-G26-I26-L26 -> 0
G27: =IF(OR(F27="Débito",F27="Crédito",F27="Internet(Shopify)"),E27*19/119,0) -> 0 | H27: =IF(F27="Débito",0.0275,IF(F27="Crédito",0.0295,0)) -> 0 | I27: =E27*H27 -> 0 | J27: =E27-G27-I27 -> 0 | K27: =IF($O27<>"Tienda",0,IF(OR($F27="Débito",$F27="Crédito"),0.05,IF(OR($F27="Efectivo",$F27="Transferencia"),0.07,0))) -> 0 | L27: =IF($O27<>"Tienda",0,$J27*$K27) -> 0 | M27: =E27-G27-I27-L27 -> 0
G28: =IF(OR(F28="Débito",F28="Crédito",F28="Internet(Shopify)"),E28*19/119,0) -> 0 | H28: =IF(F28="Débito",0.0275,IF(F28="Crédito",0.0295,0)) -> 0 | I28: =E28*H28 -> 0 | J28: =E28-G28-I28 -> 0 | K28: =IF($O28<>"Tienda",0,IF(OR($F28="Débito",$F28="Crédito"),0.05,IF(OR($F28="Efectivo",$F28="Transferencia"),0.07,0))) -> 0 | L28: =IF($O28<>"Tienda",0,$J28*$K28) -> 0 | M28: =E28-G28-I28-L28 -> 0
... G103: =IF(OR(F103="Débito",F103="Crédito",F103="Internet(Shopify)"),E103*19/119,0) -> 0 | H103: =IF(F103="Débito",0.0275,IF(F103="Crédito",0.0295,0)) -> 0 | I103: =E103*H103 -> 0 | J103: =E103-G103-I103 -> 0 | K103: =IF($O103<>"Tienda",0,IF(OR($F103="Débito",$F103="Crédito"),0.05,IF(OR($F103="Efectivo",$F103="Transferencia"),0.07,0))) -> 0 | L103: =IF($O103<>"Tienda",0,$J103*$K103) -> 0 | M103: =E103-G103-I103-L103 -> 0
A108: Enero - Gastos Fijos | G108: Enero - Gastos Extra
A109: Nombre gasto | B109: Monto (CLP) | C109: Notas | G109: Nombre gasto | H109: Monto (CLP) | I109: Fecha | J109: Notas
A110: Arriendo (CLP calculado con UF) | B110: =Parametros!$B$1*Parametros!$B$2 -> 1463000
A111: Gastos comunes | B111: 70000
A112: ADT | B112: 69000
A113: Internet | B113: 39960
A114: Luz (promedio) | B114: 35000
A115: Agua (promedio) | B115: 25000
A116: Shopify | B116: 50000
A130: Total gastos fijos | B130: =SUM(B110:B129) -> 1751960 | G130: Total gastos extra | H130: =SUM(H110:H129) -> 0
A131: Gasto fijo por integrante (÷5) | B131: =B130/5 -> 350392

Sheet Febrero
A1: Febrero - Ingresos
P2: Total ventas brutas | Q2: =SUM(E4:E103) -> 2701600
A3: Nombre prenda | B3: Talla | C3: Propietario prenda | D3: Vendedor | E3: Precio venta (BRUTO) | F3: Tipo de pago | G3: IVA (19%) | H3: % comisión bancaria | I3: $ comisión bancaria | J3: Base comisión vendedor | K3: % comisión vendedor | L3: $ comisión vendedor | M3: Neto tienda | N3: Observaciones | O3: Marca (Tienda/externa) | P3: Total IVA ventas | Q3: =SUM(G4:G103) -> 8781.5126
A4: chaqueta JPG | B4: S | C4: Benja R | D4: Marenna | E4: 300000 | F4: Transferencia | G4: =IF(OR(F4="Débito",F4="Crédito",F4="Internet(Shopify)"),E4*19/119,0) -> 0 | H4: =IF(F4="Débito",0.0275,IF(F4="Crédito",0.0295,0)) -> 0 | I4: =E4*H4 -> 0 | J4: =E4-G4-I4 -> 300000 | K4: =IF($O4<>"Tienda",0,IF(OR($F4="Débito",$F4="Crédito"),0.05,IF(OR($F4="Efectivo",$F4="Transferencia"),0.07,0))) -> 0.07 | L4: =IF($O4<>"Tienda",0,$J4*$K4) -> 21000 | M4: =E4-G4-I4-L4 -> 279000 | O4: Tienda | P4: Total comisiones bancarias | Q4: =SUM(I4:I103) -> 1512.5
A5: polera Vivienne Westwood | B5: xs | C5: Benja R | D5: Benja R | E5: 40000 | F5: Transferencia | G5: =IF(OR(F5="Débito",F5="Crédito",F5="Internet(Shopify)"),E5*19/119,0) -> 0 | H5: =IF(F5="Débito",0.0275,IF(F5="Crédito",0.0295,0)) -> 0 | I5: =E5*H5 -> 0 | J5: =E5-G5-I5 -> 40000 | K5: =IF($O5<>"Tienda",0,IF(OR($F5="Débito",$F5="Crédito"),0.05,IF(OR($F5="Efectivo",$F5="Transferencia"),0.07,0))) -> 0.07 | L5: =IF($O5<>"Tienda",0,$J5*$K5) -> 2800 | M5: =E5-G5-I5-L5 -> 37200 | N5: pagado | O5: Tienda | P5: Total comisiones vendedores (NO se divide) | Q5: =SUM(L4:L103) -> 145287.3
A6: chaqueta JPG | G6: =IF(OR(F6="Débito",F6="Crédito",F6="Internet(Shopify)"),E6*19/119,0) -> 0 | H6: =IF(F6="Débito",0.0275,IF(F6="Crédito",0.0295,0)) -> 0 | I6: =E6*H6 -> 0 | J6: =E6-G6-I6 -> 0 | K6: =IF($O6<>"Tienda",0,IF(OR($F6="Débito",$F6="Crédito"),0.05,IF(OR($F6="Efectivo",$F6="Transferencia"),0.07,0))) -> 0 | L6: =IF($O6<>"Tienda",0,$J6*$K6) -> 0 | M6: =E6-G6-I6-L6 -> 0 | P6: Total neto tienda (NO se divide) | Q6: =SUM(M4:M103) -> 2546018.7
A7: polera dyg | B7: s | C7: Benja R | D7: Marenna | E7: 30000 | F7: Transferencia | G7: =IF(OR(F7="Débito",F7="Crédito",F7="Internet(Shopify)"),E7*19/119,0) -> 0 | H7: =IF(F7="Débito",0.0275,IF(F7="Crédito",0.0295,0)) -> 0 | I7: =E7*H7 -> 0 | J7: =E7-G7-I7 -> 30000 | K7: =IF($O7<>"Tienda",0,IF(OR($F7="Débito",$F7="Crédito"),0.05,IF(OR($F7="Efectivo",$F7="Transferencia"),0.07,0))) -> 0.07 | L7: =IF($O7<>"Tienda",0,$J7*$K7) -> 2100 | M7: =E7-G7-I7-L7 -> 27900 | O7: Tienda | P7: Número de ventas | Q7: =COUNTA(E4:E103) -> 59
A8: bolso wear pedritos | C8: Tienda | D8: Marenna | E8: 40000 | F8: Transferencia | G8: =IF(OR(F8="Débito",F8="Crédito",F8="Internet(Shopify)"),E8*19/119,0) -> 0 | H8: =IF(F8="Débito",0.0275,IF(F8="Crédito",0.0295,0)) -> 0 | I8: =E8*H8 -> 0 | J8: =E8-G8-I8 -> 40000 | K8: =IF($O8<>"Tienda",0,IF(OR($F8="Débito",$F8="Crédito"),0.05,IF(OR($F8="Efectivo",$F8="Transferencia"),0.07,0))) -> 0 | L8: =IF($O8<>"Tienda",0,$J8*$K8) -> 0 | M8: =E8-G8-I8-L8 -> 40000 | N8: Pedritos (30.000) | O8: Pedritos | P8: Ticket promedio (NETO) | Q8: =IF(Q7=0,0,Q6/Q7) -> 43152.859
A9: Kenzo | B9: m | C9: Benja R | D9: Marenna | E9: 40000 | F9: Transferencia | G9: =IF(OR(F9="Débito",F9="Crédito",F9="Internet(Shopify)"),E9*19/119,0) -> 0 | H9: =IF(F9="Débito",0.0275,IF(F9="Crédito",0.0295,0)) -> 0 | I9: =E9*H9 -> 0 | J9: =E9-G9-I9 -> 40000 | K9: =IF($O9<>"Tienda",0,IF(OR($F9="Débito",$F9="Crédito"),0.05,IF(OR($F9="Efectivo",$F9="Transferencia"),0.07,0))) -> 0.07 | L9: =IF($O9<>"Tienda",0,$J9*$K9) -> 2800 | M9: =E9-G9-I9-L9 -> 37200 | O9: Tienda | P9: Ventas débito (neto) | Q9: =SUMIF(F4:F103,"Débito",M4:M103) -> 42470.688
A10: polera pop disaster raton punk | B10: L | C10: Tienda | D10: Marenna | E10: 25000 | F10: Transferencia | G10: =IF(OR(F10="Débito",F10="Crédito",F10="Internet(Shopify)"),E10*19/119,0) -> 0 | H10: =IF(F10="Débito",0.0275,IF(F10="Crédito",0.0295,0)) -> 0 | I10: =E10*H10 -> 0 | J10: =E10-G10-I10 -> 25000 | K10: =IF($O10<>"Tienda",0,IF(OR($F10="Débito",$F10="Crédito"),0.05,IF(OR($F10="Efectivo",$F10="Transferencia"),0.07,0))) -> 0 | L10: =IF($O10<>"Tienda",0,$J10*$K10) -> 0 | M10: =E10-G10-I10-L10 -> 25000 | N10: PopDistaster (18.750) | O10: Pop disaster | P10: Ventas crédito (neto) | Q10: =SUMIF(F4:F103,"Crédito",M4:M103) -> 0
A11: SACAI | B11: XS | G11: =IF(OR(F11="Débito",F11="Crédito",F11="Internet(Shopify)"),E11*19/119,0) -> 0 | H11: =IF(F11="Débito",0.0275,IF(F11="Crédito",0.0295,0)) -> 0 | I11: =E11*H11 -> 0 | J11: =E11-G11-I11 -> 0 | K11: =IF($O11<>"Tienda",0,IF(OR($F11="Débito",$F11="Crédito"),0.05,IF(OR($F11="Efectivo",$F11="Transferencia"),0.07,0))) -> 0 | L11: =IF($O11<>"Tienda",0,$J11*$K11) -> 0 | M11: =E11-G11-I11-L11 -> 0 | P11: Ventas efectivo (neto) | Q11: =SUMIF(F4:F103,"Efectivo",M4:M103) -> 69750
A12: LeSang We understand.. | B12: s | C12: Tienda | D12: Marenna | E12: 20000 | F12: Transferencia | G12: =IF(OR(F12="Débito",F12="Crédito",F12="Internet(Shopify)"),E12*19/119,0) -> 0 | H12: =IF(F12="Débito",0.0275,IF(F12="Crédito",0.0295,0)) -> 0 | I12: =E12*H12 -> 0 | J12: =E12-G12-I12 -> 20000 | K12: =IF($O12<>"Tienda",0,IF(OR($F12="Débito",$F12="Crédito"),0.05,IF(OR($F12="Efectivo",$F12="Transferencia"),0.07,0))) -> 0.07 | L12: =IF($O12<>"Tienda",0,$J12*$K12) -> 1400 | M12: =E12-G12-I12-L12 -> 18600 | O12: Tienda | P12: Ventas transferencia (neto) | Q12: =SUMIF(F4:F103,"Transferencia",M4:M103) -> 2433798
A13: polera bape | B13: M | C13: Benja R | D13: Marenna | E13: 20000 | F13: Transferencia | G13: =IF(OR(F13="Débito",F13="Crédito",F13="Internet(Shopify)"),E13*19/119,0) -> 0 | H13: =IF(F13="Débito",0.0275,IF(F13="Crédito",0.0295,0)) -> 0 | I13: =E13*H13 -> 0 | J13: =E13-G13-I13 -> 20000 | K13: =IF($O13<>"Tienda",0,IF(OR($F13="Débito",$F13="Crédito"),0.05,IF(OR($F13="Efectivo",$F13="Transferencia"),0.07,0))) -> 0.07 | L13: =IF($O13<>"Tienda",0,$J13*$K13) -> 1400 | M13: =E13-G13-I13-L13 -> 18600 | O13: Tienda | P13: Ventas Internet(Shopify) (neto) | Q13: =SUMIF(F4:F103,"Internet(Shopify)",M4:M103) -> 0
A14: polera kenzo | B14: s | C14: Benja R | D14: Benja R | E14: 30000 | F14: Transferencia | G14: =IF(OR(F14="Débito",F14="Crédito",F14="Internet(Shopify)"),E14*19/119,0) -> 0 | H14: =IF(F14="Débito",0.0275,IF(F14="Crédito",0.0295,0)) -> 0 | I14: =E14*H14 -> 0 | J14: =E14-G14-I14 -> 30000 | K14: =IF($O14<>"Tienda",0,IF(OR($F14="Débito",$F14="Crédito"),0.05,IF(OR($F14="Efectivo",$F14="Transferencia"),0.07,0))) -> 0.07 | L14: =IF($O14<>"Tienda",0,$J14*$K14) -> 2100 | M14: =E14-G14-I14-L14 -> 27900 | O14: Tienda | P14: Ventas cuenta común (D+C+T) NETO | Q14: =SUMIF(F4:F103,"Débito",M4:M103)+SUMIF(F4:F103,"Crédito",M4:M103)+SUMIF(F4:F103,"Transferencia",M4:M103) -> 2476268.7
A15: polera heron | B15: l | C15: Tienda | D15: Benja R | E15: 35000 | F15: Transferencia | G15: =IF(OR(F15="Débito",F15="Crédito",F15="Internet(Shopify)"),E15*19/119,0) -> 0 | H15: =IF(F15="Débito",0.0275,IF(F15="Crédito",0.0295,0)) -> 0 | I15: =E15*H15 -> 0 | J15: =E15-G15-I15 -> 35000 | K15: =IF($O15<>"Tienda",0,IF(OR($F15="Débito",$F15="Crédito"),0.05,IF(OR($F15="Efectivo",$F15="Transferencia"),0.07,0))) -> 0.07 | L15: =IF($O15<>"Tienda",0,$J15*$K15) -> 2450 | M15: =E15-G15-I15-L15 -> 32550 | O15: Tienda | P15: IVA compras (manual)
A16: polera idiot | B16: xs | C16: Tienda | D16: Marenna | E16: 25000 | F16: Transferencia | G16: =IF(OR(F16="Débito",F16="Crédito",F16="Internet(Shopify)"),E16*19/119,0) -> 0 | H16: =IF(F16="Débito",0.0275,IF(F16="Crédito",0.0295,0)) -> 0 | I16: =E16*H16 -> 0 | J16: =E16-G16-I16 -> 25000 | K16: =IF($O16<>"Tienda",0,IF(OR($F16="Débito",$F16="Crédito"),0.05,IF(OR($F16="Efectivo",$F16="Transferencia"),0.07,0))) -> 0 | L16: =IF($O16<>"Tienda",0,$J16*$K16) -> 0 | M16: =E16-G16-I16-L16 -> 25000 | N16: Popdisaster (18.750) | O16: Pop disaster | P16: IVA neto (ventas - compras) | Q16: =Q3-Q15 -> 8781.5126
A17: poleera cactus | B17: s | C17: Aaron | D17: Marenna | E17: 30000 | F17: Transferencia | G17: =IF(OR(F17="Débito",F17="Crédito",F17="Internet(Shopify)"),E17*19/119,0) -> 0 | H17: =IF(F17="Débito",0.0275,IF(F17="Crédito",0.0295,0)) -> 0 | I17: =E17*H17 -> 0 | J17: =E17-G17-I17 -> 30000 | K17: =IF($O17<>"Tienda",0,IF(OR($F17="Débito",$F17="Crédito"),0.05,IF(OR($F17="Efectivo",$F17="Transferencia"),0.07,0))) -> 0.07 | L17: =IF($O17<>"Tienda",0,$J17*$K17) -> 2100 | M17: =E17-G17-I17-L17 -> 27900 | O17: Tienda
A18: falda jill sanderss | B18: 38 | C18: Benja R | D18: Marenna | E18: 35000 | F18: Transferencia | G18: =IF(OR(F18="Débito",F18="Crédito",F18="Internet(Shopify)"),E18*19/119,0) -> 0 | H18: =IF(F18="Débito",0.0275,IF(F18="Crédito",0.0295,0)) -> 0 | I18: =E18*H18 -> 0 | J18: =E18-G18-I18 -> 35000 | K18: =IF($O18<>"Tienda",0,IF(OR($F18="Débito",$F18="Crédito"),0.05,IF(OR($F18="Efectivo",$F18="Transferencia"),0.07,0))) -> 0.07 | L18: =IF($O18<>"Tienda",0,$J18*$K18) -> 2450 | M18: =E18-G18-I18-L18 -> 32550 | O18: Tienda
A19: pantalon armani | B19: 40 | C19: Fabio | D19: Benja R | E19: 45000 | F19: Transferencia | G19: =IF(OR(F19="Débito",F19="Crédito",F19="Internet(Shopify)"),E19*19/119,0) -> 0 | H19: =IF(F19="Débito",0.0275,IF(F19="Crédito",0.0295,0)) -> 0 | I19: =E19*H19 -> 0 | J19: =E19-G19-I19 -> 45000 | K19: =IF($O19<>"Tienda",0,IF(OR($F19="Débito",$F19="Crédito"),0.05,IF(OR($F19="Efectivo",$F19="Transferencia"),0.07,0))) -> 0.07 | L19: =IF($O19<>"Tienda",0,$J19*$K19) -> 3150 | M19: =E19-G19-I19-L19 -> 41850 | O19: Tienda
A20: polera pique burberry | B20: L | C20: Benja R | D20: Benja R | E20: 40000 | F20: Transferencia | G20: =IF(OR(F20="Débito",F20="Crédito",F20="Internet(Shopify)"),E20*19/119,0) -> 0 | H20: =IF(F20="Débito",0.0275,IF(F20="Crédito",0.0295,0)) -> 0 | I20: =E20*H20 -> 0 | J20: =E20-G20-I20 -> 40000 | K20: =IF($O20<>"Tienda",0,IF(OR($F20="Débito",$F20="Crédito"),0.05,IF(OR($F20="Efectivo",$F20="Transferencia"),0.07,0))) -> 0.07 | L20: =IF($O20<>"Tienda",0,$J20*$K20) -> 2800 | M20: =E20-G20-I20-L20 -> 37200 | O20: Tienda
A21: Short Lee | B21: 48 | C21: Fabio | D21: Fabio | E21: 25000 | F21: Transferencia | G21: =IF(OR(F21="Débito",F21="Crédito",F21="Internet(Shopify)"),E21*19/119,0) -> 0 | H21: =IF(F21="Débito",0.0275,IF(F21="Crédito",0.0295,0)) -> 0 | I21: =E21*H21 -> 0 | J21: =E21-G21-I21 -> 25000 | K21: =IF($O21<>"Tienda",0,IF(OR($F21="Débito",$F21="Crédito"),0.05,IF(OR($F21="Efectivo",$F21="Transferencia"),0.07,0))) -> 0.07 | L21: =IF($O21<>"Tienda",0,$J21*$K21) -> 1750 | M21: =E21-G21-I21-L21 -> 23250 | O21: Tienda
A22: Lentes Gucci | B22: os | C22: Fabio | D22: Benja R | E22: 75000 | F22: Transferencia | G22: =IF(OR(F22="Débito",F22="Crédito",F22="Internet(Shopify)"),E22*19/119,0) -> 0 | H22: =IF(F22="Débito",0.0275,IF(F22="Crédito",0.0295,0)) -> 0 | I22: =E22*H22 -> 0 | J22: =E22-G22-I22 -> 75000 | K22: =IF($O22<>"Tienda",0,IF(OR($F22="Débito",$F22="Crédito"),0.05,IF(OR($F22="Efectivo",$F22="Transferencia"),0.07,0))) -> 0.07 | L22: =IF($O22<>"Tienda",0,$J22*$K22) -> 5250 | M22: =E22-G22-I22-L22 -> 69750 | O22: Tienda
A23: short pedritos tartan | B23: os | C23: Tienda | D23: Fabio | E23: 50000 | F23: Transferencia | G23: =IF(OR(F23="Débito",F23="Crédito",F23="Internet(Shopify)"),E23*19/119,0) -> 0 | H23: =IF(F23="Débito",0.0275,IF(F23="Crédito",0.0295,0)) -> 0 | I23: =E23*H23 -> 0 | J23: =E23-G23-I23 -> 50000 | K23: =IF($O23<>"Tienda",0,IF(OR($F23="Débito",$F23="Crédito"),0.05,IF(OR($F23="Efectivo",$F23="Transferencia"),0.07,0))) -> 0 | L23: =IF($O23<>"Tienda",0,$J23*$K23) -> 0 | M23: =E23-G23-I23-L23 -> 50000 | N23: Pedritos (37.500) | O23: Pedritos
A24: gorro pedritos denim | B24: os | C24: Tienda | D24: Fabio | E24: 18000 | F24: Transferencia | G24: =IF(OR(F24="Débito",F24="Crédito",F24="Internet(Shopify)"),E24*19/119,0) -> 0 | H24: =IF(F24="Débito",0.0275,IF(F24="Crédito",0.0295,0)) -> 0 | I24: =E24*H24 -> 0 | J24: =E24-G24-I24 -> 18000 | K24: =IF($O24<>"Tienda",0,IF(OR($F24="Débito",$F24="Crédito"),0.05,IF(OR($F24="Efectivo",$F24="Transferencia"),0.07,0))) -> 0 | L24: =IF($O24<>"Tienda",0,$J24*$K24) -> 0 | M24: =E24-G24-I24-L24 -> 18000 | N24: pedritos (13.500) | O24: Pedritos
A25: chaqueta stussy 90s | B25: M | C25: Aaron | D25: Aaron | E25: 0 | F25: Transferencia | G25: =IF(OR(F25="Débito",F25="Crédito",F25="Internet(Shopify)"),E25*19/119,0) -> 0 | H25: =IF(F25="Débito",0.0275,IF(F25="Crédito",0.0295,0)) -> 0 | I25: =E25*H25 -> 0 | J25: =E25-G25-I25 -> 0 | K25: =IF($O25<>"Tienda",0,IF(OR($F25="Débito",$F25="Crédito"),0.05,IF(OR($F25="Efectivo",$F25="Transferencia"),0.07,0))) -> 0.07 | L25: =IF($O25<>"Tienda",0,$J25*$K25) -> 0 | M25: =E25-G25-I25-L25 -> 0 | O25: Tienda
A26: polera louis vuitton | B26: l | C26: Aaron | D26: Aaron | E26: 0 | F26: Transferencia | G26: =IF(OR(F26="Débito",F26="Crédito",F26="Internet(Shopify)"),E26*19/119,0) -> 0 | H26: =IF(F26="Débito",0.0275,IF(F26="Crédito",0.0295,0)) -> 0 | I26: =E26*H26 -> 0 | J26: =E26-G26-I26 -> 0 | K26: =IF($O26<>"Tienda",0,IF(OR($F26="Débito",$F26="Crédito"),0.05,IF(OR($F26="Efectivo",$F26="Transferencia"),0.07,0))) -> 0.07 | L26: =IF($O26<>"Tienda",0,$J26*$K26) -> 0 | M26: =E26-G26-I26-L26 -> 0 | O26: Tienda
A27: polera baby milo | B27: s | C27: Benja R | D27: Aaron | E27: 40000 | F27: Transferencia | G27: =IF(OR(F27="Débito",F27="Crédito",F27="Internet(Shopify)"),E27*19/119,0) -> 0 | H27: =IF(F27="Débito",0.0275,IF(F27="Crédito",0.0295,0)) -> 0 | I27: =E27*H27 -> 0 | J27: =E27-G27-I27 -> 40000 | K27: =IF($O27<>"Tienda",0,IF(OR($F27="Débito",$F27="Crédito"),0.05,IF(OR($F27="Efectivo",$F27="Transferencia"),0.07,0))) -> 0.07 | L27: =IF($O27<>"Tienda",0,$J27*$K27) -> 2800 | M27: =E27-G27-I27-L27 -> 37200 | O27: Tienda
A28: polera le sang | B28: l | C28: Tienda | D28: Aaron | E28: 85800 | F28: Transferencia | G28: =IF(OR(F28="Débito",F28="Crédito",F28="Internet(Shopify)"),E28*19/119,0) -> 0 | H28: =IF(F28="Débito",0.0275,IF(F28="Crédito",0.0295,0)) -> 0 | I28: =E28*H28 -> 0 | J28: =E28-G28-I28 -> 85800 | K28: =IF($O28<>"Tienda",0,IF(OR($F28="Débito",$F28="Crédito"),0.05,IF(OR($F28="Efectivo",$F28="Transferencia"),0.07,0))) -> 0.07 | L28: =IF($O28<>"Tienda",0,$J28*$K28) -> 6006 | M28: =E28-G28-I28-L28 -> 79794 | O28: Tienda
A29: polera medalla light | B29: L | C29: Consignacion | D29: Benja R | E29: 30000 | F29: Transferencia | G29: =IF(OR(F29="Débito",F29="Crédito",F29="Internet(Shopify)"),E29*19/119,0) -> 0 | H29: =IF(F29="Débito",0.0275,IF(F29="Crédito",0.0295,0)) -> 0 | I29: =E29*H29 -> 0 | J29: =E29-G29-I29 -> 30000 | K29: =IF($O29<>"Tienda",0,IF(OR($F29="Débito",$F29="Crédito"),0.05,IF(OR($F29="Efectivo",$F29="Transferencia"),0.07,0))) -> 0 | L29: =IF($O29<>"Tienda",0,$J29*$K29) -> 0 | M29: =E29-G29-I29-L29 -> 30000 | N29: gelattos 10.000 | O29: Gelattos
A30: revista 20s 2 | B30: 0s | C30: Consignacion | D30: Marenna | E30: 20000 | F30: Transferencia | G30: =IF(OR(F30="Débito",F30="Crédito",F30="Internet(Shopify)"),E30*19/119,0) -> 0 | H30: =IF(F30="Débito",0.0275,IF(F30="Crédito",0.0295,0)) -> 0 | I30: =E30*H30 -> 0 | J30: =E30-G30-I30 -> 20000 | K30: =IF($O30<>"Tienda",0,IF(OR($F30="Débito",$F30="Crédito"),0.05,IF(OR($F30="Efectivo",$F30="Transferencia"),0.07,0))) -> 0.07 | L30: =IF($O30<>"Tienda",0,$J30*$K30) -> 1400 | M30: =E30-G30-I30-L30 -> 18600 | O30: Tienda
A31: camisa versace | B31: s | C31: Benja R | D31: Benja R | E31: 50000 | F31: Transferencia | G31: =IF(OR(F31="Débito",F31="Crédito",F31="Internet(Shopify)"),E31*19/119,0) -> 0 | H31: =IF(F31="Débito",0.0275,IF(F31="Crédito",0.0295,0)) -> 0 | I31: =E31*H31 -> 0 | J31: =E31-G31-I31 -> 50000 | K31: =IF($O31<>"Tienda",0,IF(OR($F31="Débito",$F31="Crédito"),0.05,IF(OR($F31="Efectivo",$F31="Transferencia"),0.07,0))) -> 0.07 | L31: =IF($O31<>"Tienda",0,$J31*$K31) -> 3500 | M31: =E31-G31-I31-L31 -> 46500 | O31: Tienda
A32: polera noah | B32: L | C32: Benja R | D32: Benja R | E32: 25000 | F32: Transferencia | G32: =IF(OR(F32="Débito",F32="Crédito",F32="Internet(Shopify)"),E32*19/119,0) -> 0 | H32: =IF(F32="Débito",0.0275,IF(F32="Crédito",0.0295,0)) -> 0 | I32: =E32*H32 -> 0 | J32: =E32-G32-I32 -> 25000 | K32: =IF($O32<>"Tienda",0,IF(OR($F32="Débito",$F32="Crédito"),0.05,IF(OR($F32="Efectivo",$F32="Transferencia"),0.07,0))) -> 0.07 | L32: =IF($O32<>"Tienda",0,$J32*$K32) -> 1750 | M32: =E32-G32-I32-L32 -> 23250 | N32: michelle | O32: Tienda
A33: vest margiela | B33: L | C33: Tienda | D33: Benja R | E33: 45000 | F33: Transferencia | G33: =IF(OR(F33="Débito",F33="Crédito",F33="Internet(Shopify)"),E33*19/119,0) -> 0 | H33: =IF(F33="Débito",0.0275,IF(F33="Crédito",0.0295,0)) -> 0 | I33: =E33*H33 -> 0 | J33: =E33-G33-I33 -> 45000 | K33: =IF($O33<>"Tienda",0,IF(OR($F33="Débito",$F33="Crédito"),0.05,IF(OR($F33="Efectivo",$F33="Transferencia"),0.07,0))) -> 0.07 | L33: =IF($O33<>"Tienda",0,$J33*$K33) -> 3150 | M33: =E33-G33-I33-L33 -> 41850 | O33: Tienda
A34: crewneck acne studios | B34: L | C34: Aaron | D34: Benja R | E34: 25000 | F34: Transferencia | G34: =IF(OR(F34="Débito",F34="Crédito",F34="Internet(Shopify)"),E34*19/119,0) -> 0 | H34: =IF(F34="Débito",0.0275,IF(F34="Crédito",0.0295,0)) -> 0 | I34: =E34*H34 -> 0 | J34: =E34-G34-I34 -> 25000 | K34: =IF($O34<>"Tienda",0,IF(OR($F34="Débito",$F34="Crédito"),0.05,IF(OR($F34="Efectivo",$F34="Transferencia"),0.07,0))) -> 0.07 | L34: =IF($O34<>"Tienda",0,$J34*$K34) -> 1750 | M34: =E34-G34-I34-L34 -> 23250 | O34: Tienda
A35: nike court | B35: S | G35: =IF(OR(F35="Débito",F35="Crédito",F35="Internet(Shopify)"),E35*19/119,0) -> 0 | H35: =IF(F35="Débito",0.0275,IF(F35="Crédito",0.0295,0)) -> 0 | I35: =E35*H35 -> 0 | J35: =E35-G35-I35 -> 0 | K35: =IF($O35<>"Tienda",0,IF(OR($F35="Débito",$F35="Crédito"),0.05,IF(OR($F35="Efectivo",$F35="Transferencia"),0.07,0))) -> 0 | L35: =IF($O35<>"Tienda",0,$J35*$K35) -> 0 | M35: =E35-G35-I35-L35 -> 0
A36: PANTALON JACK | B36: L | C36: Benja R | D36: Benja R | E36: 40800 | F36: Transferencia | G36: =IF(OR(F36="Débito",F36="Crédito",F36="Internet(Shopify)"),E36*19/119,0) -> 0 | H36: =IF(F36="Débito",0.0275,IF(F36="Crédito",0.0295,0)) -> 0 | I36: =E36*H36 -> 0 | J36: =E36-G36-I36 -> 40800 | K36: =IF($O36<>"Tienda",0,IF(OR($F36="Débito",$F36="Crédito"),0.05,IF(OR($F36="Efectivo",$F36="Transferencia"),0.07,0))) -> 0.07 | L36: =IF($O36<>"Tienda",0,$J36*$K36) -> 2856 | M36: =E36-G36-I36-L36 -> 37944 | O36: Tienda
A37: Polera Human Made | C37: Benja R | D37: Marenna | E37: 35000 | F37: Transferencia | G37: =IF(OR(F37="Débito",F37="Crédito",F37="Internet(Shopify)"),E37*19/119,0) -> 0 | H37: =IF(F37="Débito",0.0275,IF(F37="Crédito",0.0295,0)) -> 0 | I37: =E37*H37 -> 0 | J37: =E37-G37-I37 -> 35000 | K37: =IF($O37<>"Tienda",0,IF(OR($F37="Débito",$F37="Crédito"),0.05,IF(OR($F37="Efectivo",$F37="Transferencia"),0.07,0))) -> 0.07 | L37: =IF($O37<>"Tienda",0,$J37*$K37) -> 2450 | M37: =E37-G37-I37-L37 -> 32550 | O37: Tienda
A38: polera 4 fantasticos | B38: l | C38: Tienda | D38: Fabio | E38: 150000 | F38: Transferencia | G38: =IF(OR(F38="Débito",F38="Crédito",F38="Internet(Shopify)"),E38*19/119,0) -> 0 | H38: =IF(F38="Débito",0.0275,IF(F38="Crédito",0.0295,0)) -> 0 | I38: =E38*H38 -> 0 | J38: =E38-G38-I38 -> 150000 | K38: =IF($O38<>"Tienda",0,IF(OR($F38="Débito",$F38="Crédito"),0.05,IF(OR($F38="Efectivo",$F38="Transferencia"),0.07,0))) -> 0 | L38: =IF($O38<>"Tienda",0,$J38*$K38) -> 0 | M38: =E38-G38-I38-L38 -> 150000 | N38: gelatos 100.000 | O38: Gelattos
A39: poleron supreme | B39: L | C39: Aaron | D39: Benja R | E39: 70000 | F39: Transferencia | G39: =IF(OR(F39="Débito",F39="Crédito",F39="Internet(Shopify)"),E39*19/119,0) -> 0 | H39: =IF(F39="Débito",0.0275,IF(F39="Crédito",0.0295,0)) -> 0 | I39: =E39*H39 -> 0 | J39: =E39-G39-I39 -> 70000 | K39: =IF($O39<>"Tienda",0,IF(OR($F39="Débito",$F39="Crédito"),0.05,IF(OR($F39="Efectivo",$F39="Transferencia"),0.07,0))) -> 0.07 | L39: =IF($O39<>"Tienda",0,$J39*$K39) -> 4900 | M39: =E39-G39-I39-L39 -> 65100 | O39: Tienda
A40: pantalon guess | B40: 44 | C40: Fabio | D40: Benja R | E40: 25000 | F40: Transferencia | G40: =IF(OR(F40="Débito",F40="Crédito",F40="Internet(Shopify)"),E40*19/119,0) -> 0 | H40: =IF(F40="Débito",0.0275,IF(F40="Crédito",0.0295,0)) -> 0 | I40: =E40*H40 -> 0 | J40: =E40-G40-I40 -> 25000 | K40: =IF($O40<>"Tienda",0,IF(OR($F40="Débito",$F40="Crédito"),0.05,IF(OR($F40="Efectivo",$F40="Transferencia"),0.07,0))) -> 0.07 | L40: =IF($O40<>"Tienda",0,$J40*$K40) -> 1750 | M40: =E40-G40-I40-L40 -> 23250 | O40: Tienda
A41: PANTALÓN LEVIS | C41: Fabio | D41: Benja R | E41: 30000 | F41: Transferencia | G41: =IF(OR(F41="Débito",F41="Crédito",F41="Internet(Shopify)"),E41*19/119,0) -> 0 | H41: =IF(F41="Débito",0.0275,IF(F41="Crédito",0.0295,0)) -> 0 | I41: =E41*H41 -> 0 | J41: =E41-G41-I41 -> 30000 | K41: =IF($O41<>"Tienda",0,IF(OR($F41="Débito",$F41="Crédito"),0.05,IF(OR($F41="Efectivo",$F41="Transferencia"),0.07,0))) -> 0.07 | L41: =IF($O41<>"Tienda",0,$J41*$K41) -> 2100 | M41: =E41-G41-I41-L41 -> 27900 | O41: Tienda
A42: pulseras plata | B42: os | C42: Fabio | D42: Benja R | E42: 45000 | F42: Transferencia | G42: =IF(OR(F42="Débito",F42="Crédito",F42="Internet(Shopify)"),E42*19/119,0) -> 0 | H42: =IF(F42="Débito",0.0275,IF(F42="Crédito",0.0295,0)) -> 0 | I42: =E42*H42 -> 0 | J42: =E42-G42-I42 -> 45000 | K42: =IF($O42<>"Tienda",0,IF(OR($F42="Débito",$F42="Crédito"),0.05,IF(OR($F42="Efectivo",$F42="Transferencia"),0.07,0))) -> 0.07 | L42: =IF($O42<>"Tienda",0,$J42*$K42) -> 3150 | M42: =E42-G42-I42-L42 -> 41850 | N42: michelle | O42: Tienda
A43: camiseta livepool | B43: L | C43: Fabio | D43: Marenna | E43: 37000 | F43: Transferencia | G43: =IF(OR(F43="Débito",F43="Crédito",F43="Internet(Shopify)"),E43*19/119,0) -> 0 | H43: =IF(F43="Débito",0.0275,IF(F43="Crédito",0.0295,0)) -> 0 | I43: =E43*H43 -> 0 | J43: =E43-G43-I43 -> 37000 | K43: =IF($O43<>"Tienda",0,IF(OR($F43="Débito",$F43="Crédito"),0.05,IF(OR($F43="Efectivo",$F43="Transferencia"),0.07,0))) -> 0.07 | L43: =IF($O43<>"Tienda",0,$J43*$K43) -> 2590 | M43: =E43-G43-I43-L43 -> 34410 | O43: Tienda
A44: polera UNITY manga larga | B44: XL | C44: Tienda | D44: Marenna | E44: 35000 | F44: Transferencia | G44: =IF(OR(F44="Débito",F44="Crédito",F44="Internet(Shopify)"),E44*19/119,0) -> 0 | H44: =IF(F44="Débito",0.0275,IF(F44="Crédito",0.0295,0)) -> 0 | I44: =E44*H44 -> 0 | J44: =E44-G44-I44 -> 35000 | K44: =IF($O44<>"Tienda",0,IF(OR($F44="Débito",$F44="Crédito"),0.05,IF(OR($F44="Efectivo",$F44="Transferencia"),0.07,0))) -> 0.07 | L44: =IF($O44<>"Tienda",0,$J44*$K44) -> 2450 | M44: =E44-G44-I44-L44 -> 32550 | O44: Tienda
A45: Lentes Armani | C45: Benja R | D45: Marenna | E45: 45000 | F45: Transferencia | G45: =IF(OR(F45="Débito",F45="Crédito",F45="Internet(Shopify)"),E45*19/119,0) -> 0 | H45: =IF(F45="Débito",0.0275,IF(F45="Crédito",0.0295,0)) -> 0 | I45: =E45*H45 -> 0 | J45: =E45-G45-I45 -> 45000 | K45: =IF($O45<>"Tienda",0,IF(OR($F45="Débito",$F45="Crédito"),0.05,IF(OR($F45="Efectivo",$F45="Transferencia"),0.07,0))) -> 0.07 | L45: =IF($O45<>"Tienda",0,$J45*$K45) -> 3150 | M45: =E45-G45-I45-L45 -> 41850 | O45: Tienda
A46: polera bape | B46: L | C46: Benja R | D46: Benja R | E46: 40000 | F46: Transferencia | G46: =IF(OR(F46="Débito",F46="Crédito",F46="Internet(Shopify)"),E46*19/119,0) -> 0 | H46: =IF(F46="Débito",0.0275,IF(F46="Crédito",0.0295,0)) -> 0 | I46: =E46*H46 -> 0 | J46: =E46-G46-I46 -> 40000 | K46: =IF($O46<>"Tienda",0,IF(OR($F46="Débito",$F46="Crédito"),0.05,IF(OR($F46="Efectivo",$F46="Transferencia"),0.07,0))) -> 0.07 | L46: =IF($O46<>"Tienda",0,$J46*$K46) -> 2800 | M46: =E46-G46-I46-L46 -> 37200 | N46: michelle | O46: Tienda
A47: polera yeezus | B47: L | C47: Aaron | D47: Benja R | E47: 40000 | F47: Transferencia | G47: =IF(OR(F47="Débito",F47="Crédito",F47="Internet(Shopify)"),E47*19/119,0) -> 0 | H47: =IF(F47="Débito",0.0275,IF(F47="Crédito",0.0295,0)) -> 0 | I47: =E47*H47 -> 0 | J47: =E47-G47-I47 -> 40000 | K47: =IF($O47<>"Tienda",0,IF(OR($F47="Débito",$F47="Crédito"),0.05,IF(OR($F47="Efectivo",$F47="Transferencia"),0.07,0))) -> 0.07 | L47: =IF($O47<>"Tienda",0,$J47*$K47) -> 2800 | M47: =E47-G47-I47-L47 -> 37200 | N47: michelle | O47: Tienda
A48: polera LèSang | C48: Tienda | D48: Benja R | E48: 20000 | F48: Transferencia | G48: =IF(OR(F48="Débito",F48="Crédito",F48="Internet(Shopify)"),E48*19/119,0) -> 0 | H48: =IF(F48="Débito",0.0275,IF(F48="Crédito",0.0295,0)) -> 0 | I48: =E48*H48 -> 0 | J48: =E48-G48-I48 -> 20000 | K48: =IF($O48<>"Tienda",0,IF(OR($F48="Débito",$F48="Crédito"),0.05,IF(OR($F48="Efectivo",$F48="Transferencia"),0.07,0))) -> 0 | L48: =IF($O48<>"Tienda",0,$J48*$K48) -> 0 | M48: =E48-G48-I48-L48 -> 20000 | N48: michelle
A49: polera prada | B49: L | C49: Benja R | D49: Benja R | E49: 70000 | F49: Transferencia | G49: =IF(OR(F49="Débito",F49="Crédito",F49="Internet(Shopify)"),E49*19/119,0) -> 0 | H49: =IF(F49="Débito",0.0275,IF(F49="Crédito",0.0295,0)) -> 0 | I49: =E49*H49 -> 0 | J49: =E49-G49-I49 -> 70000 | K49: =IF($O49<>"Tienda",0,IF(OR($F49="Débito",$F49="Crédito"),0.05,IF(OR($F49="Efectivo",$F49="Transferencia"),0.07,0))) -> 0.07 | L49: =IF($O49<>"Tienda",0,$J49*$K49) -> 4900 | M49: =E49-G49-I49-L49 -> 65100 | N49: michelle | O49: Tienda
A50: Pulseras Fabio | B50: os | C50: Fabio | D50: Benja R | E50: 15000 | F50: Transferencia | G50: =IF(OR(F50="Débito",F50="Crédito",F50="Internet(Shopify)"),E50*19/119,0) -> 0 | H50: =IF(F50="Débito",0.0275,IF(F50="Crédito",0.0295,0)) -> 0 | I50: =E50*H50 -> 0 | J50: =E50-G50-I50 -> 15000 | K50: =IF($O50<>"Tienda",0,IF(OR($F50="Débito",$F50="Crédito"),0.05,IF(OR($F50="Efectivo",$F50="Transferencia"),0.07,0))) -> 0.07 | L50: =IF($O50<>"Tienda",0,$J50*$K50) -> 1050 | M50: =E50-G50-I50-L50 -> 13950 | N50: michelle | O50: Tienda
A51: polera prada | B51: L | C51: Benja R | G51: =IF(OR(F51="Débito",F51="Crédito",F51="Internet(Shopify)"),E51*19/119,0) -> 0 | H51: =IF(F51="Débito",0.0275,IF(F51="Crédito",0.0295,0)) -> 0 | I51: =E51*H51 -> 0 | J51: =E51-G51-I51 -> 0 | K51: =IF($O51<>"Tienda",0,IF(OR($F51="Débito",$F51="Crédito"),0.05,IF(OR($F51="Efectivo",$F51="Transferencia"),0.07,0))) -> 0 | L51: =IF($O51<>"Tienda",0,$J51*$K51) -> 0 | M51: =E51-G51-I51-L51 -> 0
A52: Chaqueta Moschino | B52: L | C52: Consignacion | D52: Fabio | E52: 220000 | F52: Transferencia | G52: =IF(OR(F52="Débito",F52="Crédito",F52="Internet(Shopify)"),E52*19/119,0) -> 0 | H52: =IF(F52="Débito",0.0275,IF(F52="Crédito",0.0295,0)) -> 0 | I52: =E52*H52 -> 0 | J52: =E52-G52-I52 -> 220000 | K52: =IF($O52<>"Tienda",0,IF(OR($F52="Débito",$F52="Crédito"),0.05,IF(OR($F52="Efectivo",$F52="Transferencia"),0.07,0))) -> 0.07 | L52: =IF($O52<>"Tienda",0,$J52*$K52) -> 15400 | M52: =E52-G52-I52-L52 -> 204600 | N52: 200.000 para Federico (aun abierto) | O52: Tienda
A53: Polera Vintage | B53: L | C53: Consignacion | D53: Fabio | E53: 110000 | F53: Transferencia | G53: =IF(OR(F53="Débito",F53="Crédito",F53="Internet(Shopify)"),E53*19/119,0) -> 0 | H53: =IF(F53="Débito",0.0275,IF(F53="Crédito",0.0295,0)) -> 0 | I53: =E53*H53 -> 0 | J53: =E53-G53-I53 -> 110000 | K53: =IF($O53<>"Tienda",0,IF(OR($F53="Débito",$F53="Crédito"),0.05,IF(OR($F53="Efectivo",$F53="Transferencia"),0.07,0))) -> 0 | L53: =IF($O53<>"Tienda",0,$J53*$K53) -> 0 | M53: =E53-G53-I53-L53 -> 110000 | N53: 80.000 Gelatto | O53: Gelattos
A54: Polera Valentino | B54: M | C54: Benja R | D54: Fabio | E54: 40000 | F54: Transferencia | G54: =IF(OR(F54="Débito",F54="Crédito",F54="Internet(Shopify)"),E54*19/119,0) -> 0 | H54: =IF(F54="Débito",0.0275,IF(F54="Crédito",0.0295,0)) -> 0 | I54: =E54*H54 -> 0 | J54: =E54-G54-I54 -> 40000 | K54: =IF($O54<>"Tienda",0,IF(OR($F54="Débito",$F54="Crédito"),0.05,IF(OR($F54="Efectivo",$F54="Transferencia"),0.07,0))) -> 0.07 | L54: =IF($O54<>"Tienda",0,$J54*$K54) -> 2800 | M54: =E54-G54-I54-L54 -> 37200 | O54: Tienda
A55: y3 polera | B55: s | C55: Aaron | D55: Benja R | E55: 35000 | F55: Transferencia | G55: =IF(OR(F55="Débito",F55="Crédito",F55="Internet(Shopify)"),E55*19/119,0) -> 0 | H55: =IF(F55="Débito",0.0275,IF(F55="Crédito",0.0295,0)) -> 0 | I55: =E55*H55 -> 0 | J55: =E55-G55-I55 -> 35000 | K55: =IF($O55<>"Tienda",0,IF(OR($F55="Débito",$F55="Crédito"),0.05,IF(OR($F55="Efectivo",$F55="Transferencia"),0.07,0))) -> 0.07 | L55: =IF($O55<>"Tienda",0,$J55*$K55) -> 2450 | M55: =E55-G55-I55-L55 -> 32550 | O55: Tienda
A56: Polera BBC | B56: XXL | C56: Fabio | D56: Fabio | E56: 25000 | F56: Efectivo | G56: =IF(OR(F56="Débito",F56="Crédito",F56="Internet(Shopify)"),E56*19/119,0) -> 0 | H56: =IF(F56="Débito",0.0275,IF(F56="Crédito",0.0295,0)) -> 0 | I56: =E56*H56 -> 0 | J56: =E56-G56-I56 -> 25000 | K56: =IF($O56<>"Tienda",0,IF(OR($F56="Débito",$F56="Crédito"),0.05,IF(OR($F56="Efectivo",$F56="Transferencia"),0.07,0))) -> 0.07 | L56: =IF($O56<>"Tienda",0,$J56*$K56) -> 1750 | M56: =E56-G56-I56-L56 -> 23250 | O56: Tienda
A57: Camisa Bape Cuadrille | B57: M | C57: Tienda | D57: Aaron | E57: 50000 | F57: Transferencia | G57: =IF(OR(F57="Débito",F57="Crédito",F57="Internet(Shopify)"),E57*19/119,0) -> 0 | H57: =IF(F57="Débito",0.0275,IF(F57="Crédito",0.0295,0)) -> 0 | I57: =E57*H57 -> 0 | J57: =E57-G57-I57 -> 50000 | K57: =IF($O57<>"Tienda",0,IF(OR($F57="Débito",$F57="Crédito"),0.05,IF(OR($F57="Efectivo",$F57="Transferencia"),0.07,0))) -> 0.07 | L57: =IF($O57<>"Tienda",0,$J57*$K57) -> 3500 | M57: =E57-G57-I57-L57 -> 46500 | O57: Tienda
A58: Polera D&G | B58: M | C58: Benja R | D58: Fabio | E58: 35000 | F58: Débito | G58: =IF(OR(F58="Débito",F58="Crédito",F58="Internet(Shopify)"),E58*19/119,0) -> 5588.2353 | H58: =IF(F58="Débito",0.0275,IF(F58="Crédito",0.0295,0)) -> 0.0275 | I58: =E58*H58 -> 962.5 | J58: =E58-G58-I58 -> 28449.265 | K58: =IF($O58<>"Tienda",0,IF(OR($F58="Débito",$F58="Crédito"),0.05,IF(OR($F58="Efectivo",$F58="Transferencia"),0.07,0))) -> 0.05 | L58: =IF($O58<>"Tienda",0,$J58*$K58) -> 1422.4632 | M58: =E58-G58-I58-L58 -> 27026.801 | O58: Tienda
A59: Polera LÈSANG | B59: S | C59: Tienda | D59: Fabio | E59: 20000 | F59: Débito | G59: =IF(OR(F59="Débito",F59="Crédito",F59="Internet(Shopify)"),E59*19/119,0) -> 3193.2773 | H59: =IF(F59="Débito",0.0275,IF(F59="Crédito",0.0295,0)) -> 0.0275 | I59: =E59*H59 -> 550 | J59: =E59-G59-I59 -> 16256.723 | K59: =IF($O59<>"Tienda",0,IF(OR($F59="Débito",$F59="Crédito"),0.05,IF(OR($F59="Efectivo",$F59="Transferencia"),0.07,0))) -> 0.05 | L59: =IF($O59<>"Tienda",0,$J59*$K59) -> 812.83613 | M59: =E59-G59-I59-L59 -> 15443.887 | O59: Tienda
A60: PANTALON G STAR | B60: 44 | C60: Benja R | D60: Benja R | E60: 50000 | F60: Efectivo | G60: =IF(OR(F60="Débito",F60="Crédito",F60="Internet(Shopify)"),E60*19/119,0) -> 0 | H60: =IF(F60="Débito",0.0275,IF(F60="Crédito",0.0295,0)) -> 0 | I60: =E60*H60 -> 0 | J60: =E60-G60-I60 -> 50000 | K60: =IF($O60<>"Tienda",0,IF(OR($F60="Débito",$F60="Crédito"),0.05,IF(OR($F60="Efectivo",$F60="Transferencia"),0.07,0))) -> 0.07 | L60: =IF($O60<>"Tienda",0,$J60*$K60) -> 3500 | M60: =E60-G60-I60-L60 -> 46500 | O60: Tienda
A61: Polera LÉSANG | B61: S | C61: Tienda | D61: Benja R | E61: 20000 | F61: Transferencia | G61: =IF(OR(F61="Débito",F61="Crédito",F61="Internet(Shopify)"),E61*19/119,0) -> 0 | H61: =IF(F61="Débito",0.0275,IF(F61="Crédito",0.0295,0)) -> 0 | I61: =E61*H61 -> 0 | J61: =E61-G61-I61 -> 20000 | K61: =IF($O61<>"Tienda",0,IF(OR($F61="Débito",$F61="Crédito"),0.05,IF(OR($F61="Efectivo",$F61="Transferencia"),0.07,0))) -> 0.07 | L61: =IF($O61<>"Tienda",0,$J61*$K61) -> 1400 | M61: =E61-G61-I61-L61 -> 18600 | N61: MICHELLE | O61: Tienda
A62: POLERA MONCLER | C62: Benja R | D62: Fabio | E62: 40000 | F62: Transferencia | G62: =IF(OR(F62="Débito",F62="Crédito",F62="Internet(Shopify)"),E62*19/119,0) -> 0 | H62: =IF(F62="Débito",0.0275,IF(F62="Crédito",0.0295,0)) -> 0 | I62: =E62*H62 -> 0 | J62: =E62-G62-I62 -> 40000 | K62: =IF($O62<>"Tienda",0,IF(OR($F62="Débito",$F62="Crédito"),0.05,IF(OR($F62="Efectivo",$F62="Transferencia"),0.07,0))) -> 0 | L62: =IF($O62<>"Tienda",0,$J62*$K62) -> 0 | M62: =E62-G62-I62-L62 -> 40000 | N62: FABIO Y BENJA R
A63: MONCLER PARKA | B63: S-M | C63: Aaron | D63: Fabio | E63: 0 | F63: Efectivo | G63: =IF(OR(F63="Débito",F63="Crédito",F63="Internet(Shopify)"),E63*19/119,0) -> 0 | H63: =IF(F63="Débito",0.0275,IF(F63="Crédito",0.0295,0)) -> 0 | I63: =E63*H63 -> 0 | J63: =E63-G63-I63 -> 0 | K63: =IF($O63<>"Tienda",0,IF(OR($F63="Débito",$F63="Crédito"),0.05,IF(OR($F63="Efectivo",$F63="Transferencia"),0.07,0))) -> 0.07 | L63: =IF($O63<>"Tienda",0,$J63*$K63) -> 0 | M63: =E63-G63-I63-L63 -> 0 | O63: Tienda
A64: POLERA LESANG | B64: S | C64: Tienda | D64: Benja R | E64: 20000 | F64: Transferencia | G64: =IF(OR(F64="Débito",F64="Crédito",F64="Internet(Shopify)"),E64*19/119,0) -> 0 | H64: =IF(F64="Débito",0.0275,IF(F64="Crédito",0.0295,0)) -> 0 | I64: =E64*H64 -> 0 | J64: =E64-G64-I64 -> 20000 | K64: =IF($O64<>"Tienda",0,IF(OR($F64="Débito",$F64="Crédito"),0.05,IF(OR($F64="Efectivo",$F64="Transferencia"),0.07,0))) -> 0.07 | L64: =IF($O64<>"Tienda",0,$J64*$K64) -> 1400 | M64: =E64-G64-I64-L64 -> 18600 | N64: michelle | O64: Tienda
A65: PANTALONES PEDRITOS JEANS | B65: UN | C65: Tienda | D65: Benja R | E65: 70000 | F65: Transferencia | G65: =IF(OR(F65="Débito",F65="Crédito",F65="Internet(Shopify)"),E65*19/119,0) -> 0 | H65: =IF(F65="Débito",0.0275,IF(F65="Crédito",0.0295,0)) -> 0 | I65: =E65*H65 -> 0 | J65: =E65-G65-I65 -> 70000 | K65: =IF($O65<>"Tienda",0,IF(OR($F65="Débito",$F65="Crédito"),0.05,IF(OR($F65="Efectivo",$F65="Transferencia"),0.07,0))) -> 0 | L65: =IF($O65<>"Tienda",0,$J65*$K65) -> 0 | M65: =E65-G65-I65-L65 -> 70000 | N65: MICHELLE/PEDRITOS (52.500) | O65: Pedritos
A66: POLERA POP DISASTER IDIOT | B66: S | C66: Tienda | D66: Benja R | E66: 25000 | F66: Transferencia | G66: =IF(OR(F66="Débito",F66="Crédito",F66="Internet(Shopify)"),E66*19/119,0) -> 0 | H66: =IF(F66="Débito",0.0275,IF(F66="Crédito",0.0295,0)) -> 0 | I66: =E66*H66 -> 0 | J66: =E66-G66-I66 -> 25000 | K66: =IF($O66<>"Tienda",0,IF(OR($F66="Débito",$F66="Crédito"),0.05,IF(OR($F66="Efectivo",$F66="Transferencia"),0.07,0))) -> 0 | L66: =IF($O66<>"Tienda",0,$J66*$K66) -> 0 | M66: =E66-G66-I66-L66 -> 25000 | N66: MICHELLE/ POPD (18.750) | O66: Pop disaster
G67: =IF(OR(F67="Débito",F67="Crédito",F67="Internet(Shopify)"),E67*19/119,0) -> 0 | H67: =IF(F67="Débito",0.0275,IF(F67="Crédito",0.0295,0)) -> 0 | I67: =E67*H67 -> 0 | J67: =E67-G67-I67 -> 0 | K67: =IF($O67<>"Tienda",0,IF(OR($F67="Débito",$F67="Crédito"),0.05,IF(OR($F67="Efectivo",$F67="Transferencia"),0.07,0))) -> 0 | L67: =IF($O67<>"Tienda",0,$J67*$K67) -> 0 | M67: =E67-G67-I67-L67 -> 0
G68: =IF(OR(F68="Débito",F68="Crédito",F68="Internet(Shopify)"),E68*19/119,0) -> 0 | H68: =IF(F68="Débito",0.0275,IF(F68="Crédito",0.0295,0)) -> 0 | I68: =E68*H68 -> 0 | J68: =E68-G68-I68 -> 0 | K68: =IF($O68<>"Tienda",0,IF(OR($F68="Débito",$F68="Crédito"),0.05,IF(OR($F68="Efectivo",$F68="Transferencia"),0.07,0))) -> 0 | L68: =IF($O68<>"Tienda",0,$J68*$K68) -> 0 | M68: =E68-G68-I68-L68 -> 0
G69: =IF(OR(F69="Débito",F69="Crédito",F69="Internet(Shopify)"),E69*19/119,0) -> 0 | H69: =IF(F69="Débito",0.0275,IF(F69="Crédito",0.0295,0)) -> 0 | I69: =E69*H69 -> 0 | J69: =E69-G69-I69 -> 0 | K69: =IF($O69<>"Tienda",0,IF(OR($F69="Débito",$F69="Crédito"),0.05,IF(OR($F69="Efectivo",$F69="Transferencia"),0.07,0))) -> 0 | L69: =IF($O69<>"Tienda",0,$J69*$K69) -> 0 | M69: =E69-G69-I69-L69 -> 0
G70: =IF(OR(F70="Débito",F70="Crédito",F70="Internet(Shopify)"),E70*19/119,0) -> 0 | H70: =IF(F70="Débito",0.0275,IF(F70="Crédito",0.0295,0)) -> 0 | I70: =E70*H70 -> 0 | J70: =E70-G70-I70 -> 0 | K70: =IF($O70<>"Tienda",0,IF(OR($F70="Débito",$F70="Crédito"),0.05,IF(OR($F70="Efectivo",$F70="Transferencia"),0.07,0))) -> 0 | L70: =IF($O70<>"Tienda",0,$J70*$K70) -> 0 | M70: =E70-G70-I70-L70 -> 0
G71: =IF(OR(F71="Débito",F71="Crédito",F71="Internet(Shopify)"),E71*19/119,0) -> 0 | H71: =IF(F71="Débito",0.0275,IF(F71="Crédito",0.0295,0)) -> 0 | I71: =E71*H71 -> 0 | J71: =E71-G71-I71 -> 0 | K71: =IF($O71<>"Tienda",0,IF(OR($F71="Débito",$F71="Crédito"),0.05,IF(OR($F71="Efectivo",$F71="Transferencia"),0.07,0))) -> 0 | L71: =IF($O71<>"Tienda",0,$J71*$K71) -> 0 | M71: =E71-G71-I71-L71 -> 0
G72: =IF(OR(F72="Débito",F72="Crédito",F72="Internet(Shopify)"),E72*19/119,0) -> 0 | H72: =IF(F72="Débito",0.0275,IF(F72="Crédito",0.0295,0)) -> 0 | I72: =E72*H72 -> 0 | J72: =E72-G72-I72 -> 0 | K72: =IF($O72<>"Tienda",0,IF(OR($F72="Débito",$F72="Crédito"),0.05,IF(OR($F72="Efectivo",$F72="Transferencia"),0.07,0))) -> 0 | L72: =IF($O72<>"Tienda",0,$J72*$K72) -> 0 | M72: =E72-G72-I72-L72 -> 0
G73: =IF(OR(F73="Débito",F73="Crédito",F73="Internet(Shopify)"),E73*19/119,0) -> 0 | H73: =IF(F73="Débito",0.0275,IF(F73="Crédito",0.0295,0)) -> 0 | I73: =E73*H73 -> 0 | J73: =E73-G73-I73 -> 0 | K73: =IF($O73<>"Tienda",0,IF(OR($F73="Débito",$F73="Crédito"),0.05,IF(OR($F73="Efectivo",$F73="Transferencia"),0.07,0))) -> 0 | L73: =IF($O73<>"Tienda",0,$J73*$K73) -> 0 | M73: =E73-G73-I73-L73 -> 0
G74: =IF(OR(F74="Débito",F74="Crédito",F74="Internet(Shopify)"),E74*19/119,0) -> 0 | H74: =IF(F74="Débito",0.0275,IF(F74="Crédito",0.0295,0)) -> 0 | I74: =E74*H74 -> 0 | J74: =E74-G74-I74 -> 0 | K74: =IF($O74<>"Tienda",0,IF(OR($F74="Débito",$F74="Crédito"),0.05,IF(OR($F74="Efectivo",$F74="Transferencia"),0.07,0))) -> 0 | L74: =IF($O74<>"Tienda",0,$J74*$K74) -> 0 | M74: =E74-G74-I74-L74 -> 0
G75: =IF(OR(F75="Débito",F75="Crédito",F75="Internet(Shopify)"),E75*19/119,0) -> 0 | H75: =IF(F75="Débito",0.0275,IF(F75="Crédito",0.0295,0)) -> 0 | I75: =E75*H75 -> 0 | J75: =E75-G75-I75 -> 0 | K75: =IF($O75<>"Tienda",0,IF(OR($F75="Débito",$F75="Crédito"),0.05,IF(OR($F75="Efectivo",$F75="Transferencia"),0.07,0))) -> 0 | L75: =IF($O75<>"Tienda",0,$J75*$K75) -> 0 | M75: =E75-G75-I75-L75 -> 0
G76: =IF(OR(F76="Débito",F76="Crédito",F76="Internet(Shopify)"),E76*19/119,0) -> 0 | H76: =IF(F76="Débito",0.0275,IF(F76="Crédito",0.0295,0)) -> 0 | I76: =E76*H76 -> 0 | J76: =E76-G76-I76 -> 0 | K76: =IF($O76<>"Tienda",0,IF(OR($F76="Débito",$F76="Crédito"),0.05,IF(OR($F76="Efectivo",$F76="Transferencia"),0.07,0))) -> 0 | L76: =IF($O76<>"Tienda",0,$J76*$K76) -> 0 | M76: =E76-G76-I76-L76 -> 0
G77: =IF(OR(F77="Débito",F77="Crédito",F77="Internet(Shopify)"),E77*19/119,0) -> 0 | H77: =IF(F77="Débito",0.0275,IF(F77="Crédito",0.0295,0)) -> 0 | I77: =E77*H77 -> 0 | J77: =E77-G77-I77 -> 0 | K77: =IF($O77<>"Tienda",0,IF(OR($F77="Débito",$F77="Crédito"),0.05,IF(OR($F77="Efectivo",$F77="Transferencia"),0.07,0))) -> 0 | L77: =IF($O77<>"Tienda",0,$J77*$K77) -> 0 | M77: =E77-G77-I77-L77 -> 0
G78: =IF(OR(F78="Débito",F78="Crédito",F78="Internet(Shopify)"),E78*19/119,0) -> 0 | H78: =IF(F78="Débito",0.0275,IF(F78="Crédito",0.0295,0)) -> 0 | I78: =E78*H78 -> 0 | J78: =E78-G78-I78 -> 0 | K78: =IF($O78<>"Tienda",0,IF(OR($F78="Débito",$F78="Crédito"),0.05,IF(OR($F78="Efectivo",$F78="Transferencia"),0.07,0))) -> 0 | L78: =IF($O78<>"Tienda",0,$J78*$K78) -> 0 | M78: =E78-G78-I78-L78 -> 0
... G103: =IF(OR(F103="Débito",F103="Crédito",F103="Internet(Shopify)"),E103*19/119,0) -> 0 | H103: =IF(F103="Débito",0.0275,IF(F103="Crédito",0.0295,0)) -> 0 | I103: =E103*H103 -> 0 | J103: =E103-G103-I103 -> 0 | K103: =IF($O103<>"Tienda",0,IF(OR($F103="Débito",$F103="Crédito"),0.05,IF(OR($F103="Efectivo",$F103="Transferencia"),0.07,0))) -> 0 | L103: =IF($O103<>"Tienda",0,$J103*$K103) -> 0 | M103: =E103-G103-I103-L103 -> 0
A108: Febrero - Gastos Fijos | G108: Febrero - Gastos Extra
A109: Nombre gasto | B109: Monto (CLP) | C109: Notas | G109: Nombre gasto | H109: Monto (CLP) | I109: Fecha | J109: Notas
A110: Arriendo (CLP calculado con UF) | B110: =Parametros!$B$1*Parametros!$B$2 -> 1463000
A111: Gastos comunes | B111: 70000
A112: ADT | B112: 69000
A113: Internet | B113: 39960
A114: Luz (promedio) | B114: 35000
A115: Agua (promedio) | B115: 25000
A116: Shopify | B116: 50000
A130: Total gastos fijos | B130: =SUM(B110:B129) -> 1751960 | G130: Total gastos extra | H130: =SUM(H110:H129) -> 0
A131: Gasto fijo por integrante (÷5) | B131: =B130/5 -> 350392

Sheet Marzo
P2: Total ventas brutas | Q2: =SUM(E4:E103) -> 9525000
A3: Nombre prenda | B3: Talla | C3: Propietario prenda | D3: Vendedor | E3: Precio venta (BRUTO) | F3: Tipo de pago | G3: IVA (19%) | H3: % comisión bancaria | I3: $ comisión bancaria | J3: Base comisión vendedor | K3: % comisión vendedor | L3: $ comisión vendedor | M3: Neto tienda | N3: Observaciones | O3: Marca (Tienda/externa) | P3: Total IVA ventas | Q3: =SUM(G4:G103) -> 26344.538
A4: pulsera plata | B4: os | C4: Fabio | D4: Benja R | E4: 25000 | F4: Efectivo | G4: =IF(OR(F4="Débito",F4="Crédito",F4="Internet(Shopify)"),E4*19/119,0) -> 0 | H4: =IF(F4="Débito",0.0275,IF(F4="Crédito",0.0295,0)) -> 0 | I4: =E4*H4 -> 0 | J4: =E4-G4-I4 -> 25000 | K4: =IF($O4<>"Tienda",0,IF(OR($F4="Débito",$F4="Crédito"),0.05,IF(OR($F4="Efectivo",$F4="Transferencia"),0.07,0))) -> 0 | L4: =IF($O4<>"Tienda",0,$J4*$K4) -> 0 | M4: =E4-G4-I4-L4 -> 25000 | O4: Pedritos | P4: Total comisiones bancarias | Q4: =SUM(I4:I103) -> 4537.5
A5: polera pedritos ken kagami | B5: S | C5: Tienda | D5: Benja R | E5: 35000 | F5: Transferencia | G5: =IF(OR(F5="Débito",F5="Crédito",F5="Internet(Shopify)"),E5*19/119,0) -> 0 | H5: =IF(F5="Débito",0.0275,IF(F5="Crédito",0.0295,0)) -> 0 | I5: =E5*H5 -> 0 | J5: =E5-G5-I5 -> 35000 | K5: =IF($O5<>"Tienda",0,IF(OR($F5="Débito",$F5="Crédito"),0.05,IF(OR($F5="Efectivo",$F5="Transferencia"),0.07,0))) -> 0.07 | L5: =IF($O5<>"Tienda",0,$J5*$K5) -> 2450 | M5: =E5-G5-I5-L5 -> 32550 | N5: pedritos (26.250) | O5: Tienda | P5: Total comisiones vendedores (NO se divide) | Q5: =SUM(L4:L103) -> 537305.9
A6: supreme moai manga larga | B6: L | C6: Aaron | D6: Benja R | E6: 35000 | F6: Transferencia | G6: =IF(OR(F6="Débito",F6="Crédito",F6="Internet(Shopify)"),E6*19/119,0) -> 0 | H6: =IF(F6="Débito",0.0275,IF(F6="Crédito",0.0295,0)) -> 0 | I6: =E6*H6 -> 0 | J6: =E6-G6-I6 -> 35000 | K6: =IF($O6<>"Tienda",0,IF(OR($F6="Débito",$F6="Crédito"),0.05,IF(OR($F6="Efectivo",$F6="Transferencia"),0.07,0))) -> 0.07 | L6: =IF($O6<>"Tienda",0,$J6*$K6) -> 2450 | M6: =E6-G6-I6-L6 -> 32550 | O6: Tienda | P6: Total neto tienda (NO se divide) | Q6: =SUM(M4:M103) -> 8911812.1
A7: Lentes GUCCI | C7: Benja R | D7: Benja R | E7: 80000 | F7: Transferencia | G7: =IF(OR(F7="Débito",F7="Crédito",F7="Internet(Shopify)"),E7*19/119,0) -> 0 | H7: =IF(F7="Débito",0.0275,IF(F7="Crédito",0.0295,0)) -> 0 | I7: =E7*H7 -> 0 | J7: =E7-G7-I7 -> 80000 | K7: =IF($O7<>"Tienda",0,IF(OR($F7="Débito",$F7="Crédito"),0.05,IF(OR($F7="Efectivo",$F7="Transferencia"),0.07,0))) -> 0.07 | L7: =IF($O7<>"Tienda",0,$J7*$K7) -> 5600 | M7: =E7-G7-I7-L7 -> 74400 | N7: MICHELLE | O7: Tienda | P7: Número de ventas | Q7: =COUNTA(E4:E103) -> 92
A8: bufanda pop disaster | B8: os | C8: Tienda | D8: Benja R | E8: 15000 | F8: Transferencia | G8: =IF(OR(F8="Débito",F8="Crédito",F8="Internet(Shopify)"),E8*19/119,0) -> 0 | H8: =IF(F8="Débito",0.0275,IF(F8="Crédito",0.0295,0)) -> 0 | I8: =E8*H8 -> 0 | J8: =E8-G8-I8 -> 15000 | K8: =IF($O8<>"Tienda",0,IF(OR($F8="Débito",$F8="Crédito"),0.05,IF(OR($F8="Efectivo",$F8="Transferencia"),0.07,0))) -> 0 | L8: =IF($O8<>"Tienda",0,$J8*$K8) -> 0 | M8: =E8-G8-I8-L8 -> 15000 | N8: Pop disaster (11.250) | O8: Pop disaster | P8: Ticket promedio (NETO) | Q8: =IF(Q7=0,0,Q6/Q7) -> 96867.522
A9: polera le sang | B9: s | C9: Tienda | D9: Benja R | E9: 20000 | F9: Transferencia | G9: =IF(OR(F9="Débito",F9="Crédito",F9="Internet(Shopify)"),E9*19/119,0) -> 0 | H9: =IF(F9="Débito",0.0275,IF(F9="Crédito",0.0295,0)) -> 0 | I9: =E9*H9 -> 0 | J9: =E9-G9-I9 -> 20000 | K9: =IF($O9<>"Tienda",0,IF(OR($F9="Débito",$F9="Crédito"),0.05,IF(OR($F9="Efectivo",$F9="Transferencia"),0.07,0))) -> 0.07 | L9: =IF($O9<>"Tienda",0,$J9*$K9) -> 1400 | M9: =E9-G9-I9-L9 -> 18600 | O9: Tienda | P9: Ventas débito (neto) | Q9: =SUMIF(F4:F103,"Débito",M4:M103) -> 127412.06
A10: polera pop disaster | B10: M youth | C10: Tienda | D10: Benja R | E10: 25000 | F10: Transferencia | G10: =IF(OR(F10="Débito",F10="Crédito",F10="Internet(Shopify)"),E10*19/119,0) -> 0 | H10: =IF(F10="Débito",0.0275,IF(F10="Crédito",0.0295,0)) -> 0 | I10: =E10*H10 -> 0 | J10: =E10-G10-I10 -> 25000 | K10: =IF($O10<>"Tienda",0,IF(OR($F10="Débito",$F10="Crédito"),0.05,IF(OR($F10="Efectivo",$F10="Transferencia"),0.07,0))) -> 0 | L10: =IF($O10<>"Tienda",0,$J10*$K10) -> 0 | M10: =E10-G10-I10-L10 -> 25000 | N10: pop disaster (18.750) | O10: Pop disaster | P10: Ventas crédito (neto) | Q10: =SUMIF(F4:F103,"Crédito",M4:M103) -> 0
A11: collar vivienne | B11: OS | C11: Tienda | D11: Benja R | E11: 200000 | F11: Transferencia | G11: =IF(OR(F11="Débito",F11="Crédito",F11="Internet(Shopify)"),E11*19/119,0) -> 0 | H11: =IF(F11="Débito",0.0275,IF(F11="Crédito",0.0295,0)) -> 0 | I11: =E11*H11 -> 0 | J11: =E11-G11-I11 -> 200000 | K11: =IF($O11<>"Tienda",0,IF(OR($F11="Débito",$F11="Crédito"),0.05,IF(OR($F11="Efectivo",$F11="Transferencia"),0.07,0))) -> 0.07 | L11: =IF($O11<>"Tienda",0,$J11*$K11) -> 14000 | M11: =E11-G11-I11-L11 -> 186000 | O11: Tienda | P11: Ventas efectivo (neto) | Q11: =SUMIF(F4:F103,"Efectivo",M4:M103) -> 45000
A12: camiseta colo colo | B12: L | C12: Fabio | D12: Benja R | E12: 32000 | F12: Transferencia | G12: =IF(OR(F12="Débito",F12="Crédito",F12="Internet(Shopify)"),E12*19/119,0) -> 0 | H12: =IF(F12="Débito",0.0275,IF(F12="Crédito",0.0295,0)) -> 0 | I12: =E12*H12 -> 0 | J12: =E12-G12-I12 -> 32000 | K12: =IF($O12<>"Tienda",0,IF(OR($F12="Débito",$F12="Crédito"),0.05,IF(OR($F12="Efectivo",$F12="Transferencia"),0.07,0))) -> 0.07 | L12: =IF($O12<>"Tienda",0,$J12*$K12) -> 2240 | M12: =E12-G12-I12-L12 -> 29760 | O12: Tienda | P12: Ventas transferencia (neto) | Q12: =SUMIF(F4:F103,"Transferencia",M4:M103) -> 8739400
A13: Polera Cactus Jack | B13: L | C13: Tienda | D13: Benja R | E13: 31000 | F13: Transferencia | G13: =IF(OR(F13="Débito",F13="Crédito",F13="Internet(Shopify)"),E13*19/119,0) -> 0 | H13: =IF(F13="Débito",0.0275,IF(F13="Crédito",0.0295,0)) -> 0 | I13: =E13*H13 -> 0 | J13: =E13-G13-I13 -> 31000 | K13: =IF($O13<>"Tienda",0,IF(OR($F13="Débito",$F13="Crédito"),0.05,IF(OR($F13="Efectivo",$F13="Transferencia"),0.07,0))) -> 0.07 | L13: =IF($O13<>"Tienda",0,$J13*$K13) -> 2170 | M13: =E13-G13-I13-L13 -> 28830 | O13: Tienda | P13: Ventas Internet(Shopify) (neto) | Q13: =SUMIF(F4:F103,"Internet(Shopify)",M4:M103) -> 0
A14: Bayer Munchen* (Ultima 05/03) | B14: L | C14: Fabio | D14: Benja R | E14: 25000 | F14: Transferencia | G14: =IF(OR(F14="Débito",F14="Crédito",F14="Internet(Shopify)"),E14*19/119,0) -> 0 | H14: =IF(F14="Débito",0.0275,IF(F14="Crédito",0.0295,0)) -> 0 | I14: =E14*H14 -> 0 | J14: =E14-G14-I14 -> 25000 | K14: =IF($O14<>"Tienda",0,IF(OR($F14="Débito",$F14="Crédito"),0.05,IF(OR($F14="Efectivo",$F14="Transferencia"),0.07,0))) -> 0.07 | L14: =IF($O14<>"Tienda",0,$J14*$K14) -> 1750 | M14: =E14-G14-I14-L14 -> 23250 | O14: Tienda | P14: Ventas cuenta común (D+C+T) NETO | Q14: =SUMIF(F4:F103,"Débito",M4:M103)+SUMIF(F4:F103,"Crédito",M4:M103)+SUMIF(F4:F103,"Transferencia",M4:M103) -> 8866812.1
A15: pantalon season lineas | B15: S | C15: Tienda | D15: Benja R | E15: 75000 | F15: Transferencia | G15: =IF(OR(F15="Débito",F15="Crédito",F15="Internet(Shopify)"),E15*19/119,0) -> 0 | H15: =IF(F15="Débito",0.0275,IF(F15="Crédito",0.0295,0)) -> 0 | I15: =E15*H15 -> 0 | J15: =E15-G15-I15 -> 75000 | K15: =IF($O15<>"Tienda",0,IF(OR($F15="Débito",$F15="Crédito"),0.05,IF(OR($F15="Efectivo",$F15="Transferencia"),0.07,0))) -> 0 | L15: =IF($O15<>"Tienda",0,$J15*$K15) -> 0 | M15: =E15-G15-I15-L15 -> 75000 | N15: Season Archive (56.250) | O15: Season Archive | P15: IVA compras (manual)
A16: chaqueta season azul raw | B16: L | C16: Tienda | D16: Marenna | E16: 80000 | F16: Transferencia | G16: =IF(OR(F16="Débito",F16="Crédito",F16="Internet(Shopify)"),E16*19/119,0) -> 0 | H16: =IF(F16="Débito",0.0275,IF(F16="Crédito",0.0295,0)) -> 0 | I16: =E16*H16 -> 0 | J16: =E16-G16-I16 -> 80000 | K16: =IF($O16<>"Tienda",0,IF(OR($F16="Débito",$F16="Crédito"),0.05,IF(OR($F16="Efectivo",$F16="Transferencia"),0.07,0))) -> 0 | L16: =IF($O16<>"Tienda",0,$J16*$K16) -> 0 | M16: =E16-G16-I16-L16 -> 80000 | N16: Season Archive (60.000) | O16: Season Archive | P16: IVA neto (ventas - compras) | Q16: =Q3-Q15 -> 26344.538
A17: Ed Hardy Polera Blanca | B17: M | C17: Benja R | D17: Fabio | E17: 25000 | F17: Transferencia | G17: =IF(OR(F17="Débito",F17="Crédito",F17="Internet(Shopify)"),E17*19/119,0) -> 0 | H17: =IF(F17="Débito",0.0275,IF(F17="Crédito",0.0295,0)) -> 0 | I17: =E17*H17 -> 0 | J17: =E17-G17-I17 -> 25000 | K17: =IF($O17<>"Tienda",0,IF(OR($F17="Débito",$F17="Crédito"),0.05,IF(OR($F17="Efectivo",$F17="Transferencia"),0.07,0))) -> 0.07 | L17: =IF($O17<>"Tienda",0,$J17*$K17) -> 1750 | M17: =E17-G17-I17-L17 -> 23250 | O17: Tienda
A18: pantalon season | B18: M | C18: Tienda | D18: Benja R | E18: 75000 | F18: Transferencia | G18: =IF(OR(F18="Débito",F18="Crédito",F18="Internet(Shopify)"),E18*19/119,0) -> 0 | H18: =IF(F18="Débito",0.0275,IF(F18="Crédito",0.0295,0)) -> 0 | I18: =E18*H18 -> 0 | J18: =E18-G18-I18 -> 75000 | K18: =IF($O18<>"Tienda",0,IF(OR($F18="Débito",$F18="Crédito"),0.05,IF(OR($F18="Efectivo",$F18="Transferencia"),0.07,0))) -> 0 | L18: =IF($O18<>"Tienda",0,$J18*$K18) -> 0 | M18: =E18-G18-I18-L18 -> 75000 | N18: Season Archive (56.250) | O18: Season Archive
A19: PANT SEASON ARCHIVE | B19: M | C19: Tienda | D19: Benja R | E19: 75000 | F19: Transferencia | G19: =IF(OR(F19="Débito",F19="Crédito",F19="Internet(Shopify)"),E19*19/119,0) -> 0 | H19: =IF(F19="Débito",0.0275,IF(F19="Crédito",0.0295,0)) -> 0 | I19: =E19*H19 -> 0 | J19: =E19-G19-I19 -> 75000 | K19: =IF($O19<>"Tienda",0,IF(OR($F19="Débito",$F19="Crédito"),0.05,IF(OR($F19="Efectivo",$F19="Transferencia"),0.07,0))) -> 0 | L19: =IF($O19<>"Tienda",0,$J19*$K19) -> 0 | M19: =E19-G19-I19-L19 -> 75000 | N19: Season Archive (56.250) | O19: Season Archive
A20: polera yankees | C20: Aaron | D20: Benja R | E20: 35000 | F20: Transferencia | G20: =IF(OR(F20="Débito",F20="Crédito",F20="Internet(Shopify)"),E20*19/119,0) -> 0 | H20: =IF(F20="Débito",0.0275,IF(F20="Crédito",0.0295,0)) -> 0 | I20: =E20*H20 -> 0 | J20: =E20-G20-I20 -> 35000 | K20: =IF($O20<>"Tienda",0,IF(OR($F20="Débito",$F20="Crédito"),0.05,IF(OR($F20="Efectivo",$F20="Transferencia"),0.07,0))) -> 0.07 | L20: =IF($O20<>"Tienda",0,$J20*$K20) -> 2450 | M20: =E20-G20-I20-L20 -> 32550 | N20: michelle | O20: Tienda
A21: traje de perro | B21: OS | C21: Tienda | D21: Benja R | E21: 40000 | F21: Transferencia | G21: =IF(OR(F21="Débito",F21="Crédito",F21="Internet(Shopify)"),E21*19/119,0) -> 0 | H21: =IF(F21="Débito",0.0275,IF(F21="Crédito",0.0295,0)) -> 0 | I21: =E21*H21 -> 0 | J21: =E21-G21-I21 -> 40000 | K21: =IF($O21<>"Tienda",0,IF(OR($F21="Débito",$F21="Crédito"),0.05,IF(OR($F21="Efectivo",$F21="Transferencia"),0.07,0))) -> 0.07 | L21: =IF($O21<>"Tienda",0,$J21*$K21) -> 2800 | M21: =E21-G21-I21-L21 -> 37200 | N21: michelle | O21: Tienda
A22: polera Burberry | B22: S | C22: Benja R | D22: Benja R | E22: 17000 | F22: Transferencia | G22: =IF(OR(F22="Débito",F22="Crédito",F22="Internet(Shopify)"),E22*19/119,0) -> 0 | H22: =IF(F22="Débito",0.0275,IF(F22="Crédito",0.0295,0)) -> 0 | I22: =E22*H22 -> 0 | J22: =E22-G22-I22 -> 17000 | K22: =IF($O22<>"Tienda",0,IF(OR($F22="Débito",$F22="Crédito"),0.05,IF(OR($F22="Efectivo",$F22="Transferencia"),0.07,0))) -> 0.07 | L22: =IF($O22<>"Tienda",0,$J22*$K22) -> 1190 | M22: =E22-G22-I22-L22 -> 15810 | N22: michelle | O22: Tienda
A23: botas ugg | B23: 39 | C23: Benja R | D23: Benja R | E23: 250000 | F23: Transferencia | G23: =IF(OR(F23="Débito",F23="Crédito",F23="Internet(Shopify)"),E23*19/119,0) -> 0 | H23: =IF(F23="Débito",0.0275,IF(F23="Crédito",0.0295,0)) -> 0 | I23: =E23*H23 -> 0 | J23: =E23-G23-I23 -> 250000 | K23: =IF($O23<>"Tienda",0,IF(OR($F23="Débito",$F23="Crédito"),0.05,IF(OR($F23="Efectivo",$F23="Transferencia"),0.07,0))) -> 0.07 | L23: =IF($O23<>"Tienda",0,$J23*$K23) -> 17500 | M23: =E23-G23-I23-L23 -> 232500 | O23: Tienda
A24: bolso LV | B24: os | C24: Consignacion | D24: Benja R | E24: 700000 | F24: Transferencia | G24: =IF(OR(F24="Débito",F24="Crédito",F24="Internet(Shopify)"),E24*19/119,0) -> 0 | H24: =IF(F24="Débito",0.0275,IF(F24="Crédito",0.0295,0)) -> 0 | I24: =E24*H24 -> 0 | J24: =E24-G24-I24 -> 700000 | K24: =IF($O24<>"Tienda",0,IF(OR($F24="Débito",$F24="Crédito"),0.05,IF(OR($F24="Efectivo",$F24="Transferencia"),0.07,0))) -> 0.07 | L24: =IF($O24<>"Tienda",0,$J24*$K24) -> 49000 | M24: =E24-G24-I24-L24 -> 651000 | N24: pagar 350.000 | O24: Tienda
A25: chaqueta season mujer negra | B25: m | C25: Tienda | D25: Benja R | E25: 80000 | F25: Transferencia | G25: =IF(OR(F25="Débito",F25="Crédito",F25="Internet(Shopify)"),E25*19/119,0) -> 0 | H25: =IF(F25="Débito",0.0275,IF(F25="Crédito",0.0295,0)) -> 0 | I25: =E25*H25 -> 0 | J25: =E25-G25-I25 -> 80000 | K25: =IF($O25<>"Tienda",0,IF(OR($F25="Débito",$F25="Crédito"),0.05,IF(OR($F25="Efectivo",$F25="Transferencia"),0.07,0))) -> 0 | L25: =IF($O25<>"Tienda",0,$J25*$K25) -> 0 | M25: =E25-G25-I25-L25 -> 80000 | N25: Season Archive (60.000) | O25: Season Archive
A26: polera pedritos roja pedidos | B26: baby s | C26: Tienda | D26: Fabio | E26: 25000 | F26: Transferencia | G26: =IF(OR(F26="Débito",F26="Crédito",F26="Internet(Shopify)"),E26*19/119,0) -> 0 | H26: =IF(F26="Débito",0.0275,IF(F26="Crédito",0.0295,0)) -> 0 | I26: =E26*H26 -> 0 | J26: =E26-G26-I26 -> 25000 | K26: =IF($O26<>"Tienda",0,IF(OR($F26="Débito",$F26="Crédito"),0.05,IF(OR($F26="Efectivo",$F26="Transferencia"),0.07,0))) -> 0 | L26: =IF($O26<>"Tienda",0,$J26*$K26) -> 0 | M26: =E26-G26-I26-L26 -> 25000 | N26: pedritos(18.750) | O26: Pedritos
A27: pantalon season cuadrille | B27: M | C27: Tienda | D27: Fabio | E27: 75000 | F27: Transferencia | G27: =IF(OR(F27="Débito",F27="Crédito",F27="Internet(Shopify)"),E27*19/119,0) -> 0 | H27: =IF(F27="Débito",0.0275,IF(F27="Crédito",0.0295,0)) -> 0 | I27: =E27*H27 -> 0 | J27: =E27-G27-I27 -> 75000 | K27: =IF($O27<>"Tienda",0,IF(OR($F27="Débito",$F27="Crédito"),0.05,IF(OR($F27="Efectivo",$F27="Transferencia"),0.07,0))) -> 0 | L27: =IF($O27<>"Tienda",0,$J27*$K27) -> 0 | M27: =E27-G27-I27-L27 -> 75000 | N27: season Archive (60.000) | O27: Season Archive
A28: polera pedritos negra | B28: bby S | C28: Tienda | D28: Benja R | E28: 25000 | F28: Transferencia | G28: =IF(OR(F28="Débito",F28="Crédito",F28="Internet(Shopify)"),E28*19/119,0) -> 0 | H28: =IF(F28="Débito",0.0275,IF(F28="Crédito",0.0295,0)) -> 0 | I28: =E28*H28 -> 0 | J28: =E28-G28-I28 -> 25000 | K28: =IF($O28<>"Tienda",0,IF(OR($F28="Débito",$F28="Crédito"),0.05,IF(OR($F28="Efectivo",$F28="Transferencia"),0.07,0))) -> 0 | L28: =IF($O28<>"Tienda",0,$J28*$K28) -> 0 | M28: =E28-G28-I28-L28 -> 25000 | N28: pedritos(18.750) | O28: Pedritos
A29: polera patos | B29: s | C29: Fabio | D29: Benja R | E29: 25000 | F29: Transferencia | G29: =IF(OR(F29="Débito",F29="Crédito",F29="Internet(Shopify)"),E29*19/119,0) -> 0 | H29: =IF(F29="Débito",0.0275,IF(F29="Crédito",0.0295,0)) -> 0 | I29: =E29*H29 -> 0 | J29: =E29-G29-I29 -> 25000 | K29: =IF($O29<>"Tienda",0,IF(OR($F29="Débito",$F29="Crédito"),0.05,IF(OR($F29="Efectivo",$F29="Transferencia"),0.07,0))) -> 0.07 | L29: =IF($O29<>"Tienda",0,$J29*$K29) -> 1750 | M29: =E29-G29-I29-L29 -> 23250 | O29: Tienda
A30: polera season palomas | B30: S | C30: Tienda | D30: Benja R | E30: 25000 | F30: Transferencia | G30: =IF(OR(F30="Débito",F30="Crédito",F30="Internet(Shopify)"),E30*19/119,0) -> 0 | H30: =IF(F30="Débito",0.0275,IF(F30="Crédito",0.0295,0)) -> 0 | I30: =E30*H30 -> 0 | J30: =E30-G30-I30 -> 25000 | K30: =IF($O30<>"Tienda",0,IF(OR($F30="Débito",$F30="Crédito"),0.05,IF(OR($F30="Efectivo",$F30="Transferencia"),0.07,0))) -> 0 | L30: =IF($O30<>"Tienda",0,$J30*$K30) -> 0 | M30: =E30-G30-I30-L30 -> 25000 | N30: pop disaster(18.750) | O30: Pop disaster
A31: lentes prada | B31: os | C31: Fabio | D31: Benja R | E31: 45000 | F31: Transferencia | N31: michelle | O31: Tienda
A32: pantalon season cuadrille | B32: S | C32: Tienda | D32: Benja R | E32: 75000 | F32: Transferencia | G32: =IF(OR(F32="Débito",F32="Crédito",F32="Internet(Shopify)"),E32*19/119,0) -> 0 | H32: =IF(F32="Débito",0.0275,IF(F32="Crédito",0.0295,0)) -> 0 | I32: =E32*H32 -> 0 | J32: =E32-G32-I32 -> 75000 | K32: =IF($O32<>"Tienda",0,IF(OR($F32="Débito",$F32="Crédito"),0.05,IF(OR($F32="Efectivo",$F32="Transferencia"),0.07,0))) -> 0 | L32: =IF($O32<>"Tienda",0,$J32*$K32) -> 0 | M32: =E32-G32-I32-L32 -> 75000 | N32: season archive (56.250) | O32: Season Archive
A33: lentes prada | B33: os | C33: Benja R | D33: Benja R | E33: 100000 | F33: Transferencia | G33: =IF(OR(F33="Débito",F33="Crédito",F33="Internet(Shopify)"),E33*19/119,0) -> 0 | H33: =IF(F33="Débito",0.0275,IF(F33="Crédito",0.0295,0)) -> 0 | I33: =E33*H33 -> 0 | J33: =E33-G33-I33 -> 100000 | K33: =IF($O33<>"Tienda",0,IF(OR($F33="Débito",$F33="Crédito"),0.05,IF(OR($F33="Efectivo",$F33="Transferencia"),0.07,0))) -> 0.07 | L33: =IF($O33<>"Tienda",0,$J33*$K33) -> 7000 | M33: =E33-G33-I33-L33 -> 93000 | O33: Tienda
A34: cartera Chanel | B34: os | C34: Tienda | D34: Benja R | E34: 1500000 | F34: Transferencia | G34: =IF(OR(F34="Débito",F34="Crédito",F34="Internet(Shopify)"),E34*19/119,0) -> 0 | H34: =IF(F34="Débito",0.0275,IF(F34="Crédito",0.0295,0)) -> 0 | I34: =E34*H34 -> 0 | J34: =E34-G34-I34 -> 1500000 | K34: =IF($O34<>"Tienda",0,IF(OR($F34="Débito",$F34="Crédito"),0.05,IF(OR($F34="Efectivo",$F34="Transferencia"),0.07,0))) -> 0.07 | L34: =IF($O34<>"Tienda",0,$J34*$K34) -> 105000 | M34: =E34-G34-I34-L34 -> 1395000 | N34: michelle | O34: Tienda
A35: chaqueta season | B35: L | C35: Tienda | D35: Benja R | E35: 80000 | F35: Transferencia | G35: =IF(OR(F35="Débito",F35="Crédito",F35="Internet(Shopify)"),E35*19/119,0) -> 0 | H35: =IF(F35="Débito",0.0275,IF(F35="Crédito",0.0295,0)) -> 0 | I35: =E35*H35 -> 0 | J35: =E35-G35-I35 -> 80000 | K35: =IF($O35<>"Tienda",0,IF(OR($F35="Débito",$F35="Crédito"),0.05,IF(OR($F35="Efectivo",$F35="Transferencia"),0.07,0))) -> 0 | L35: =IF($O35<>"Tienda",0,$J35*$K35) -> 0 | M35: =E35-G35-I35-L35 -> 80000 | N35: season archive (60.000) | O35: Season Archive
A36: pantalon season cuadrille | B36: S | C36: Tienda | D36: Benja R | E36: 75000 | F36: Transferencia | G36: =IF(OR(F36="Débito",F36="Crédito",F36="Internet(Shopify)"),E36*19/119,0) -> 0 | H36: =IF(F36="Débito",0.0275,IF(F36="Crédito",0.0295,0)) -> 0 | I36: =E36*H36 -> 0 | J36: =E36-G36-I36 -> 75000 | K36: =IF($O36<>"Tienda",0,IF(OR($F36="Débito",$F36="Crédito"),0.05,IF(OR($F36="Efectivo",$F36="Transferencia"),0.07,0))) -> 0 | L36: =IF($O36<>"Tienda",0,$J36*$K36) -> 0 | M36: =E36-G36-I36-L36 -> 75000 | N36: season archive (56.250) | O36: Season Archive
A37: balerina vw | B37: 38 | C37: Tienda | D37: Benja R | E37: 50000 | F37: Transferencia | G37: =IF(OR(F37="Débito",F37="Crédito",F37="Internet(Shopify)"),E37*19/119,0) -> 0 | H37: =IF(F37="Débito",0.0275,IF(F37="Crédito",0.0295,0)) -> 0 | I37: =E37*H37 -> 0 | J37: =E37-G37-I37 -> 50000 | K37: =IF($O37<>"Tienda",0,IF(OR($F37="Débito",$F37="Crédito"),0.05,IF(OR($F37="Efectivo",$F37="Transferencia"),0.07,0))) -> 0.07 | L37: =IF($O37<>"Tienda",0,$J37*$K37) -> 3500 | M37: =E37-G37-I37-L37 -> 46500 | O37: Tienda
A38: polera Le sang | B38: L | C38: Tienda | D38: Benja R | E38: 20000 | F38: Transferencia | G38: =IF(OR(F38="Débito",F38="Crédito",F38="Internet(Shopify)"),E38*19/119,0) -> 0 | H38: =IF(F38="Débito",0.0275,IF(F38="Crédito",0.0295,0)) -> 0 | I38: =E38*H38 -> 0 | J38: =E38-G38-I38 -> 20000 | K38: =IF($O38<>"Tienda",0,IF(OR($F38="Débito",$F38="Crédito"),0.05,IF(OR($F38="Efectivo",$F38="Transferencia"),0.07,0))) -> 0.07 | L38: =IF($O38<>"Tienda",0,$J38*$K38) -> 1400 | M38: =E38-G38-I38-L38 -> 18600 | O38: Tienda
A39: chaqueta azul | B39: M | C39: Tienda | D39: Benja R | E39: 80000 | F39: Transferencia | G39: =IF(OR(F39="Débito",F39="Crédito",F39="Internet(Shopify)"),E39*19/119,0) -> 0 | H39: =IF(F39="Débito",0.0275,IF(F39="Crédito",0.0295,0)) -> 0 | I39: =E39*H39 -> 0 | J39: =E39-G39-I39 -> 80000 | K39: =IF($O39<>"Tienda",0,IF(OR($F39="Débito",$F39="Crédito"),0.05,IF(OR($F39="Efectivo",$F39="Transferencia"),0.07,0))) -> 0 | L39: =IF($O39<>"Tienda",0,$J39*$K39) -> 0 | M39: =E39-G39-I39-L39 -> 80000 | N39: season archive (60.000) | O39: Season Archive
A40: chaqueta season | B40: S | C40: Tienda | D40: Benja R | E40: 80000 | F40: Transferencia | G40: =IF(OR(F40="Débito",F40="Crédito",F40="Internet(Shopify)"),E40*19/119,0) -> 0 | H40: =IF(F40="Débito",0.0275,IF(F40="Crédito",0.0295,0)) -> 0 | I40: =E40*H40 -> 0 | J40: =E40-G40-I40 -> 80000 | K40: =IF($O40<>"Tienda",0,IF(OR($F40="Débito",$F40="Crédito"),0.05,IF(OR($F40="Efectivo",$F40="Transferencia"),0.07,0))) -> 0 | L40: =IF($O40<>"Tienda",0,$J40*$K40) -> 0 | M40: =E40-G40-I40-L40 -> 80000 | N40: season archive (60.000) | O40: Season Archive
A41: chaqueta negra | B41: L | C41: Tienda | D41: Benja R | E41: 80000 | F41: Transferencia | G41: =IF(OR(F41="Débito",F41="Crédito",F41="Internet(Shopify)"),E41*19/119,0) -> 0 | H41: =IF(F41="Débito",0.0275,IF(F41="Crédito",0.0295,0)) -> 0 | I41: =E41*H41 -> 0 | J41: =E41-G41-I41 -> 80000 | K41: =IF($O41<>"Tienda",0,IF(OR($F41="Débito",$F41="Crédito"),0.05,IF(OR($F41="Efectivo",$F41="Transferencia"),0.07,0))) -> 0 | L41: =IF($O41<>"Tienda",0,$J41*$K41) -> 0 | M41: =E41-G41-I41-L41 -> 80000 | N41: season archive (60.000) | O41: Season Archive
A42: polera CP company | B42: L | C42: Benja R | D42: Benja R | E42: 45000 | F42: Transferencia | G42: =IF(OR(F42="Débito",F42="Crédito",F42="Internet(Shopify)"),E42*19/119,0) -> 0 | H42: =IF(F42="Débito",0.0275,IF(F42="Crédito",0.0295,0)) -> 0 | I42: =E42*H42 -> 0 | J42: =E42-G42-I42 -> 45000 | K42: =IF($O42<>"Tienda",0,IF(OR($F42="Débito",$F42="Crédito"),0.05,IF(OR($F42="Efectivo",$F42="Transferencia"),0.07,0))) -> 0.07 | L42: =IF($O42<>"Tienda",0,$J42*$K42) -> 3150 | M42: =E42-G42-I42-L42 -> 41850 | O42: Tienda
A43: lentes prada | B43: os | G43: =IF(OR(F43="Débito",F43="Crédito",F43="Internet(Shopify)"),E43*19/119,0) -> 0 | H43: =IF(F43="Débito",0.0275,IF(F43="Crédito",0.0295,0)) -> 0 | I43: =E43*H43 -> 0 | J43: =E43-G43-I43 -> 0 | K43: =IF($O43<>"Tienda",0,IF(OR($F43="Débito",$F43="Crédito"),0.05,IF(OR($F43="Efectivo",$F43="Transferencia"),0.07,0))) -> 0 | L43: =IF($O43<>"Tienda",0,$J43*$K43) -> 0 | M43: =E43-G43-I43-L43 -> 0
A44: lentes prada | B44: os | C44: Tienda | D44: Benja R | E44: 200000 | F44: Transferencia | G44: =IF(OR(F44="Débito",F44="Crédito",F44="Internet(Shopify)"),E44*19/119,0) -> 0 | H44: =IF(F44="Débito",0.0275,IF(F44="Crédito",0.0295,0)) -> 0 | I44: =E44*H44 -> 0 | J44: =E44-G44-I44 -> 200000 | K44: =IF($O44<>"Tienda",0,IF(OR($F44="Débito",$F44="Crédito"),0.05,IF(OR($F44="Efectivo",$F44="Transferencia"),0.07,0))) -> 0.07 | L44: =IF($O44<>"Tienda",0,$J44*$K44) -> 14000 | M44: =E44-G44-I44-L44 -> 186000 | N44: a pagar 100.000 | O44: Tienda
A45: chaqueta season hombre | B45: M | C45: Tienda | D45: Fabio | E45: 80000 | F45: Transferencia | G45: =IF(OR(F45="Débito",F45="Crédito",F45="Internet(Shopify)"),E45*19/119,0) -> 0 | H45: =IF(F45="Débito",0.0275,IF(F45="Crédito",0.0295,0)) -> 0 | I45: =E45*H45 -> 0 | J45: =E45-G45-I45 -> 80000 | K45: =IF($O45<>"Tienda",0,IF(OR($F45="Débito",$F45="Crédito"),0.05,IF(OR($F45="Efectivo",$F45="Transferencia"),0.07,0))) -> 0 | L45: =IF($O45<>"Tienda",0,$J45*$K45) -> 0 | M45: =E45-G45-I45-L45 -> 80000 | N45: season archive(60.000) | O45: Season Archive
A46: polera le sang | B46: L | C46: Tienda | D46: Fabio | E46: 20000 | F46: Transferencia | G46: =IF(OR(F46="Débito",F46="Crédito",F46="Internet(Shopify)"),E46*19/119,0) -> 0 | H46: =IF(F46="Débito",0.0275,IF(F46="Crédito",0.0295,0)) -> 0 | I46: =E46*H46 -> 0 | J46: =E46-G46-I46 -> 20000 | K46: =IF($O46<>"Tienda",0,IF(OR($F46="Débito",$F46="Crédito"),0.05,IF(OR($F46="Efectivo",$F46="Transferencia"),0.07,0))) -> 0.07 | L46: =IF($O46<>"Tienda",0,$J46*$K46) -> 1400 | M46: =E46-G46-I46-L46 -> 18600 | O46: Tienda
A47: polera vultures | B47: L | C47: Aaron | D47: Fabio | E47: 80000 | F47: Transferencia | G47: =IF(OR(F47="Débito",F47="Crédito",F47="Internet(Shopify)"),E47*19/119,0) -> 0 | H47: =IF(F47="Débito",0.0275,IF(F47="Crédito",0.0295,0)) -> 0 | I47: =E47*H47 -> 0 | J47: =E47-G47-I47 -> 80000 | K47: =IF($O47<>"Tienda",0,IF(OR($F47="Débito",$F47="Crédito"),0.05,IF(OR($F47="Efectivo",$F47="Transferencia"),0.07,0))) -> 0.07 | L47: =IF($O47<>"Tienda",0,$J47*$K47) -> 5600 | M47: =E47-G47-I47-L47 -> 74400 | O47: Tienda
A48: Malla Jean paul gaultier | B48: S | C48: Tienda | D48: Benja R | E48: 170000 | F48: Transferencia | G48: =IF(OR(F48="Débito",F48="Crédito",F48="Internet(Shopify)"),E48*19/119,0) -> 0 | H48: =IF(F48="Débito",0.0275,IF(F48="Crédito",0.0295,0)) -> 0 | I48: =E48*H48 -> 0 | J48: =E48-G48-I48 -> 170000 | K48: =IF($O48<>"Tienda",0,IF(OR($F48="Débito",$F48="Crédito"),0.05,IF(OR($F48="Efectivo",$F48="Transferencia"),0.07,0))) -> 0.07 | L48: =IF($O48<>"Tienda",0,$J48*$K48) -> 11900 | M48: =E48-G48-I48-L48 -> 158100 | N48: Marena descuenta sueldo | O48: Tienda
A49: polera season | B49: L | C49: Tienda | D49: Benja R | E49: 20000 | F49: Transferencia | G49: =IF(OR(F49="Débito",F49="Crédito",F49="Internet(Shopify)"),E49*19/119,0) -> 0 | H49: =IF(F49="Débito",0.0275,IF(F49="Crédito",0.0295,0)) -> 0 | I49: =E49*H49 -> 0 | J49: =E49-G49-I49 -> 20000 | K49: =IF($O49<>"Tienda",0,IF(OR($F49="Débito",$F49="Crédito"),0.05,IF(OR($F49="Efectivo",$F49="Transferencia"),0.07,0))) -> 0 | L49: =IF($O49<>"Tienda",0,$J49*$K49) -> 0 | M49: =E49-G49-I49-L49 -> 20000 | N49: Season Archive (15.000) | O49: Season Archive
A50: polera noob destroyer | B50: L | C50: Tienda | D50: Benja R | E50: 25000 | F50: Transferencia | G50: =IF(OR(F50="Débito",F50="Crédito",F50="Internet(Shopify)"),E50*19/119,0) -> 0 | H50: =IF(F50="Débito",0.0275,IF(F50="Crédito",0.0295,0)) -> 0 | I50: =E50*H50 -> 0 | J50: =E50-G50-I50 -> 25000 | K50: =IF($O50<>"Tienda",0,IF(OR($F50="Débito",$F50="Crédito"),0.05,IF(OR($F50="Efectivo",$F50="Transferencia"),0.07,0))) -> 0.07 | L50: =IF($O50<>"Tienda",0,$J50*$K50) -> 1750 | M50: =E50-G50-I50-L50 -> 23250 | O50: Tienda
A51: camiseta seleccion nacional | B51: M | C51: Fabio | D51: Benja R | E51: 25000 | F51: Débito | G51: =IF(OR(F51="Débito",F51="Crédito",F51="Internet(Shopify)"),E51*19/119,0) -> 3991.5966 | H51: =IF(F51="Débito",0.0275,IF(F51="Crédito",0.0295,0)) -> 0.0275 | I51: =E51*H51 -> 687.5 | J51: =E51-G51-I51 -> 20320.903 | K51: =IF($O51<>"Tienda",0,IF(OR($F51="Débito",$F51="Crédito"),0.05,IF(OR($F51="Efectivo",$F51="Transferencia"),0.07,0))) -> 0.05 | L51: =IF($O51<>"Tienda",0,$J51*$K51) -> 1016.0452 | M51: =E51-G51-I51-L51 -> 19304.858 | O51: Tienda
A52: chaqueta JPG | B52: M | C52: Tienda | D52: Benja R | E52: 215000 | F52: Transferencia | G52: =IF(OR(F52="Débito",F52="Crédito",F52="Internet(Shopify)"),E52*19/119,0) -> 0 | H52: =IF(F52="Débito",0.0275,IF(F52="Crédito",0.0295,0)) -> 0 | I52: =E52*H52 -> 0 | J52: =E52-G52-I52 -> 215000 | K52: =IF($O52<>"Tienda",0,IF(OR($F52="Débito",$F52="Crédito"),0.05,IF(OR($F52="Efectivo",$F52="Transferencia"),0.07,0))) -> 0.07 | L52: =IF($O52<>"Tienda",0,$J52*$K52) -> 15050 | M52: =E52-G52-I52-L52 -> 199950 | N52: consignacion 120.000 | O52: Tienda
A53: polera season ornamento | B53: M | C53: Tienda | D53: Benja R | E53: 20000 | F53: Efectivo | G53: =IF(OR(F53="Débito",F53="Crédito",F53="Internet(Shopify)"),E53*19/119,0) -> 0 | H53: =IF(F53="Débito",0.0275,IF(F53="Crédito",0.0295,0)) -> 0 | I53: =E53*H53 -> 0 | J53: =E53-G53-I53 -> 20000 | K53: =IF($O53<>"Tienda",0,IF(OR($F53="Débito",$F53="Crédito"),0.05,IF(OR($F53="Efectivo",$F53="Transferencia"),0.07,0))) -> 0 | L53: =IF($O53<>"Tienda",0,$J53*$K53) -> 0 | M53: =E53-G53-I53-L53 -> 20000 | N53: Season Archive (15.000) | O53: Season Archive
A54: chaqueta season hombre | B54: S | C54: Tienda | D54: Benja R | E54: 80000 | F54: Transferencia | G54: =IF(OR(F54="Débito",F54="Crédito",F54="Internet(Shopify)"),E54*19/119,0) -> 0 | H54: =IF(F54="Débito",0.0275,IF(F54="Crédito",0.0295,0)) -> 0 | I54: =E54*H54 -> 0 | J54: =E54-G54-I54 -> 80000 | K54: =IF($O54<>"Tienda",0,IF(OR($F54="Débito",$F54="Crédito"),0.05,IF(OR($F54="Efectivo",$F54="Transferencia"),0.07,0))) -> 0 | L54: =IF($O54<>"Tienda",0,$J54*$K54) -> 0 | M54: =E54-G54-I54-L54 -> 80000 | N54: Season Archive (60.000) | O54: Season Archive
A55: pulsera plata | B55: os | C55: Fabio | D55: Fabio | E55: 25000 | F55: Transferencia | G55: =IF(OR(F55="Débito",F55="Crédito",F55="Internet(Shopify)"),E55*19/119,0) -> 0 | H55: =IF(F55="Débito",0.0275,IF(F55="Crédito",0.0295,0)) -> 0 | I55: =E55*H55 -> 0 | J55: =E55-G55-I55 -> 25000 | K55: =IF($O55<>"Tienda",0,IF(OR($F55="Débito",$F55="Crédito"),0.05,IF(OR($F55="Efectivo",$F55="Transferencia"),0.07,0))) -> 0.07 | L55: =IF($O55<>"Tienda",0,$J55*$K55) -> 1750 | M55: =E55-G55-I55-L55 -> 23250 | O55: Tienda
A56: pulser plata | B56: os | C56: Fabio | D56: Benja R | E56: 30000 | F56: Transferencia | G56: =IF(OR(F56="Débito",F56="Crédito",F56="Internet(Shopify)"),E56*19/119,0) -> 0 | H56: =IF(F56="Débito",0.0275,IF(F56="Crédito",0.0295,0)) -> 0 | I56: =E56*H56 -> 0 | J56: =E56-G56-I56 -> 30000 | K56: =IF($O56<>"Tienda",0,IF(OR($F56="Débito",$F56="Crédito"),0.05,IF(OR($F56="Efectivo",$F56="Transferencia"),0.07,0))) -> 0.07 | L56: =IF($O56<>"Tienda",0,$J56*$K56) -> 2100 | M56: =E56-G56-I56-L56 -> 27900 | O56: Tienda
A57: polera le sang | B57: M | C57: Tienda | D57: Fabio | E57: 20000 | F57: Transferencia | G57: =IF(OR(F57="Débito",F57="Crédito",F57="Internet(Shopify)"),E57*19/119,0) -> 0 | H57: =IF(F57="Débito",0.0275,IF(F57="Crédito",0.0295,0)) -> 0 | I57: =E57*H57 -> 0 | J57: =E57-G57-I57 -> 20000 | K57: =IF($O57<>"Tienda",0,IF(OR($F57="Débito",$F57="Crédito"),0.05,IF(OR($F57="Efectivo",$F57="Transferencia"),0.07,0))) -> 0.07 | L57: =IF($O57<>"Tienda",0,$J57*$K57) -> 1400 | M57: =E57-G57-I57-L57 -> 18600 | O57: Tienda
A58: chaqueta jpg negra | B58: M | C58: Tienda | D58: Benja R | E58: 200000 | F58: Transferencia | G58: =IF(OR(F58="Débito",F58="Crédito",F58="Internet(Shopify)"),E58*19/119,0) -> 0 | H58: =IF(F58="Débito",0.0275,IF(F58="Crédito",0.0295,0)) -> 0 | I58: =E58*H58 -> 0 | J58: =E58-G58-I58 -> 200000 | K58: =IF($O58<>"Tienda",0,IF(OR($F58="Débito",$F58="Crédito"),0.05,IF(OR($F58="Efectivo",$F58="Transferencia"),0.07,0))) -> 0.07 | L58: =IF($O58<>"Tienda",0,$J58*$K58) -> 14000 | M58: =E58-G58-I58-L58 -> 186000 | O58: Tienda
A59: pantalon flare | B59: S | C59: Tienda | D59: Benja R | E59: 65000 | F59: Transferencia | G59: =IF(OR(F59="Débito",F59="Crédito",F59="Internet(Shopify)"),E59*19/119,0) -> 0 | H59: =IF(F59="Débito",0.0275,IF(F59="Crédito",0.0295,0)) -> 0 | I59: =E59*H59 -> 0 | J59: =E59-G59-I59 -> 65000 | K59: =IF($O59<>"Tienda",0,IF(OR($F59="Débito",$F59="Crédito"),0.05,IF(OR($F59="Efectivo",$F59="Transferencia"),0.07,0))) -> 0 | L59: =IF($O59<>"Tienda",0,$J59*$K59) -> 0 | M59: =E59-G59-I59-L59 -> 65000 | N59: season Archive (48.750) | O59: Season Archive
A60: chaqueta hombre | B60: L | C60: Tienda | D60: Benja R | E60: 80000 | F60: Transferencia | G60: =IF(OR(F60="Débito",F60="Crédito",F60="Internet(Shopify)"),E60*19/119,0) -> 0 | H60: =IF(F60="Débito",0.0275,IF(F60="Crédito",0.0295,0)) -> 0 | I60: =E60*H60 -> 0 | J60: =E60-G60-I60 -> 80000 | K60: =IF($O60<>"Tienda",0,IF(OR($F60="Débito",$F60="Crédito"),0.05,IF(OR($F60="Efectivo",$F60="Transferencia"),0.07,0))) -> 0 | L60: =IF($O60<>"Tienda",0,$J60*$K60) -> 0 | M60: =E60-G60-I60-L60 -> 80000 | N60: Season Archive (60.000) | O60: Season Archive
A61: pantalon hombre lienas | B61: L | C61: Tienda | D61: Benja R | E61: 70000 | F61: Transferencia | G61: =IF(OR(F61="Débito",F61="Crédito",F61="Internet(Shopify)"),E61*19/119,0) -> 0 | H61: =IF(F61="Débito",0.0275,IF(F61="Crédito",0.0295,0)) -> 0 | I61: =E61*H61 -> 0 | J61: =E61-G61-I61 -> 70000 | K61: =IF($O61<>"Tienda",0,IF(OR($F61="Débito",$F61="Crédito"),0.05,IF(OR($F61="Efectivo",$F61="Transferencia"),0.07,0))) -> 0 | L61: =IF($O61<>"Tienda",0,$J61*$K61) -> 0 | M61: =E61-G61-I61-L61 -> 70000 | N61: Season Archive (53.500) | O61: Season Archive
